Workbook

Sheet Life Cycle Testing
B1: Year | C1: Operating Cash Margin | D1: Operating Cash Margin(3 year Sum) | E1: (Invested)/generated from Net Working Assets | F1: (Invested)/generated from Net Working Assets (3 Year) | G1: Total Sources of cash flow for 3 years | H1: 3 Year Operating Cash Margin and Invested / Generated from Net working capital / 3 Year Total Sources of Cash Flow | I1: Revenue | J1: Five year Revenue CAGR | K1: Three year Revenue CAGR | L1: GDP | M1: Three year GDP CAGR | N1: 5 year GDP CAGR | O1: GDP Multiplier * Three year GDP CAGR | P1: Revenue Available for Less than 3 Financial Years | Q1: 3 Year Revenue CAGR Less than equal to 3 Year CAGR GDP | R1: 3 Year Revenue CAGR More than equal to 3 Year CAGR GDP But Less than equal to Multiplier time 3 Years CAGR GDP | S1: 3 Year Operating Cash Margin and Invested / Generated from Net working capital less than 30% of 3 Year Total Sources of Cash Flow | T1: 3 Year Revenue CAGR greater than equal to Multiplier Time Revenue Multiple CAGR of 3 Year Nominal GDP | U1: AND 3 Year Operating Cash Margin and Invested/ Generated from Net working capitalmore than 30% of Total Sources of Cash Flow If fails, Mark to Early Stage | V1: 3 Year Revenue CAGR is Less than equal to 5 Year Revenue CAGR | W1: 3 Year Revenue CAGR is Greater than equal to 5 Year Revenue CAGR | X1: High Growth Company | Y1: Early Stage | Z1: Low To Moderate | AA1: Attempt To Revival | AB1: Decline | AC1: Number of Years | AD1: Final Result | AE1: Frontend Displays
A2: Microsoft Corporation | B2: FY 2000 | C2: 15.426 | E2: -3.2 | I2: 22.956 | J2: -% | K2: - | L2: 10250.952 | M2: - | N2: - | O2: - | P2: 1 | AC2: =COUNT($I$2:I2) -> 1 | AD2: =IF(AC2<4,"Recently Listed",IF(X2=1,"High Growth",IF(Y2=1,"Early Stage",IF(Z2=1,"Low To Moderate",IF(AA2=1,"Attempt to Rivival",IF(AB2=1,"Decline","Undetermined")))))) -> Recently Listed
A3: Microsoft Corporation | B3: FY 2001 | C3: 15.025 | E3: -0.303 | I3: 25.296 | J3: -% | K3: - | L3: 10581.929 | M3: - | N3: - | O3: - | P3: 1 | AC3: =COUNT($I$2:I3) -> 2 | AD3: =IF(AC3<4,"Recently Listed",IF(X3=1,"High Growth",IF(Y3=1,"Early Stage",IF(Z3=1,"Low To Moderate",IF(AA3=1,"Attempt to Rivival",IF(AB3=1,"Decline","Undetermined")))))) -> Recently Listed
A4: Microsoft Corporation | B4: FY 2002 | C4: 16.64 | D4: =SUM(C2:C4) -> 47.091 | E4: -0.231 | F4: =SUM(E2:E4) -> -3.734 | G4: 49.05 | H4: =(D4+F4)/G4*100 -> 88.393476 | I4: 28.365 | J4: -% | K4: - | L4: 10929.108 | M4: - | N4: - | O4: - | P4: 1 | Q4: =IF(OR(K4="",M4="",K4="-",M4="-"),0,IF(K4<=M4,1,0)) -> 0 | R4: =IF(OR(K4="",M4="",O4="",K4="-",M4="-",O4="-"),0,IF(AND(K4>=M4,K4<=O4),1,0)) -> 0 | S4: =IF(OR(H4="",H4="-"),0,IF(H4<30,1,0)) -> 0 | T4: =IF(OR(K4="",O4="",K4="-",O4="-"),0,IF(K4>=O4,1,0)) -> 0 | U4: =IF(OR(H4="",H4="-"),0,IF(H4>30,1,0)) -> 1 | V4: =IF(OR(K4="",J4="",K4="-",J4="-"),0,IF(K4<=J4,1,0)) -> 0 | W4: =IF(OR(K4="",J4="",K4="-",J4="-"),0,IF(K4>=J4,1,0)) -> 0 | AC4: =COUNT($I$2:I4) -> 3 | AD4: =IF(AC4<4,"Recently Listed",IF(X4=1,"High Growth",IF(Y4=1,"Early Stage",IF(Z4=1,"Low To Moderate",IF(AA4=1,"Attempt to Rivival",IF(AB4=1,"Decline","Undetermined")))))) -> Recently Listed
A5: Microsoft Corporation | B5: FY 2003 | C5: 17.097 | D5: =SUM(C3:C5) -> 48.762 | E5: 1.5 | F5: =SUM(E3:E5) -> 0.966 | G5: 49.963 | H5: =(D5+F5)/G5*100 -> 99.529652 | I5: 32.187 | J5: -% | K5: =(I5/I2)^(1/3)-1 -> 0.11925256 | L5: 11456.45 | M5: =(L5/L2)^(1/3)-1 -> 0.037756084 | O5: =M5*1.3 -> 0.049082909 | P5: 0 | Q5: =IF(OR(K5="",M5="",K5="-",M5="-"),0,IF(K5<=M5,1,0)) -> 0 | R5: =IF(OR(K5="",M5="",O5="",K5="-",M5="-",O5="-"),0,IF(AND(K5>=M5,K5<=O5),1,0)) -> 0 | S5: =IF(OR(H5="",H5="-"),0,IF(H5<30,1,0)) -> 0 | T5: =IF(OR(K5="",O5="",K5="-",O5="-"),0,IF(K5>=O5,1,0)) -> 1 | U5: =IF(OR(H5="",H5="-"),0,IF(H5>30,1,0)) -> 1 | V5: =IF(OR(K5="",J5="",K5="-",J5="-"),0,IF(K5<=J5,1,0)) -> 1 | W5: =IF(OR(K5="",J5="",K5="-",J5="-"),0,IF(K5>=J5,1,0)) -> 0 | X5: =IF(AND(T5=1,U5=1),1,0) -> 1 | Y5: =IF(OR(AND(Q5=1,U5=0),AND(T5=1,U5=0)),1,0) -> 0 | Z5: =IF(R5=1,1,0) -> 0 | AA5: =IF(AND(Q5=1,W5=1),1,0) -> 0 | AB5: =IF(AND(Q5=1,V5=1),1,0) -> 0 | AC5: =COUNT($I$2:I5) -> 4 | AD5: =IF(AC5<4,"Recently Listed",IF(X5=1,"High Growth",IF(Y5=1,"Early Stage",IF(Z5=1,"Low To Moderate",IF(AA5=1,"Attempt to Rivival",IF(AB5=1,"Decline","Undetermined")))))) -> High Growth
A6: Microsoft Corporation | B6: FY 2004 | C6: 15.163 | D6: =SUM(C4:C6) -> 48.9 | E6: 1.963 | F6: =SUM(E4:E6) -> 3.232 | G6: 52.132 | H6: =(D6+F6)/G6*100 -> 100 | I6: 36.835 | J6: -% | K6: =(I6/I3)^(1/3)-1 -> 0.1334515 | L6: 12217.2 | M6: =(L6/L3)^(1/3)-1 -> 0.049064715 | O6: =M6*1.3 -> 0.06378413 | P6: 0 | Q6: =IF(OR(K6="",M6="",K6="-",M6="-"),0,IF(K6<=M6,1,0)) -> 0 | R6: =IF(OR(K6="",M6="",O6="",K6="-",M6="-",O6="-"),0,IF(AND(K6>=M6,K6<=O6),1,0)) -> 0 | S6: =IF(OR(H6="",H6="-"),0,IF(H6<30,1,0)) -> 0 | T6: =IF(OR(K6="",O6="",K6="-",O6="-"),0,IF(K6>=O6,1,0)) -> 1 | U6: =IF(OR(H6="",H6="-"),0,IF(H6>30,1,0)) -> 1 | V6: =IF(OR(K6="",J6="",K6="-",J6="-"),0,IF(K6<=J6,1,0)) -> 1 | W6: =IF(OR(K6="",J6="",K6="-",J6="-"),0,IF(K6>=J6,1,0)) -> 0 | X6: =IF(AND(T6=1,U6=1),1,0) -> 1 | Y6: =IF(OR(AND(Q6=1,U6=0),AND(T6=1,U6=0)),1,0) -> 0 | Z6: =IF(R6=1,1,0) -> 0 | AA6: =IF(AND(Q6=1,W6=1),1,0) -> 0 | AB6: =IF(AND(Q6=1,V6=1),1,0) -> 0 | AC6: =COUNT($I$2:I6) -> 5 | AD6: =IF(AC6<4,"Recently Listed",IF(X6=1,"High Growth",IF(Y6=1,"Early Stage",IF(Z6=1,"Low To Moderate",IF(AA6=1,"Attempt to Rivival",IF(AB6=1,"Decline","Undetermined")))))) -> High Growth
A7: Microsoft Corporation | B7: FY 2005 | C7: 20.731 | D7: =SUM(C5:C7) -> 52.991 | E7: 0.174 | F7: =SUM(E5:E7) -> 3.637 | G7: 64.985 | H7: =(D7+F7)/G7*100 -> 87.140109 | I7: 39.788 | J7: =(I7/I2)^(1/5)-1 -> 0.11627495 | K7: =(I7/I4)^(1/3)-1 -> 0.11941152 | L7: 13039.2 | M7: =(L7/L4)^(1/3)-1 -> 0.060609248 | N7: =(L7/L2)^(1/5)-1 -> 0.049294386 | O7: =M7*1.3 -> 0.078792023 | P7: 0 | Q7: =IF(OR(K7="",M7="",K7="-",M7="-"),0,IF(K7<=M7,1,0)) -> 0 | R7: =IF(OR(K7="",M7="",O7="",K7="-",M7="-",O7="-"),0,IF(AND(K7>=M7,K7<=O7),1,0)) -> 0 | S7: =IF(OR(H7="",H7="-"),0,IF(H7<30,1,0)) -> 0 | T7: =IF(OR(K7="",O7="",K7="-",O7="-"),0,IF(K7>=O7,1,0)) -> 1 | U7: =IF(OR(H7="",H7="-"),0,IF(H7>30,1,0)) -> 1 | V7: =IF(OR(K7="",J7="",K7="-",J7="-"),0,IF(K7<=J7,1,0)) -> 0 | W7: =IF(OR(K7="",J7="",K7="-",J7="-"),0,IF(K7>=J7,1,0)) -> 1 | X7: =IF(AND(T7=1,U7=1),1,0) -> 1 | Y7: =IF(OR(AND(Q7=1,U7=0),AND(T7=1,U7=0)),1,0) -> 0 | Z7: =IF(R7=1,1,0) -> 0 | AA7: =IF(AND(Q7=1,W7=1),1,0) -> 0 | AB7: =IF(AND(Q7=1,V7=1),1,0) -> 0 | AC7: =COUNT($I$2:I7) -> 6 | AD7: =IF(AC7<4,"Recently Listed",IF(X7=1,"High Growth",IF(Y7=1,"Early Stage",IF(Z7=1,"Low To Moderate",IF(AA7=1,"Attempt to Rivival",IF(AB7=1,"Decline","Undetermined")))))) -> High Growth
A8: Microsoft Corporation | B8: FY 2006 | C8: 21.69 | D8: =SUM(C6:C8) -> 57.584 | E8: -2.397 | F8: =SUM(E6:E8) -> -0.26 | G8: 81.409 | H8: =(D8+F8)/G8*100 -> 70.414819 | I8: 44.282 | J8: =(I8/I3)^(1/5)-1 -> 0.11849765 | K8: =(I8/I5)^(1/3)-1 -> 0.11219834 | L8: 13815.58 | M8: =(L8/L5)^(1/3)-1 -> 0.064403644 | N8: =(L8/L3)^(1/5)-1 -> 0.054777497 | O8: =M8*1.3 -> 0.083724737 | P8: 0 | Q8: =IF(OR(K8="",M8="",K8="-",M8="-"),0,IF(K8<=M8,1,0)) -> 0 | R8: =IF(OR(K8="",M8="",O8="",K8="-",M8="-",O8="-"),0,IF(AND(K8>=M8,K8<=O8),1,0)) -> 0 | S8: =IF(OR(H8="",H8="-"),0,IF(H8<30,1,0)) -> 0 | T8: =IF(OR(K8="",O8="",K8="-",O8="-"),0,IF(K8>=O8,1,0)) -> 1 | U8: =IF(OR(H8="",H8="-"),0,IF(H8>30,1,0)) -> 1 | V8: =IF(OR(K8="",J8="",K8="-",J8="-"),0,IF(K8<=J8,1,0)) -> 1 | W8: =IF(OR(K8="",J8="",K8="-",J8="-"),0,IF(K8>=J8,1,0)) -> 0 | X8: =IF(AND(T8=1,U8=1),1,0) -> 1 | Y8: =IF(OR(AND(Q8=1,U8=0),AND(T8=1,U8=0)),1,0) -> 0 | Z8: =IF(R8=1,1,0) -> 0 | AA8: =IF(AND(Q8=1,W8=1),1,0) -> 0 | AB8: =IF(AND(Q8=1,V8=1),1,0) -> 0 | AC8: =COUNT($I$2:I8) -> 7 | AD8: =IF(AC8<4,"Recently Listed",IF(X8=1,"High Growth",IF(Y8=1,"Early Stage",IF(Z8=1,"Low To Moderate",IF(AA8=1,"Attempt to Rivival",IF(AB8=1,"Decline","Undetermined")))))) -> High Growth
A9: Microsoft Corporation | B9: FY 2007 | C9: 24.034 | D9: =SUM(C7:C9) -> 66.455 | E9: -0.961 | F9: =SUM(E7:E9) -> -3.184 | G9: 110.494 | H9: =(D9+F9)/G9*100 -> 57.261933 | I9: 51.122 | J9: =(I9/I4)^(1/5)-1 -> 0.12503235 | K9: =(I9/I6)^(1/3)-1 -> 0.11544729 | L9: 14474.23 | M9: =(L9/L6)^(1/3)-1 -> 0.058135444 | N9: =(L9/L4)^(1/5)-1 -> 0.05779656 | O9: =M9*1.3 -> 0.075576077 | P9: 0 | Q9: =IF(OR(K9="",M9="",K9="-",M9="-"),0,IF(K9<=M9,1,0)) -> 0 | R9: =IF(OR(K9="",M9="",O9="",K9="-",M9="-",O9="-"),0,IF(AND(K9>=M9,K9<=O9),1,0)) -> 0 | S9: =IF(OR(H9="",H9="-"),0,IF(H9<30,1,0)) -> 0 | T9: =IF(OR(K9="",O9="",K9="-",O9="-"),0,IF(K9>=O9,1,0)) -> 1 | U9: =IF(OR(H9="",H9="-"),0,IF(H9>30,1,0)) -> 1 | V9: =IF(OR(K9="",J9="",K9="-",J9="-"),0,IF(K9<=J9,1,0)) -> 1 | W9: =IF(OR(K9="",J9="",K9="-",J9="-"),0,IF(K9>=J9,1,0)) -> 0 | X9: =IF(AND(T9=1,U9=1),1,0) -> 1 | Y9: =IF(OR(AND(Q9=1,U9=0),AND(T9=1,U9=0)),1,0) -> 0 | Z9: =IF(R9=1,1,0) -> 0 | AA9: =IF(AND(Q9=1,W9=1),1,0) -> 0 | AB9: =IF(AND(Q9=1,V9=1),1,0) -> 0 | AC9: =COUNT($I$2:I9) -> 8 | AD9: =IF(AC9<4,"Recently Listed",IF(X9=1,"High Growth",IF(Y9=1,"Early Stage",IF(Z9=1,"Low To Moderate",IF(AA9=1,"Attempt to Rivival",IF(AB9=1,"Decline","Undetermined")))))) -> High Growth
A10: Microsoft Corporation | B10: FY 2008 | C10: 29.567 | D10: =SUM(C8:C10) -> 75.291 | E10: -2.435 | F10: =SUM(E8:E10) -> -5.793 | G10: 101.883 | H10: =(D10+F10)/G10*100 -> 68.213539 | I10: 60.42 | J10: =(I10/I5)^(1/5)-1 -> 0.13422716 | K10: =(I10/I7)^(1/3)-1 -> 0.14941326 | L10: 14769.86 | M10: =(L10/L7)^(1/3)-1 -> 0.042417781 | N10: =(L10/L5)^(1/5)-1 -> 0.052119968 | O10: =M10*1.3 -> 0.055143115 | P10: 0 | Q10: =IF(OR(K10="",M10="",K10="-",M10="-"),0,IF(K10<=M10,1,0)) -> 0 | R10: =IF(OR(K10="",M10="",O10="",K10="-",M10="-",O10="-"),0,IF(AND(K10>=M10,K10<=O10),1,0)) -> 0 | S10: =IF(OR(H10="",H10="-"),0,IF(H10<30,1,0)) -> 0 | T10: =IF(OR(K10="",O10="",K10="-",O10="-"),0,IF(K10>=O10,1,0)) -> 1 | U10: =IF(OR(H10="",H10="-"),0,IF(H10>30,1,0)) -> 1 | V10: =IF(OR(K10="",J10="",K10="-",J10="-"),0,IF(K10<=J10,1,0)) -> 0 | W10: =IF(OR(K10="",J10="",K10="-",J10="-"),0,IF(K10>=J10,1,0)) -> 1 | X10: =IF(AND(T10=1,U10=1),1,0) -> 1 | Y10: =IF(OR(AND(Q10=1,U10=0),AND(T10=1,U10=0)),1,0) -> 0 | Z10: =IF(R10=1,1,0) -> 0 | AA10: =IF(AND(Q10=1,W10=1),1,0) -> 0 | AB10: =IF(AND(Q10=1,V10=1),1,0) -> 0 | AC10: =COUNT($I$2:I10) -> 9 | AD10: =IF(AC10<4,"Recently Listed",IF(X10=1,"High Growth",IF(Y10=1,"Early Stage",IF(Z10=1,"Low To Moderate",IF(AA10=1,"Attempt to Rivival",IF(AB10=1,"Decline","Undetermined")))))) -> High Growth
A11: Microsoft Corporation | B11: FY 2009 | C11: 25.867 | D11: =SUM(C9:C11) -> 79.468 | E11: -0.178 | F11: =SUM(E9:E11) -> -3.574 | G11: 90.346 | H11: =(D11+F11)/G11*100 -> 84.003719 | I11: 57.933 | J11: =(I11/I6)^(1/5)-1 -> 0.094795664 | K11: =(I11/I8)^(1/3)-1 -> 0.093703488 | L11: 14478.07 | M11: =(L11/L8)^(1/3)-1 -> 0.015735232 | N11: =(L11/L6)^(1/5)-1 -> 0.034541216 | O11: =M11*1.3 -> 0.020455801 | P11: 0 | Q11: =IF(OR(K11="",M11="",K11="-",M11="-"),0,IF(K11<=M11,1,0)) -> 0 | R11: =IF(OR(K11="",M11="",O11="",K11="-",M11="-",O11="-"),0,IF(AND(K11>=M11,K11<=O11),1,0)) -> 0 | S11: =IF(OR(H11="",H11="-"),0,IF(H11<30,1,0)) -> 0 | T11: =IF(OR(K11="",O11="",K11="-",O11="-"),0,IF(K11>=O11,1,0)) -> 1 | U11: =IF(OR(H11="",H11="-"),0,IF(H11>30,1,0)) -> 1 | V11: =IF(OR(K11="",J11="",K11="-",J11="-"),0,IF(K11<=J11,1,0)) -> 1 | W11: =IF(OR(K11="",J11="",K11="-",J11="-"),0,IF(K11>=J11,1,0)) -> 0 | X11: =IF(AND(T11=1,U11=1),1,0) -> 1 | Y11: =IF(OR(AND(Q11=1,U11=0),AND(T11=1,U11=0)),1,0) -> 0 | Z11: =IF(R11=1,1,0) -> 0 | AA11: =IF(AND(Q11=1,W11=1),1,0) -> 0 | AB11: =IF(AND(Q11=1,V11=1),1,0) -> 0 | AC11: =COUNT($I$2:I11) -> 10 | AD11: =IF(AC11<4,"Recently Listed",IF(X11=1,"High Growth",IF(Y11=1,"Early Stage",IF(Z11=1,"Low To Moderate",IF(AA11=1,"Attempt to Rivival",IF(AB11=1,"Decline","Undetermined")))))) -> High Growth
A12: Microsoft Corporation | B12: FY 2010 | C12: 27.702 | D12: =SUM(C10:C12) -> 83.136 | E12: 0.661 | F12: =SUM(E10:E12) -> -1.952 | G12: 89.678 | H12: =(D12+F12)/G12*100 -> 90.528335 | I12: 63.55 | J12: =(I12/I7)^(1/5)-1 -> 0.098177873 | K12: =(I12/I9)^(1/3)-1 -> 0.075232971 | L12: 15048.97 | M12: =(L12/L9)^(1/3)-1 -> 0.013064512 | N12: =(L12/L7)^(1/5)-1 -> 0.029084806 | O12: =M12*1.3 -> 0.016983866 | P12: 0 | Q12: =IF(OR(K12="",M12="",K12="-",M12="-"),0,IF(K12<=M12,1,0)) -> 0 | R12: =IF(OR(K12="",M12="",O12="",K12="-",M12="-",O12="-"),0,IF(AND(K12>=M12,K12<=O12),1,0)) -> 0 | S12: =IF(OR(H12="",H12="-"),0,IF(H12<30,1,0)) -> 0 | T12: =IF(OR(K12="",O12="",K12="-",O12="-"),0,IF(K12>=O12,1,0)) -> 1 | U12: =IF(OR(H12="",H12="-"),0,IF(H12>30,1,0)) -> 1 | V12: =IF(OR(K12="",J12="",K12="-",J12="-"),0,IF(K12<=J12,1,0)) -> 1 | W12: =IF(OR(K12="",J12="",K12="-",J12="-"),0,IF(K12>=J12,1,0)) -> 0 | X12: =IF(AND(T12=1,U12=1),1,0) -> 1 | Y12: =IF(OR(AND(Q12=1,U12=0),AND(T12=1,U12=0)),1,0) -> 0 | Z12: =IF(R12=1,1,0) -> 0 | AA12: =IF(AND(Q12=1,W12=1),1,0) -> 0 | AB12: =IF(AND(Q12=1,V12=1),1,0) -> 0 | AC12: =COUNT($I$2:I12) -> 11 | AD12: =IF(AC12<4,"Recently Listed",IF(X12=1,"High Growth",IF(Y12=1,"Early Stage",IF(Z12=1,"Low To Moderate",IF(AA12=1,"Attempt to Rivival",IF(AB12=1,"Decline","Undetermined")))))) -> High Growth
A13: Microsoft Corporation | B13: FY 2011 | C13: 35.511 | D13: =SUM(C11:C13) -> 89.08 | E13: -3.003 | F13: =SUM(E11:E13) -> -2.52 | G13: 101.705 | H13: =(D13+F13)/G13*100 -> 85.108893 | I13: 71.148 | J13: =(I13/I8)^(1/5)-1 -> 0.099479392 | K13: =(I13/I10)^(1/3)-1 -> 0.055992074 | L13: 15599.73 | M13: =(L13/L10)^(1/3)-1 -> 0.01838869 | N13: =(L13/L8)^(1/5)-1 -> 0.024588771 | O13: =M13*1.3 -> 0.023905297 | P13: 0 | Q13: =IF(OR(K13="",M13="",K13="-",M13="-"),0,IF(K13<=M13,1,0)) -> 0 | R13: =IF(OR(K13="",M13="",O13="",K13="-",M13="-",O13="-"),0,IF(AND(K13>=M13,K13<=O13),1,0)) -> 0 | S13: =IF(OR(H13="",H13="-"),0,IF(H13<30,1,0)) -> 0 | T13: =IF(OR(K13="",O13="",K13="-",O13="-"),0,IF(K13>=O13,1,0)) -> 1 | U13: =IF(OR(H13="",H13="-"),0,IF(H13>30,1,0)) -> 1 | V13: =IF(OR(K13="",J13="",K13="-",J13="-"),0,IF(K13<=J13,1,0)) -> 1 | W13: =IF(OR(K13="",J13="",K13="-",J13="-"),0,IF(K13>=J13,1,0)) -> 0 | X13: =IF(AND(T13=1,U13=1),1,0) -> 1 | Y13: =IF(OR(AND(Q13=1,U13=0),AND(T13=1,U13=0)),1,0) -> 0 | Z13: =IF(R13=1,1,0) -> 0 | AA13: =IF(AND(Q13=1,W13=1),1,0) -> 0 | AB13: =IF(AND(Q13=1,V13=1),1,0) -> 0 | AC13: =COUNT($I$2:I13) -> 12 | AD13: =IF(AC13<4,"Recently Listed",IF(X13=1,"High Growth",IF(Y13=1,"Early Stage",IF(Z13=1,"Low To Moderate",IF(AA13=1,"Attempt to Rivival",IF(AB13=1,"Decline","Undetermined")))))) -> High Growth
A14: Microsoft Corporation | B14: FY 2012 | C14: 35.737 | D14: =SUM(C12:C14) -> 98.95 | E14: -0.174 | F14: =SUM(E12:E14) -> -2.516 | G14: 105.1 | H14: =(D14+F14)/G14*100 -> 91.75452 | I14: 74.607 | J14: =(I14/I9)^(1/5)-1 -> 0.078535261 | K14: =(I14/I11)^(1/3)-1 -> 0.087972336 | L14: 16253.97 | M14: =(L14/L11)^(1/3)-1 -> 0.03932074 | N14: =(L14/L9)^(1/5)-1 -> 0.023464532 | O14: =M14*1.3 -> 0.051116962 | P14: 0 | Q14: =IF(OR(K14="",M14="",K14="-",M14="-"),0,IF(K14<=M14,1,0)) -> 0 | R14: =IF(OR(K14="",M14="",O14="",K14="-",M14="-",O14="-"),0,IF(AND(K14>=M14,K14<=O14),1,0)) -> 0 | S14: =IF(OR(H14="",H14="-"),0,IF(H14<30,1,0)) -> 0 | T14: =IF(OR(K14="",O14="",K14="-",O14="-"),0,IF(K14>=O14,1,0)) -> 1 | U14: =IF(OR(H14="",H14="-"),0,IF(H14>30,1,0)) -> 1 | V14: =IF(OR(K14="",J14="",K14="-",J14="-"),0,IF(K14<=J14,1,0)) -> 0 | W14: =IF(OR(K14="",J14="",K14="-",J14="-"),0,IF(K14>=J14,1,0)) -> 1 | X14: =IF(AND(T14=1,U14=1),1,0) -> 1 | Y14: =IF(OR(AND(Q14=1,U14=0),AND(T14=1,U14=0)),1,0) -> 0 | Z14: =IF(R14=1,1,0) -> 0 | AA14: =IF(AND(Q14=1,W14=1),1,0) -> 0 | AB14: =IF(AND(Q14=1,V14=1),1,0) -> 0 | AC14: =COUNT($I$2:I14) -> 13 | AD14: =IF(AC14<4,"Recently Listed",IF(X14=1,"High Growth",IF(Y14=1,"Early Stage",IF(Z14=1,"Low To Moderate",IF(AA14=1,"Attempt to Rivival",IF(AB14=1,"Decline","Undetermined")))))) -> High Growth
A15: Microsoft Corporation | B15: FY 2013 | C15: 34.688 | D15: =SUM(C13:C15) -> 105.936 | E15: -1.375 | F15: =SUM(E13:E15) -> -4.552 | G15: 117.134 | H15: =(D15+F15)/G15*100 -> 86.553861 | I15: 78.566 | J15: =(I15/I10)^(1/5)-1 -> 0.053927616 | K15: =(I15/I12)^(1/3)-1 -> 0.073263507 | L15: 16880.68 | M15: =(L15/L12)^(1/3)-1 -> 0.039029122 | N15: =(L15/L10)^(1/5)-1 -> 0.027076309 | O15: =M15*1.3 -> 0.050737859 | P15: 0 | Q15: =IF(OR(K15="",M15="",K15="-",M15="-"),0,IF(K15<=M15,1,0)) -> 0 | R15: =IF(OR(K15="",M15="",O15="",K15="-",M15="-",O15="-"),0,IF(AND(K15>=M15,K15<=O15),1,0)) -> 0 | S15: =IF(OR(H15="",H15="-"),0,IF(H15<30,1,0)) -> 0 | T15: =IF(OR(K15="",O15="",K15="-",O15="-"),0,IF(K15>=O15,1,0)) -> 1 | U15: =IF(OR(H15="",H15="-"),0,IF(H15>30,1,0)) -> 1 | V15: =IF(OR(K15="",J15="",K15="-",J15="-"),0,IF(K15<=J15,1,0)) -> 0 | W15: =IF(OR(K15="",J15="",K15="-",J15="-"),0,IF(K15>=J15,1,0)) -> 1 | X15: =IF(AND(T15=1,U15=1),1,0) -> 1 | Y15: =IF(OR(AND(Q15=1,U15=0),AND(T15=1,U15=0)),1,0) -> 0 | Z15: =IF(R15=1,1,0) -> 0 | AA15: =IF(AND(Q15=1,W15=1),1,0) -> 0 | AB15: =IF(AND(Q15=1,V15=1),1,0) -> 0 | AC15: =COUNT($I$2:I15) -> 14 | AD15: =IF(AC15<4,"Recently Listed",IF(X15=1,"High Growth",IF(Y15=1,"Early Stage",IF(Z15=1,"Low To Moderate",IF(AA15=1,"Attempt to Rivival",IF(AB15=1,"Decline","Undetermined")))))) -> High Growth
A16: Microsoft Corporation | B16: FY 2014 | C16: 37.887 | D16: =SUM(C14:C16) -> 108.312 | E16: 0.624 | F16: =SUM(E14:E16) -> -0.925 | G16: 119.752 | H16: =(D16+F16)/G16*100 -> 89.674494 | I16: 87.491 | J16: =(I16/I11)^(1/5)-1 -> 0.085944106 | K16: =(I16/I13)^(1/3)-1 -> 0.071355396 | L16: 17608.14 | M16: =(L16/L13)^(1/3)-1 -> 0.041195143 | N16: =(L16/L11)^(1/5)-1 -> 0.039921512 | O16: =M16*1.3 -> 0.053553686 | P16: 0 | Q16: =IF(OR(K16="",M16="",K16="-",M16="-"),0,IF(K16<=M16,1,0)) -> 0 | R16: =IF(OR(K16="",M16="",O16="",K16="-",M16="-",O16="-"),0,IF(AND(K16>=M16,K16<=O16),1,0)) -> 0 | S16: =IF(OR(H16="",H16="-"),0,IF(H16<30,1,0)) -> 0 | T16: =IF(OR(K16="",O16="",K16="-",O16="-"),0,IF(K16>=O16,1,0)) -> 1 | U16: =IF(OR(H16="",H16="-"),0,IF(H16>30,1,0)) -> 1 | V16: =IF(OR(K16="",J16="",K16="-",J16="-"),0,IF(K16<=J16,1,0)) -> 1 | W16: =IF(OR(K16="",J16="",K16="-",J16="-"),0,IF(K16>=J16,1,0)) -> 0 | X16: =IF(AND(T16=1,U16=1),1,0) -> 1 | Y16: =IF(OR(AND(Q16=1,U16=0),AND(T16=1,U16=0)),1,0) -> 0 | Z16: =IF(R16=1,1,0) -> 0 | AA16: =IF(AND(Q16=1,W16=1),1,0) -> 0 | AB16: =IF(AND(Q16=1,V16=1),1,0) -> 0 | AC16: =COUNT($I$2:I16) -> 15 | AD16: =IF(AC16<4,"Recently Listed",IF(X16=1,"High Growth",IF(Y16=1,"Early Stage",IF(Z16=1,"Low To Moderate",IF(AA16=1,"Attempt to Rivival",IF(AB16=1,"Decline","Undetermined")))))) -> High Growth
A17: Microsoft Corporation | B17: FY 2015 | C17: 33.175 | D17: =SUM(C15:C17) -> 105.75 | E17: 1.513 | F17: =SUM(E15:E17) -> 0.762 | G17: 132.328 | H17: =(D17+F17)/G17*100 -> 80.490901 | I17: 96.148 | J17: =(I17/I12)^(1/5)-1 -> 0.086337921 | K17: =(I17/I14)^(1/3)-1 -> 0.088228827 | L17: 18295.02 | M17: =(L17/L14)^(1/3)-1 -> 0.040218272 | N17: =(L17/L12)^(1/5)-1 -> 0.039836894 | O17: =M17*1.3 -> 0.052283754 | P17: 0 | Q17: =IF(OR(K17="",M17="",K17="-",M17="-"),0,IF(K17<=M17,1,0)) -> 0 | R17: =IF(OR(K17="",M17="",O17="",K17="-",M17="-",O17="-"),0,IF(AND(K17>=M17,K17<=O17),1,0)) -> 0 | S17: =IF(OR(H17="",H17="-"),0,IF(H17<30,1,0)) -> 0 | T17: =IF(OR(K17="",O17="",K17="-",O17="-"),0,IF(K17>=O17,1,0)) -> 1 | U17: =IF(OR(H17="",H17="-"),0,IF(H17>30,1,0)) -> 1 | V17: =IF(OR(K17="",J17="",K17="-",J17="-"),0,IF(K17<=J17,1,0)) -> 0 | W17: =IF(OR(K17="",J17="",K17="-",J17="-"),0,IF(K17>=J17,1,0)) -> 1 | X17: =IF(AND(T17=1,U17=1),1,0) -> 1 | Y17: =IF(OR(AND(Q17=1,U17=0),AND(T17=1,U17=0)),1,0) -> 0 | Z17: =IF(R17=1,1,0) -> 0 | AA17: =IF(AND(Q17=1,W17=1),1,0) -> 0 | AB17: =IF(AND(Q17=1,V17=1),1,0) -> 0 | AC17: =COUNT($I$2:I17) -> 16 | AD17: =IF(AC17<4,"Recently Listed",IF(X17=1,"High Growth",IF(Y17=1,"Early Stage",IF(Z17=1,"Low To Moderate",IF(AA17=1,"Attempt to Rivival",IF(AB17=1,"Decline","Undetermined")))))) -> High Growth
A18: Microsoft Corporation | B18: FY 2016 | C18: 40.401 | D18: =SUM(C16:C18) -> 111.463 | E18: -2.076 | F18: =SUM(E16:E18) -> 0.061 | G18: 111.524 | H18: =(D18+F18)/G18*100 -> 100 | I18: 86.132 | J18: =(I18/I13)^(1/5)-1 -> 0.038963683 | K18: =(I18/I15)^(1/3)-1 -> 0.031121786 | L18: 18804.91 | M18: =(L18/L15)^(1/3)-1 -> 0.036637959 | N18: =(L18/L13)^(1/5)-1 -> 0.038080028 | O18: =M18*1.3 -> 0.047629346 | P18: 0 | Q18: =IF(OR(K18="",M18="",K18="-",M18="-"),0,IF(K18<=M18,1,0)) -> 1 | R18: =IF(OR(K18="",M18="",O18="",K18="-",M18="-",O18="-"),0,IF(AND(K18>=M18,K18<=O18),1,0)) -> 0 | S18: =IF(OR(H18="",H18="-"),0,IF(H18<30,1,0)) -> 0 | T18: =IF(OR(K18="",O18="",K18="-",O18="-"),0,IF(K18>=O18,1,0)) -> 0 | U18: =IF(OR(H18="",H18="-"),0,IF(H18>30,1,0)) -> 1 | V18: =IF(OR(K18="",J18="",K18="-",J18="-"),0,IF(K18<=J18,1,0)) -> 1 | W18: =IF(OR(K18="",J18="",K18="-",J18="-"),0,IF(K18>=J18,1,0)) -> 0 | X18: =IF(AND(T18=1,U18=1),1,0) -> 0 | Y18: =IF(OR(AND(Q18=1,U18=0),AND(T18=1,U18=0)),1,0) -> 0 | Z18: =IF(R18=1,1,0) -> 0 | AA18: =IF(AND(Q18=1,W18=1),1,0) -> 0 | AB18: =IF(AND(Q18=1,V18=1),1,0) -> 1 | AC18: =COUNT($I$2:I18) -> 17 | AD18: =IF(AC18<4,"Recently Listed",IF(X18=1,"High Growth",IF(Y18=1,"Early Stage",IF(Z18=1,"Low To Moderate",IF(AA18=1,"Attempt to Rivival",IF(AB18=1,"Decline","Undetermined")))))) -> Decline
... A26: Microsoft Corporation | B26: FY 2024 | C26: 123.97 | D26: =SUM(C24:C26) -> 328.882 | E26: 19.678 | F26: =SUM(E24:E26) -> 34.083 | G26: 401.769 | H26: =(D26+F26)/G26*100 -> 90.341714 | I26: 245.122 | J26: =(I26/I21)^(1/5)-1 -> 0.13654592 | K26: =(I26/I23)^(1/3)-1 -> 0.12617219 | L26: 29167.78 | M26: =(L26/L23)^(1/3)-1 -> 0.071930776 | N26: =(L26/L21)^(1/5)-1 -> 0.06250655 | O26: =M26*1.3 -> 0.093510009 | P26: 0 | Q26: =IF(OR(K26="",M26="",K26="-",M26="-"),0,IF(K26<=M26,1,0)) -> 0 | R26: =IF(OR(K26="",M26="",O26="",K26="-",M26="-",O26="-"),0,IF(AND(K26>=M26,K26<=O26),1,0)) -> 0 | S26: =IF(OR(H26="",H26="-"),0,IF(H26<30,1,0)) -> 0 | T26: =IF(OR(K26="",O26="",K26="-",O26="-"),0,IF(K26>=O26,1,0)) -> 1 | U26: =IF(OR(H26="",H26="-"),0,IF(H26>30,1,0)) -> 1 | V26: =IF(OR(K26="",J26="",K26="-",J26="-"),0,IF(K26<=J26,1,0)) -> 1 | W26: =IF(OR(K26="",J26="",K26="-",J26="-"),0,IF(K26>=J26,1,0)) -> 0 | X26: =IF(AND(T26=1,U26=1),1,0) -> 1 | Y26: =IF(OR(AND(Q26=1,U26=0),AND(T26=1,U26=0)),1,0) -> 0 | Z26: =IF(R26=1,1,0) -> 0 | AA26: =IF(AND(Q26=1,W26=1),1,0) -> 0 | AB26: =IF(AND(Q26=1,V26=1),1,0) -> 0 | AC26: =COUNT($I$2:I26) -> 25 | AD26: =IF(AC26<4,"Recently Listed",IF(X26=1,"High Growth",IF(Y26=1,"Early Stage",IF(Z26=1,"Low To Moderate",IF(AA26=1,"Attempt to Rivival",IF(AB26=1,"Decline","Undetermined")))))) -> High Growth
A27: Microsoft Corporation | B27: FY 2025 | C27: 171.812 | D27: =SUM(C25:C27) -> 402.554 | E27: -5.35 | F27: =SUM(E25:E27) -> 19.938 | G27: 443.817 | H27: =(D27+F27)/G27*100 -> 95.195092 | I27: 276.823 | J27: =(I27/I22)^(1/5)-1 -> 0.13699527 | K27: =(I27/I24)^(1/3)-1 -> 0.11704874 | P27: 0 | Q27: =IF(OR(K27="",M27="",K27="-",M27="-"),0,IF(K27<=M27,1,0)) -> 0 | R27: =IF(OR(K27="",M27="",O27="",K27="-",M27="-",O27="-"),0,IF(AND(K27>=M27,K27<=O27),1,0)) -> 0 | S27: =IF(OR(H27="",H27="-"),0,IF(H27<30,1,0)) -> 0 | T27: =IF(OR(K27="",O27="",K27="-",O27="-"),0,IF(K27>=O27,1,0)) -> 0 | U27: =IF(OR(H27="",H27="-"),0,IF(H27>30,1,0)) -> 1 | V27: =IF(OR(K27="",J27="",K27="-",J27="-"),0,IF(K27<=J27,1,0)) -> 1 | W27: =IF(OR(K27="",J27="",K27="-",J27="-"),0,IF(K27>=J27,1,0)) -> 0 | X27: =IF(AND(T27=1,U27=1),1,0) -> 0 | Y27: =IF(OR(AND(Q27=1,U27=0),AND(T27=1,U27=0)),1,0) -> 0 | Z27: =IF(R27=1,1,0) -> 0 | AA27: =IF(AND(Q27=1,W27=1),1,0) -> 0 | AB27: =IF(AND(Q27=1,V27=1),1,0) -> 0 | AC27: =COUNT($I$2:I27) -> 26 | AD27: =IF(AC27<4,"Recently Listed",IF(X27=1,"High Growth",IF(Y27=1,"Early Stage",IF(Z27=1,"Low To Moderate",IF(AA27=1,"Attempt to Rivival",IF(AB27=1,"Decline","Undetermined")))))) -> Undetermined | AE27: High Growth

Sheet Sheet17
A1: Amount in BUSD | B1: 36678 | C1: 37043 | D1: 37408 | E1: 37773 | F1: 38139 | G1: 38504 | H1: 38869 | I1: 39234 | J1: 39600 | K1: 39965 | L1: 40330 | M1: 40695 | N1: 41061 | O1: 41426 | P1: 41791 | Q1: 42156 | R1: 42522 | S1: 42887 | T1: 43252 | U1: 43617 | V1: 43983 | W1: 44348 | X1: 44713 | Y1: 45078 | Z1: 45444 | AA1: 45809
A2: Operating Cash Margin | B2: 15.426 | C2: 15.025 | D2: 16.64 | E2: 17.097 | F2: 15.163 | G2: 20.731 | H2: 21.69 | I2: 24.034 | J2: 29.567 | K2: 25.867 | L2: 27.702 | M2: 35.511 | N2: 35.737 | O2: 34.688 | P2: 37.887 | Q2: 33.175 | R2: 40.401 | S2: 41.855 | T2: 31.317 | U2: 59.119 | V2: 77.058 | W2: 93.076 | X2: 98.14 | Y2: 106.772 | Z2: 123.97 | AA2: 171.812 | AB2: =SUM(B2:D2) -> 47.091 | AC2: =SUM(C2:E2) -> 48.762 | AD2: =SUM(D2:F2) -> 48.9 | AE2: =SUM(E2:G2) -> 52.991 | AF2: =SUM(F2:H2) -> 57.584 | AG2: =SUM(G2:I2) -> 66.455 | AH2: =SUM(H2:J2) -> 75.291 | AI2: =SUM(I2:K2) -> 79.468 | ... AY2: =SUM(Y2:AA2) -> 402.554
A3: Exceptional Items | B3: 0 | C3: 0 | D3: 0 | E3: 0 | F3: 0 | G3: 0 | H3: 0 | I3: 0 | J3: 0 | K3: 0 | L3: 0 | M3: 0 | N3: 0 | O3: 0 | P3: 0 | Q3: 0 | R3: 0 | S3: 0 | T3: 0 | U3: 0 | V3: 0 | W3: 0 | X3: 0 | Y3: 0 | Z3: 0 | AA3: 0 | AB3: =SUM(B3:D3) -> 0 | AC3: =SUM(C3:E3) -> 0 | AD3: =SUM(D3:F3) -> 0 | AE3: =SUM(E3:G3) -> 0 | AF3: =SUM(F3:H3) -> 0 | AG3: =SUM(G3:I3) -> 0 | AH3: =SUM(H3:J3) -> 0 | AI3: =SUM(I3:K3) -> 0 | ... AY3: =SUM(Y3:AA3) -> 0
A4: (Invested)/generated From Net Working Assets | B4: -3.2 | C4: -0.303 | D4: -0.231 | E4: 1.5 | F4: 1.963 | G4: 0.174 | H4: -2.397 | I4: -0.961 | J4: -2.435 | K4: -0.178 | L4: 0.661 | M4: -3.003 | N4: -0.174 | O4: -1.375 | P4: 0.624 | Q4: 1.513 | R4: -2.076 | S4: 1.652 | T4: 20.467 | U4: 3.866 | V4: -1.483 | W4: -0.936 | X4: 8.795 | Y4: 5.61 | Z4: 19.678 | AA4: -5.35 | AB4: =SUM(B4:D4) -> -3.734 | AC4: =SUM(C4:E4) -> 0.966 | AD4: =SUM(D4:F4) -> 3.232 | AE4: =SUM(E4:G4) -> 3.637 | AF4: =SUM(F4:H4) -> -0.26 | AG4: =SUM(G4:I4) -> -3.184 | AH4: =SUM(H4:J4) -> -5.793 | AI4: =SUM(I4:K4) -> -3.574 | ... AY4: =SUM(Y4:AA4) -> 19.938
A5: NET Capex | B5: -0.879 | C5: -1.103 | D5: -0.77 | E5: -1.954 | F5: -1.113 | G5: -1.019 | H5: -2.227 | I5: -3.414 | J5: -11.235 | K5: -3.987 | L5: -2.222 | M5: -2.426 | N5: -12.417 | O5: -5.841 | P5: -11.422 | Q5: -9.667 | R5: -9.736 | S5: -34.073 | T5: -12.52 | U5: -16.313 | V5: -17.962 | W5: -29.531 | X5: -45.924 | Y5: -29.777 | Z5: -113.609 | AA5: -70.529 | AB5: =SUM(B5:D5) -> -2.752 | AC5: =SUM(C5:E5) -> -3.827 | AD5: =SUM(D5:F5) -> -3.837 | AE5: =SUM(E5:G5) -> -4.086 | AF5: =SUM(F5:H5) -> -4.359 | AG5: =SUM(G5:I5) -> -6.66 | AH5: =SUM(H5:J5) -> -16.876 | AI5: =SUM(I5:K5) -> -18.636 | ... AY5: =SUM(Y5:AA5) -> -213.915
A6: Taxation | B6: -0.8 | C6: -1.3 | D6: -1.9 | E6: -2.8 | F6: -2.5 | G6: -4.3 | H6: -4.8 | I6: -5.2 | J6: -5.4 | K6: -6.6 | L6: -4.1 | M6: -5.3 | N6: -3.5 | O6: -3.9 | P6: -5.5 | Q6: -4.4 | R6: -3.9 | S6: -2.4 | T6: -5.5 | U6: -8.4 | V6: -12.5 | W6: -13.4 | X6: -16 | Y6: -23.1 | Z6: -23.4 | AA6: -28.7 | AB6: =SUM(B6:D6) -> -4 | AC6: =SUM(C6:E6) -> -6 | AD6: =SUM(D6:F6) -> -7.2 | AE6: =SUM(E6:G6) -> -9.6 | AF6: =SUM(F6:H6) -> -11.6 | AG6: =SUM(G6:I6) -> -14.3 | AH6: =SUM(H6:J6) -> -15.4 | AI6: =SUM(I6:K6) -> -17.2 | ... AY6: =SUM(Y6:AA6) -> -75.2
A7: Cash Available To Satisfy Finance Providers | B7: 10.547 | C7: 12.319 | D7: 13.739 | E7: 13.843 | F7: 13.513 | G7: 15.586 | H7: 12.266 | I7: 14.459 | J7: 10.497 | K7: 15.102 | L7: 22.041 | M7: 24.782 | N7: 19.646 | O7: 23.572 | P7: 21.589 | Q7: 20.621 | R7: 24.689 | S7: 7.034 | T7: 33.764 | U7: 38.272 | V7: 45.113 | W7: 49.209 | X7: 45.011 | Y7: 59.505 | Z7: 6.639 | AA7: 67.233 | AB7: =SUM(B7:D7) -> 36.605 | AC7: =SUM(C7:E7) -> 39.901 | AD7: =SUM(D7:F7) -> 41.095 | AE7: =SUM(E7:G7) -> 42.942 | AF7: =SUM(F7:H7) -> 41.365 | AG7: =SUM(G7:I7) -> 42.311 | AH7: =SUM(H7:J7) -> 37.222 | AI7: =SUM(I7:K7) -> 40.058 | ... AY7: =SUM(Y7:AA7) -> 133.377
A8: Debt Service Cost Paid | B8: 0 | C8: 0 | D8: 0 | E8: 0 | F8: 0 | G8: 0 | H8: 0 | I8: 0 | J8: 0 | K8: 0 | L8: -0.145 | M8: -0.197 | N8: -0.344 | O8: -0.371 | P8: -0.509 | Q8: -0.62 | R8: -1.1 | S8: -1.6 | T8: -2.4 | U8: -2.4 | V8: -2.4 | W8: -2 | X8: -1.9 | Y8: -1.7 | Z8: -1.7 | AA8: -1.6 | AB8: =SUM(B8:D8) -> 0 | AC8: =SUM(C8:E8) -> 0 | AD8: =SUM(D8:F8) -> 0 | AE8: =SUM(E8:G8) -> 0 | AF8: =SUM(F8:H8) -> 0 | AG8: =SUM(G8:I8) -> 0 | AH8: =SUM(H8:J8) -> 0 | AI8: =SUM(I8:K8) -> 0 | ... AY8: =SUM(Y8:AA8) -> -5
A9: Dividend & Dividend Tax Paid | B9: -0.013 | C9: 0 | D9: 0 | E9: -0.857 | F9: -1.729 | G9: -36.112 | H9: -3.545 | I9: -3.805 | J9: -4.015 | K9: -4.468 | L9: -4.578 | M9: -5.18 | N9: -6.385 | O9: -7.455 | P9: -8.879 | Q9: -9.882 | R9: -11.006 | S9: -11.845 | T9: -12.699 | U9: -13.811 | V9: -15.137 | W9: -16.521 | X9: -18.135 | Y9: -19.8 | Z9: -21.771 | AA9: -24.082 | AB9: =SUM(B9:D9) -> -0.013 | AC9: =SUM(C9:E9) -> -0.857 | AD9: =SUM(D9:F9) -> -2.586 | AE9: =SUM(E9:G9) -> -38.698 | AF9: =SUM(F9:H9) -> -41.386 | AG9: =SUM(G9:I9) -> -43.462 | AH9: =SUM(H9:J9) -> -11.365 | AI9: =SUM(I9:K9) -> -12.288 | ... AY9: =SUM(Y9:AA9) -> -65.653
A10: Investments/Loans & Advances | B10: -8.484 | C10: -7.657 | D10: -10.073 | E10: -5.48 | F10: -2.202 | G10: 16.039 | H10: 10.248 | I10: 9.559 | J10: 6.785 | K10: -11.85 | L10: -9.131 | M10: -12.087 | N10: -12.473 | O10: -17.978 | P10: -7.55 | Q10: -13.407 | R10: -14.281 | S10: -12.689 | T10: 6.509 | U10: 0.425 | V10: 5.538 | W10: 1.925 | X10: 15.472 | Y10: 6.903 | Z10: 16.429 | AA10: -2.007 | AB10: =SUM(B10:D10) -> -26.214 | AC10: =SUM(C10:E10) -> -23.21 | AD10: =SUM(D10:F10) -> -17.755 | AE10: =SUM(E10:G10) -> 8.357 | AF10: =SUM(F10:H10) -> 24.085 | AG10: =SUM(G10:I10) -> 35.846 | AH10: =SUM(H10:J10) -> 26.592 | AI10: =SUM(I10:K10) -> 4.494 | ... AY10: =SUM(Y10:AA10) -> 21.325
A11: Net Cash generated/(Absorbed) Before Financing | B11: 2.05 | C11: 4.662 | D11: 3.666 | E11: 7.506 | F11: 9.582 | G11: -4.487 | H11: 18.969 | I11: 20.213 | J11: 13.267 | K11: -1.216 | L11: 8.187 | M11: 7.318 | N11: 0.444 | O11: -2.232 | P11: 4.651 | Q11: -3.288 | R11: -1.698 | S11: -19.1 | T11: 25.174 | U11: 22.486 | V11: 33.114 | W11: 32.613 | X11: 40.448 | Y11: 44.908 | Z11: -0.403 | AA11: 39.544 | AB11: =SUM(B11:D11) -> 10.378 | AC11: =SUM(C11:E11) -> 15.834 | AD11: =SUM(D11:F11) -> 20.754 | AE11: =SUM(E11:G11) -> 12.601 | AF11: =SUM(F11:H11) -> 24.064 | AG11: =SUM(G11:I11) -> 34.695 | AH11: =SUM(H11:J11) -> 52.449 | AI11: =SUM(I11:K11) -> 32.264 | ... AY11: =SUM(Y11:AA11) -> 84.049
A12: Increase/(decrease) In Equity | B12: -2.179 | C12: -5.821 | D12: -4.572 | E12: -4.366 | F12: -0.635 | G12: -4.948 | H12: -17.106 | I12: -20.793 | J12: -9.039 | K12: -8.774 | L12: -8.958 | M12: -9.133 | N12: -3.116 | O12: -4.429 | P12: -6.709 | Q12: -13.809 | R12: -15.301 | S12: -11.016 | T12: -9.719 | U12: -18.401 | V12: -21.625 | W12: -25.692 | X12: -30.855 | Y12: -20.379 | Z12: -15.252 | AA12: -16.364 | AB12: =SUM(B12:D12) -> -12.572 | AC12: =SUM(C12:E12) -> -14.759 | AD12: =SUM(D12:F12) -> -9.573 | AE12: =SUM(E12:G12) -> -9.949 | AF12: =SUM(F12:H12) -> -22.689 | AG12: =SUM(G12:I12) -> -42.847 | AH12: =SUM(H12:J12) -> -46.938 | AI12: =SUM(I12:K12) -> -38.606 | ... AY12: =SUM(Y12:AA12) -> -51.995
A13: Increase/(decrease) In Debt | B13: 0 | C13: 0 | D13: 0 | E13: 0 | F13: 0 | G13: 0 | H13: 0 | I13: 0 | J13: 0 | K13: 5.746 | L13: 0.19 | M13: 5.96 | N13: 0 | O13: 3.537 | P13: 6.962 | Q13: 13.661 | R13: 18.283 | S13: 31.459 | T13: -10.201 | U13: -4 | V13: -8.935 | W13: -5.504 | X13: -9.023 | Y13: -2.75 | Z13: 0.575 | AA13: -8.962 | AB13: =SUM(B13:D13) -> 0 | AC13: =SUM(C13:E13) -> 0 | AD13: =SUM(D13:F13) -> 0 | AE13: =SUM(E13:G13) -> 0 | AF13: =SUM(F13:H13) -> 0 | AG13: =SUM(G13:I13) -> 0 | AH13: =SUM(H13:J13) -> 0 | AI13: =SUM(I13:K13) -> 5.746 | ... AY13: =SUM(Y13:AA13) -> -11.137
... A17: (Increase)/Decrease In Cash | B17: 0.129 | C17: 0.924 | D17: 0.906 | E17: -3.14 | F17: -8.947 | G17: 9.453 | H17: -1.863 | I17: 0.603 | J17: -4.228 | K17: 4.263 | L17: 0.571 | M17: -4.105 | N17: 2.672 | O17: 3.134 | P17: -4.865 | Q17: 3.074 | R17: -0.915 | S17: -1.153 | T17: -4.283 | U17: 0.59 | V17: -2.22 | W17: -0.648 | X17: 0.293 | Y17: -20.773 | Z17: 16.389 | AA17: -11.927 | AB17: =SUM(B17:D17) -> 1.959 | AC17: =SUM(C17:E17) -> -1.31 | AD17: =SUM(D17:F17) -> -11.181 | AE17: =SUM(E17:G17) -> -2.634 | AF17: =SUM(F17:H17) -> -1.357 | AG17: =SUM(G17:I17) -> 8.193 | AH17: =SUM(H17:J17) -> -5.488 | AI17: =SUM(I17:K17) -> 0.638 | ... AY17: =SUM(Y17:AA17) -> -16.311
AB18: =AB15+AB17+AB2 -> 49.05 | AC18: =AC15+AC14+AC4+AC2 -> 49.963 | AD18: =AD15+AD4+AD2 -> 52.132 | AE18: =AE15+AE10+AE4+AE2 -> 64.985 | AF18: =AF15+AF10+AF4+AF2 -> 81.409 | AG18: =AG15+AG17+AG2+AG13+AG10 -> 110.494 | AH18: =AH15+AH10+AH2 -> 101.883 | AI18: =AI15+AI17+AI2+AI13+AI10 -> 90.346 | AJ18: =AJ15+AJ17+AJ2+AJ13 -> 89.678 | AK18: =AK15+AK17+AK2+AK13 -> 101.705 | AL18: =AL15+AL13+AL2 -> 105.1 | AM18: =AM15+AM17+AM2+AM13 -> 117.134 | AN18: =AN15+AN17+AN2+AN13 -> 119.752 | AO18: =AO15+AO17+AO4+AO2+AO13+AO14 -> 132.328 | AP18: =AP15+AP4+AP2 -> 111.524 | AQ18: =AQ15+AQ17+AQ4+AQ2 -> 117.526 | AR18: =AR15+AR10+AR4+AR2 -> 113.155 | AS18: =AS15+AS10+AS4+AS2 -> 152.521 | AT18: =AT15+AT10+AT4+AT2 -> 202.816 | AU18: =AU15+AU10+AU4+AU2 -> 238.588 | AV18: =AV15+AV10+AV4+AV2 -> 297.585 | AW18: =AW15+AW10+AW4+AW2 -> 335.757 | AX18: =AX15+AX10+AX4+AX2 -> 401.769 | AY18: =AY15+AY10+AY4+AY2 -> 443.817

Sheet Micro Valuation Calculation
A1: STOCK PERFORMANCE CHART | P1: Total outstanding share including future commitment | S1: Market Capitalization Evolution | AA1: Market Valuation Components and Implied Earning Growth Rates | AI1: Earning Yield Comparison | AL1: Price Earning Ratio | AQ1: Comparative Price to Earning | AV1: Price to Book Value/Price to Sales | BB1: Cash Flow Yields | BG1: Net Asset Value Comparisons | BS1: Market Cap Co-relation with Underlying Business | CF1: Free Cash Flow Based Valuation
A2: Company Name | B2: Years | C2: Operating Cash Margin | D2: Market Cap | E2: Revenue | F2: S&P 500 | G2: Net Profit (W/o Excep Items) | H2: Price To Earning Ratio | I2: Price To Earning Ratio(Excep) | J2: NET Capex | K2: Taxation | L2: (Invested)/generated from Net Working Assets | M2: Debt Service Cost Paid | N2: Free Cash Flow | P2: Total Outstanding Share | Q2: Total Outstanding Share (%Growth) | S2: Share Price Per Share | T2: Market Capitalization | U2: Mcap Growth % | V2: Equity | W2: Equity (%Growth) | X2: Net Tangible Asset Value | Y2: Net Tangible Asset Value (%Growth) | AA2: Hurdle rate | AB2: Equity | AC2: Book Value (Previous Year) Component of Market Valuation | AD2: No Growth Scenario Component of Market Valuation | AE2: Speculative Value Component of Market Valuation | AF2: Implied Growth Rate to Reach Market Valuation | AG2: Check for Ratio | AI2: Net Profit After Tax | AJ2: Net Profit (W/o Excep Items) | AL2: Net Profit After Tax | AM2: Price to Earning Ratio | AN2: Net Profit (W/o Excep Items) | AO2: Price to Earning Ratio (Excep Items) | AQ2: Comparative Price to Earning | AR2: Price To Earnings (Average (All Year To Latest) | AS2: Comparative Price to Earning (Excep Items) | AT2: Price To Earnings (Average (All Year To Latest) | AV2: Mcap to Equity | AW2: Mcap to Revenue | AX2: Intangible Assets | AY2: Net Tangible Asset | AZ2: Mcap to Net Tangible Asset | BB2: Cash Available to Satisfy Finance Providers | BC2: Net Cash generated/(Absorbed) before Financing | BD2: Cash Flow Available to Satisfy Finance Providers Yield | BE2: Cash Flow Availability before Financing Yield | BG2: Share Price Per Share | BH2: Total Outstanding Share | BI2: Market Capitalization | BJ2: Equity | BK2: Net Tangible Asset Value | BL2: Current assets | BM2: Current Liabilities | BN2: Non-current Liabilities | BO2: Net Current Asset Value | BP2: Cash and cash equivalents | BQ2: Net Cash Asset Value | BS2: Mcap | BT2: Revenue | BU2: Free Cash Flow (Excep Items) | BV2: Npat (Excep Items) | BW2: 5 Years Mcap | BX2: 5 Years Revenue | BY2: 5 Years FCF | BZ2: 5 Years Npat(Excep Items | CA2: 10 Years Mcap | CB2: 10 Years Revenue | CC2: 10 Years FCF | CD2: 10 Years Npat(Excep Items | CF2: Market Cap | CG2: Free Cash Flows | CH2: Free Cash Flows to Dereive Market Cap(RHS) | CI2: Teasury Yield | CJ2: Numers | CK2: Latest Firm value1% | CL2: Latest Firm value2% | CM2: Firm value3% | CN2: Firm value3.87% | CO2: Firm value4% | CP2: Firm value 5% | CQ2: Firm value6% | CR2: Firm value6.62% | CS2: Firm value8% | CT2: Firm value9% | CU2: Firm value10% | CV2: Firm value11% | CW2: Firm value12% | CX2: Firm value13% | CY2: Firm value14% | CZ2: Firm value15% | DA2: Free Cash Flow (Latest Average Based Valuation)1%...15% | DB2: 3..All Years Average | DC2: 3year Average Firm value1% | DD2: 3year Average Firm value2% | DE2: 3year Firm value3% | DF2: 3year Firm value3.87% | DG2: 3year Firm value4% | DH2: 3year Firm value5% | DI2: 3year Firm value6% | DJ2: 3year Firm value6.62% | DK2: Average Firm value8% | DL2: 3year Firm value9% | DM2: 3year Average Firm value10% | DN2: 3year Firm value11% | DO2: 3year Average Firm value12% | DP2: 3year Firm value13% | DQ2: 3year Firm value14% | DR2: 3year Average Firm value15% | DS2: Free Cash Flow (3 years Average Based Valuation)1%...15% | DT2: 5 to All Year Average | DU2: Free Cash Flow (5 years Average Based Valuation) 1 % | DV2: Lates Firm value 2% | DW2: Latest Firm value3% | DX2: Firm value3.87% | DY2: Firm value4% | DZ2: Firm value5% | EA2: Firm value6.33% | EB2: Firm value7% | EC2: Firm value8% | ED2: Firm value9% | EE2: Firm value10% | EF2: Firm value11% | EG2: Firm value12% | EH2: Firm value13% | EI2: Firm value14% | EJ2: Firm value15% | EK2: Free Cash Flow (5 years Average Based Valuation)1%...15% | EL2: 10 Years Average | EM2: Free Cash Flow (5 years Average Based Valuation) 1 % | EN2: Lates Firm value 2% | EO2: Latest Firm value3% | EP2: Firm value3.87% | EQ2: Firm value4% | ER2: Firm value5% | ES2: Firm value6% | ET2: Firm value6.62% | EU2: Firm value8% | EV2: Firm value9% | EW2: Firm value10% | EX2: Firm value11% | EY2: Firm value12% | EZ2: Firm value13% | FA2: Firm value14% | FB2: Firm value15% | FC2: Free Cash Flow (10 years Average Based Valuation)1%...15% | FD2: All Year Average | FE2: Free Cash Flow (All years Average Based Valuation) 1 % | FF2: Free Cash Flow (All years Average Based Valuation) 2 % | FG2: Free Cash Flow (All years Average Based Valuation) 3 % | FH2: Free Cash Flow (All years Average Based Valuation) 3.87 % | FI2: Free Cash Flow (All years Average Based Valuation) 4 % | FJ2: Free Cash Flow (All years Average Based Valuation) 5 % | FK2: Free Cash Flow (All years Average Based Valuation) 6 % | FL2: Free Cash Flow (All years Average Based Valuation) 6.62 % | FM2: Free Cash Flow (All years Average Based Valuation) 8 % | FN2: Free Cash Flow (All years Average Based Valuation) 9 % | FO2: Free Cash Flow (All years Average Based Valuation) 10 % | FP2: Free Cash Flow (All years Average Based Valuation) 11 % | FQ2: Free Cash Flow (All years Average Based Valuation) 12 % | FR2: Free Cash Flow (All years Average Based Valuation) 13 % | FS2: Free Cash Flow (All years Average Based Valuation) 14 % | FT2: Free Cash Flow (All years Average Based Valuation) 15 % | FU2: Free Cash Flow (All years Average Based Valuation)1%...15% | FV2: Free Cash Flows to Dereive Market Cap(RHS) | FW2: Free Cash Flow to Dereive Market cap (RHS) 1 % | FX2: Free Cash Flow to Dereive Market cap 2 % | FY2: Free Cash Flow to Dereive Market cap 3 % | FZ2: Free Cash Flow to Dereive Market cap 3.87 % | GA2: Free Cash Flow to Dereive Market cap 4 % | GB2: Free Cash Flow to Dereive Market cap 5 % | GC2: Free Cash Flow to Dereive Market cap 6 % | GD2: Free Cash Flow to Dereive Market cap 6.62 % | GE2: Free Cash Flow to Dereive Market cap 8 % | GF2: Free Cash Flow to Dereive Market cap 9 % | GG2: Free Cash Flow to Dereive Market cap 10 % | GH2: Free Cash Flow to Dereive Market cap ) 11 % | GI2: Free Cash Flow to Dereive Market cap 12 % | GJ2: Free Cash Flow to Dereive Market cap 13 % | GK2: Free Cash Flow to Dereive Market cap 14 % | GL2: Free Cash Flow to Dereive Market cap 15 % | GM2: Free Cash Flow to dereive mcap (1%...15%)
A3: Microsoft | B3: 36707 | C3: 15.426 | D3: 528.60582 | E3: 22.956 | F3: 1334.2 | G3: 6.152 | H3: =(D3/AI3) -> 56.109311 | I3: =(D3/G3) -> 85.924223 | J3: -0.879 | K3: -0.8 | L3: -3.2 | M3: 0 | N3: =(C3+L3+J3+K3+M3) -> 10.547 | P3: 6849000000 | S3: 77.18 | T3: =(S3*P3) -> 5.2860582e+11 | V3: 41.368 | X3: 41.368 | AA3: 0.1 | AB3: 41.368 | AI3: 9.421 | AJ3: 6.152 | AL3: 9.421 | AM3: =D3/AL3 -> 56.109311 | AN3: 6.152 | AO3: =D3/AN3 -> 85.924223 | AQ3: =$D$28/AL3 -> 294.12474 | AR3: =AVERAGE(AQ3:AQ27) -> 175.26694 | AS3: =$D$28/AN3 -> 450.41436 | AT3: =AVERAGE(AS3:AS27) -> 196.80191 | AV3: =(D3/AB3) -> 12.778133 | AW3: =(D3/E3) -> 23.026913 | AX3: 0 | AY3: =(AB3-AX3) -> 41.368 | AZ3: =(D3/AY3) -> 12.778133 | BB3: 10.547 | BC3: 2.05 | BD3: =(BB3/D3)*100 -> 1.9952486 | BE3: =(BC3/D3)*100 -> 0.3878126 | BG3: 77.18 | BH3: 6849000000 | BI3: =(BG3*BH3) -> 5.2860582e+11 | BJ3: 41.368 | BK3: =AY3 -> 41.368 | BL3: 30.308 | BM3: 9.755 | BN3: 1.027 | BO3: =(BL3-BM3-BN3) -> 19.526 | BP3: 23.798 | BQ3: =(BP3-BM3-BN3) -> 13.016 | BS3: =D3 -> 528.60582 | BT3: =E3 -> 22.956 | BU3: =N3 -> 10.547 | BV3: =G3 -> 6.152 | CE3: 36707 | CF3: 528.60582 | CG3: 10.547 | CH3: =(CG3/CF3) -> 0.019952486 | CI3: 0.01 | CJ3: 1 | CK3: =$CG$27/(1+$CI$3)^CJ3 -> 4.890099 | CL3: =$CG$27/(1+$CI$4)^CJ3 -> 4.8421569 | CM3: =$CG$27/(1+$CI$5)^CJ3 -> 4.7951456 | CN3: =$CG$27/(1+$CI$6)^CJ3 -> 4.7549822 | CO3: =$CG$27/(1+$CI$7)^CJ3 -> 4.7490385 | CP3: =$CG$27/(1+$CI$8)^CJ3 -> 4.7038095 | CQ3: =$CG$27/(1+$CI$9)^CJ3 -> 4.659434 | CR3: =$CG$27/(1+$CI$10)^CJ3 -> 4.6323391 | CS3: =$CG$27/(1+$CI$11)^CJ3 -> 4.5731481 | CT3: =$CG$27/(1+$CI$12)^CJ3 -> 4.5311927 | CU3: =$CG$27/(1+$CI$13)^CJ3 -> 4.49 | CV3: =$CG$27/(1+$CI$14)^CJ3 -> 4.4495495 | CW3: =$CG$27/(1+$CI$15)^CJ3 -> 4.4098214 | CX3: =$CG$27/(1+$CI$16)^CJ3 -> 4.3707965 | CY3: =$CG$27/(1+$CI$17)^CJ3 -> 4.3324561 | CZ3: =$CG$27/(1+$CI$18)^CJ3 -> 4.2947826 | DA3: =SUM(CK3:CK52) -> 190.27233 | DB3: =AVERAGE(CG25:CG27) -> 35.285 | DC3: =$DB$3/(1+$CI$3)^CJ3 -> 34.935644 | DD3: =$DB$3/(1+$CI$4)^CJ3 -> 34.593137 | DE3: =$DB$3/(1+$CI$5)^CJ3 -> 34.257282 | DF3: =$DB$3/(1+$CI$6)^CJ3 -> 33.970348 | DG3: =$DB$3/(1+$CI$7)^CJ3 -> 33.927885 | DH3: =$DB$3/(1+$CI$8)^CJ3 -> 33.604762 | DI3: =$DB$3/(1+$CI$9)^CJ3 -> 33.287736 | DJ3: =$DB$3/(1+$CI$10)^CJ3 -> 33.094166 | DK3: =$DB$3/(1+$CI$11)^CJ3 -> 32.671296 | DL3: =$DB$3/(1+$CI$12)^CJ3 -> 32.37156 | DM3: =$DB$3/(1+$CI$13)^CJ3 -> 32.077273 | DN3: =$DB$3/(1+$CI$14)^CJ3 -> 31.788288 | DO3: =$DB$3/(1+$CI$15)^CJ3 -> 31.504464 | DP3: =$DB$3/(1+$CI$16)^CJ3 -> 31.225664 | DQ3: =$DB$3/(1+$CI$17)^CJ3 -> 30.951754 | DR3: =$DB$3/(1+$CI$18)^CJ3 -> 30.682609 | DS3: =SUM(DC3:DC52) -> 1359.3357 | DT3: =AVERAGE(CG23:CG27) -> 39.1554 | DU3: =$DT$3/(1+$CI$3)^CJ3 -> 38.767723 | DV3: =$DT$3/(1+$CI$4)^CJ3 -> 38.387647 | DW3: =$DT$3/(1+$CI$5)^CJ3 -> 38.014951 | DX3: =$DT$3/(1+$CI$6)^CJ3 -> 37.696544 | DY3: =$DT$3/(1+$CI$7)^CJ3 -> 37.649423 | DZ3: =$DT$3/(1+$CI$8)^CJ3 -> 37.290857 | EA3: =$DT$3/(1+$CI$9)^CJ3 -> 36.939057 | EB3: =$DT$3/(1+$CI$10)^CJ3 -> 36.724254 | EC3: =$DT$3/(1+$CI$11)^CJ3 -> 36.255 | ED3: =$DT$3/(1+$CI$12)^CJ3 -> 35.922385 | EE3: =$DT$3/(1+$CI$13)^CJ3 -> 35.595818 | EF3: =$DT$3/(1+$CI$14)^CJ3 -> 35.275135 | EG3: =$DT$3/(1+$CI$15)^CJ3 -> 34.960179 | EH3: =$DT$3/(1+$CI$16)^CJ3 -> 34.650796 | EI3: =$DT$3/(1+$CI$17)^CJ3 -> 34.346842 | EJ3: =$DT$3/(1+$CI$18)^CJ3 -> 34.048174 | EK3: =SUM(DU3:DU52) -> 1508.4408 | EL3: =AVERAGE(CG18:CG27) -> 31.2037 | EM3: =$EL$3/(1+$CI$3)^CJ3 -> 30.894752 | EN3: =$EL$3/(1+$CI$4)^CJ3 -> 30.591863 | EO3: =$EL$3/(1+$CI$5)^CJ3 -> 30.294854 | EP3: =$EL$3/(1+$CI$6)^CJ3 -> 30.041109 | EQ3: =$EL$3/(1+$CI$7)^CJ3 -> 30.003558 | ER3: =$EL$3/(1+$CI$8)^CJ3 -> 29.71781 | ES3: =$EL$3/(1+$CI$9)^CJ3 -> 29.437453 | ET3: =$EL$3/(1+$CI$10)^CJ3 -> 29.266273 | EU3: =$EL$3/(1+$CI$11)^CJ3 -> 28.892315 | EV3: =$EL$3/(1+$CI$12)^CJ3 -> 28.627248 | EW3: =$EL$3/(1+$CI$13)^CJ3 -> 28.367 | EX3: =$EL$3/(1+$CI$14)^CJ3 -> 28.111441 | EY3: =$EL$3/(1+$CI$15)^CJ3 -> 27.860446 | EZ3: =$EL$3/(1+$CI$16)^CJ3 -> 27.613894 | FA3: =$EL$3/(1+$CI$17)^CJ3 -> 27.371667 | FB3: =$EL$3/(1+$CI$18)^CJ3 -> 27.133652 | FC3: =SUM(EM3:EM52) -> 1202.1058 | FD3: =AVERAGE(CG3:CG27) -> 22.11996 | FE3: =$FD$3/(1+$CI$3)^CJ3 -> 21.90095 | FF3: =$FD$3/(1+$CI$4)^CJ3 -> 21.686235 | FG3: =$FD$3/(1+$CI$5)^CJ3 -> 21.475689 | FH3: =$FD$3/(1+$CI$6)^CJ3 -> 21.295812 | FI3: =$FD$3/(1+$CI$7)^CJ3 -> 21.269192 | FJ3: =$FD$3/(1+$CI$8)^CJ3 -> 21.066629 | FK3: =$FD$3/(1+$CI$9)^CJ3 -> 20.867887 | FL3: =$FD$3/(1+$CI$10)^CJ3 -> 20.746539 | FM3: =$FD$3/(1+$CI$11)^CJ3 -> 20.481444 | FN3: =$FD$3/(1+$CI$12)^CJ3 -> 20.293541 | FO3: =$FD$3/(1+$CI$13)^CJ3 -> 20.109055 | FP3: =$FD$3/(1+$CI$14)^CJ3 -> 19.927892 | FQ3: =$FD$3/(1+$CI$15)^CJ3 -> 19.749964 | FR3: =$FD$3/(1+$CI$16)^CJ3 -> 19.575186 | FS3: =$FD$3/(1+$CI$17)^CJ3 -> 19.403474 | FT3: =$FD$3/(1+$CI$18)^CJ3 -> 19.234748 | FU3: =SUM(FE3:FE52) -> 852.15961 | FV3: =AVERAGE(CH3:CH27) -> 0.040692862 | FW3: =$FV$3/(1+$CI$3)^CJ3 -> 0.040289963 | FX3: =$FV$3/(1+$CI$4)^CJ3 -> 0.039894963 | FY3: =$FV$3/(1+$CI$5)^CJ3 -> 0.039507633 | FZ3: =$FV$3/(1+$CI$6)^CJ3 -> 0.039176723 | GA3: =$FV$3/(1+$CI$7)^CJ3 -> 0.039127752 | GB3: =$FV$3/(1+$CI$8)^CJ3 -> 0.038755107 | GC3: =$FV$3/(1+$CI$9)^CJ3 -> 0.038389493 | GD3: =$FV$3/(1+$CI$10)^CJ3 -> 0.038166256 | GE3: =$FV$3/(1+$CI$11)^CJ3 -> 0.037678576 | GF3: =$FV$3/(1+$CI$12)^CJ3 -> 0.037332901 | GG3: =$FV$3/(1+$CI$13)^CJ3 -> 0.036993511 | GH3: =$FV$3/(1+$CI$14)^CJ3 -> 0.036660236 | GI3: =$FV$3/(1+$CI$15)^CJ3 -> 0.036332913 | GJ3: =$FV$3/(1+$CI$16)^CJ3 -> 0.036011383 | GK3: =$FV$3/(1+$CI$17)^CJ3 -> 0.035695493 | GL3: =$FV$3/(1+$CI$18)^CJ3 -> 0.035385098 | GM3: =SUM(FW3:FW52) -> 1.5676707
A4: Microsoft | B4: 37072 | C4: 15.025 | D4: 560.142 | E4: 25.296 | F4: 1158.3 | G4: 7.916 | H4: =(D4/AI4) -> 76.251293 | I4: =(D4/G4) -> 70.760738 | J4: -1.103 | K4: -1.3 | L4: -0.303 | M4: 0 | N4: =(C4+L4+J4+K4+M4) -> 12.319 | P4: 6831000000 | Q4: =(P4-P3)/P3*100 -> -0.26281209 | S4: 82 | T4: =(S4*P4) -> 560142000000 | U4: =(D4-D3)/D3*100 -> 5.9659162 | V4: 47.289 | W4: =(V4-V3)/V3*100 -> 14.312996 | X4: 45.377 | Y4: =(X4-X3)/X3*100 -> 9.6910656 | AA4: 0.1 | AB4: 47.289 | AC4: 41.368 | AD4: =(G3/AA3) -> 61.52 | AE4: =(D4-AC4-AD4) -> 457.254 | AF4: =((((D4-AD4)/(G4)*AA4)-1)/(1+(D4-AD4)/(G4))) -> 0.082809582 | AG4: =(1+AF4)/(1+AA4) -> 0.98437235 | AI4: 7.346 | AJ4: 7.916 | AL4: 7.346 | AM4: =D4/AL4 -> 76.251293 | AN4: 7.916 | AO4: =D4/AN4 -> 70.760738 | AQ4: =$D$28/AL4 -> 377.20517 | AS4: =$D$28/AN4 -> 350.04411 | AV4: =(D4/AB4) -> 11.84508 | AW4: =(D4/E4) -> 22.143501 | AX4: 1.912 | AY4: =(AB4-AX4) -> 45.377 | AZ4: =(D4/AY4) -> 12.344183 | BB4: 12.319 | BC4: 4.662 | BD4: =(BB4/D4)*100 -> 2.1992638 | BE4: =(BC4/D4)*100 -> 0.83228896 | BG4: 82 | BH4: 6831000000 | BI4: =(BG4*BH4) -> 560142000000 | BJ4: 47.289 | BK4: =AY4 -> 45.377 | BL4: 39.21 | BM4: 9.254 | BN4: 2.287 | BO4: =(BL4-BM4-BN4) -> 27.669 | BP4: 31.6 | BQ4: =(BP4-BM4-BN4) -> 20.059 | BS4: =D4 -> 560.142 | BT4: =E4 -> 25.296 | BU4: =N4 -> 12.319 | BV4: =G4 -> 7.916 | CE4: 37072 | CF4: 560.142 | CG4: 12.319 | CH4: =(CG4/CF4) -> 0.021992638 | CI4: 0.02 | CJ4: 2 | CK4: =$CG$27/(1+$CI$3)^CJ4 -> 4.8416822 | CL4: =$CG$27/(1+$CI$4)^CJ4 -> 4.7472126 | CM4: =$CG$27/(1+$CI$5)^CJ4 -> 4.6554812 | CN4: =$CG$27/(1+$CI$6)^CJ4 -> 4.5778205 | CO4: =$CG$27/(1+$CI$7)^CJ4 -> 4.5663831 | CP4: =$CG$27/(1+$CI$8)^CJ4 -> 4.4798186 | CQ4: =$CG$27/(1+$CI$9)^CJ4 -> 4.3956924 | CR4: =$CG$27/(1+$CI$10)^CJ4 -> 4.3447188 | CS4: =$CG$27/(1+$CI$11)^CJ4 -> 4.2343964 | CT4: =$CG$27/(1+$CI$12)^CJ4 -> 4.1570575 | CU4: =$CG$27/(1+$CI$13)^CJ4 -> 4.0818182 | CV4: =$CG$27/(1+$CI$14)^CJ4 -> 4.0086032 | CW4: =$CG$27/(1+$CI$15)^CJ4 -> 3.9373406 | CX4: =$CG$27/(1+$CI$16)^CJ4 -> 3.8679615 | CY4: =$CG$27/(1+$CI$17)^CJ4 -> 3.8004001 | CZ4: =$CG$27/(1+$CI$18)^CJ4 -> 3.7345936 | DA4: =SUM(CL3:CL52) -> 152.96436 | DB4: =AVERAGE(CG23:CG27) -> 39.1554 | DC4: =$DB$3/(1+$CI$3)^CJ4 -> 34.589746 | DD4: =$DB$3/(1+$CI$4)^CJ4 -> 33.91484 | DE4: =$DB$3/(1+$CI$5)^CJ4 -> 33.259497 | DF4: =$DB$3/(1+$CI$6)^CJ4 -> 32.704677 | DG4: =$DB$3/(1+$CI$7)^CJ4 -> 32.622966 | DH4: =$DB$3/(1+$CI$8)^CJ4 -> 32.004535 | DI4: =$DB$3/(1+$CI$9)^CJ4 -> 31.403524 | DJ4: =$DB$3/(1+$CI$10)^CJ4 -> 31.039361 | DK4: =$DB$3/(1+$CI$11)^CJ4 -> 30.2512 | DL4: =$DB$3/(1+$CI$12)^CJ4 -> 29.698679 | DM4: =$DB$3/(1+$CI$13)^CJ4 -> 29.161157 | DN4: =$DB$3/(1+$CI$14)^CJ4 -> 28.638098 | DO4: =$DB$3/(1+$CI$15)^CJ4 -> 28.128986 | DP4: =$DB$3/(1+$CI$16)^CJ4 -> 27.633331 | DQ4: =$DB$3/(1+$CI$17)^CJ4 -> 27.150662 | DR4: =$DB$3/(1+$CI$18)^CJ4 -> 26.680529 | DS4: =SUM(DD3:DD52) -> 1092.8017 | DT4: =AVERAGE(CG18:CG27) -> 31.2037 | DU4: =$DT$3/(1+$CI$3)^CJ4 -> 38.383884 | DV4: =$DT$3/(1+$CI$4)^CJ4 -> 37.634948 | DW4: =$DT$3/(1+$CI$5)^CJ4 -> 36.90772 | DX4: =$DT$3/(1+$CI$6)^CJ4 -> 36.292042 | DY4: =$DT$3/(1+$CI$7)^CJ4 -> 36.201368 | DZ4: =$DT$3/(1+$CI$8)^CJ4 -> 35.515102 | EA4: =$DT$3/(1+$CI$9)^CJ4 -> 34.848167 | EB4: =$DT$3/(1+$CI$10)^CJ4 -> 34.444058 | EC4: =$DT$3/(1+$CI$11)^CJ4 -> 33.569444 | ED4: =$DT$3/(1+$CI$12)^CJ4 -> 32.956317 | EE4: =$DT$3/(1+$CI$13)^CJ4 -> 32.359835 | EF4: =$DT$3/(1+$CI$14)^CJ4 -> 31.779401 | EG4: =$DT$3/(1+$CI$15)^CJ4 -> 31.214445 | EH4: =$DT$3/(1+$CI$16)^CJ4 -> 30.664422 | EI4: =$DT$3/(1+$CI$17)^CJ4 -> 30.128809 | EJ4: =$DT$3/(1+$CI$18)^CJ4 -> 29.607108 | EK4: =SUM(DV3:DV52) -> 1212.6708 | EL4: =AVERAGE(CG3:CG27) -> 22.11996 | EM4: =$EL$3/(1+$CI$3)^CJ4 -> 30.588864 | EN4: =$EL$3/(1+$CI$4)^CJ4 -> 29.992022 | EO4: =$EL$3/(1+$CI$5)^CJ4 -> 29.41248 | EP4: =$EL$3/(1+$CI$6)^CJ4 -> 28.921834 | EQ4: =$EL$3/(1+$CI$7)^CJ4 -> 28.849575 | ER4: =$EL$3/(1+$CI$8)^CJ4 -> 28.302676 | ES4: =$EL$3/(1+$CI$9)^CJ4 -> 27.771182 | ET4: =$EL$3/(1+$CI$10)^CJ4 -> 27.44914 | EU4: =$EL$3/(1+$CI$11)^CJ4 -> 26.752143 | EV4: =$EL$3/(1+$CI$12)^CJ4 -> 26.26353 | EW4: =$EL$3/(1+$CI$13)^CJ4 -> 25.788182 | EX4: =$EL$3/(1+$CI$14)^CJ4 -> 25.325623 | EY4: =$EL$3/(1+$CI$15)^CJ4 -> 24.875399 | EZ4: =$EL$3/(1+$CI$16)^CJ4 -> 24.437074 | FA4: =$EL$3/(1+$CI$17)^CJ4 -> 24.010234 | FB4: =$EL$3/(1+$CI$18)^CJ4 -> 23.59448 | FC4: =SUM(EN3:EN52) -> 966.40091 | FE4: =$FD$3/(1+$CI$3)^CJ4 -> 21.684109 | FF4: =$FD$3/(1+$CI$4)^CJ4 -> 21.261015 | FG4: =$FD$3/(1+$CI$5)^CJ4 -> 20.850184 | FH4: =$FD$3/(1+$CI$6)^CJ4 -> 20.50237 | FI4: =$FD$3/(1+$CI$7)^CJ4 -> 20.451146 | FJ4: =$FD$3/(1+$CI$8)^CJ4 -> 20.063456 | FK4: =$FD$3/(1+$CI$9)^CJ4 -> 19.686686 | FL4: =$FD$3/(1+$CI$10)^CJ4 -> 19.458393 | FM4: =$FD$3/(1+$CI$11)^CJ4 -> 18.9643 | FN4: =$FD$3/(1+$CI$12)^CJ4 -> 18.617928 | FO4: =$FD$3/(1+$CI$13)^CJ4 -> 18.280959 | FP4: =$FD$3/(1+$CI$14)^CJ4 -> 17.953056 | FQ4: =$FD$3/(1+$CI$15)^CJ4 -> 17.633897 | FR4: =$FD$3/(1+$CI$16)^CJ4 -> 17.323173 | FS4: =$FD$3/(1+$CI$17)^CJ4 -> 17.020591 | FT4: =$FD$3/(1+$CI$18)^CJ4 -> 16.725868 | FU4: =SUM(FF3:FF52) -> 685.07099 | FW4: =$FV$3/(1+$CI$3)^CJ4 -> 0.039891052 | FX4: =$FV$3/(1+$CI$4)^CJ4 -> 0.039112709 | FY4: =$FV$3/(1+$CI$5)^CJ4 -> 0.038356926 | FZ4: =$FV$3/(1+$CI$6)^CJ4 -> 0.037717072 | GA4: =$FV$3/(1+$CI$7)^CJ4 -> 0.037622839 | GB4: =$FV$3/(1+$CI$8)^CJ4 -> 0.036909626 | GC4: =$FV$3/(1+$CI$9)^CJ4 -> 0.036216503 | GD4: =$FV$3/(1+$CI$10)^CJ4 -> 0.035796526 | GE4: =$FV$3/(1+$CI$11)^CJ4 -> 0.034887571 | GF4: =$FV$3/(1+$CI$12)^CJ4 -> 0.034250368 | GG4: =$FV$3/(1+$CI$13)^CJ4 -> 0.033630465 | GH4: =$FV$3/(1+$CI$14)^CJ4 -> 0.03302724 | GI4: =$FV$3/(1+$CI$15)^CJ4 -> 0.032440101 | GJ4: =$FV$3/(1+$CI$16)^CJ4 -> 0.03186848 | GK4: =$FV$3/(1+$CI$17)^CJ4 -> 0.031311836 | GL4: =$FV$3/(1+$CI$18)^CJ4 -> 0.03076965 | GM4: =SUM(FX3:FX52) -> 1.2602871
A5: Microsoft | B5: 37437 | C5: 16.64 | D5: 486.50928 | E5: 28.365 | F5: 879.4 | G5: 8.226 | H5: =(D5/AI5) -> 62.141944 | I5: =(D5/G5) -> 59.142874 | J5: -0.77 | K5: -1.9 | L5: -0.231 | M5: 0 | N5: =(C5+L5+J5+K5+M5) -> 13.739 | P5: 6704000000 | Q5: =(P5-P4)/P4*100 -> -1.8591714 | S5: 72.57 | T5: =(S5*P5) -> 4.8650928e+11 | U5: =(D5-D4)/D4*100 -> -13.145367 | V5: 54.842 | W5: =(V5-V4)/V4*100 -> 15.972002 | X5: 53.173 | Y5: =(X5-X4)/X4*100 -> 17.18051 | AA5: 0.1 | AB5: 54.842 | AC5: 47.289 | AD5: =(G4/AA5) -> 79.16 | AE5: =(D5-AC5-AD5) -> 360.06028 | AF5: =((((D5-AD5)/(G5)*AA5)-1)/(1+(D5-AD5)/(G5))) -> 0.078226328 | AG5: =(1+AF5)/(1+AA5) -> 0.98020575 | AI5: 7.829 | AJ5: 8.226 | AL5: 7.829 | AM5: =D5/AL5 -> 62.141944 | AN5: 8.226 | AO5: =D5/AN5 -> 59.142874 | AQ5: =$D$28/AL5 -> 353.93398 | AS5: =$D$28/AN5 -> 336.85256 | AV5: =(D5/AB5) -> 8.8711075 | AW5: =(D5/E5) -> 17.151746 | AX5: 1.669 | AY5: =(AB5-AX5) -> 53.173 | AZ5: =(D5/AY5) -> 9.1495548 | BB5: 13.739 | BC5: 3.666 | BD5: =(BB5/D5)*100 -> 2.8239955 | BE5: =(BC5/D5)*100 -> 0.75353136 | BG5: 72.57 | BH5: 6704000000 | BI5: =(BG5*BH5) -> 4.8650928e+11 | BJ5: 54.842 | BK5: =AY5 -> 53.173 | BL5: 48.576 | BM5: 12.744 | BN5: 0.06 | BO5: =(BL5-BM5-BN5) -> 35.772 | BP5: 38.652 | BQ5: =(BP5-BM5-BN5) -> 25.848 | BS5: =D5 -> 486.50928 | BT5: =E5 -> 28.365 | BU5: =N5 -> 13.739 | BV5: =G5 -> 8.226 | CE5: 37437 | CF5: 486.50928 | CG5: 13.739 | CH5: =(CG5/CF5) -> 0.028239955 | CI5: 0.03 | CJ5: 3 | CK5: =$CG$27/(1+$CI$3)^CJ5 -> 4.7937447 | CL5: =$CG$27/(1+$CI$4)^CJ5 -> 4.65413 | CM5: =$CG$27/(1+$CI$5)^CJ5 -> 4.5198847 | CN5: =$CG$27/(1+$CI$6)^CJ5 -> 4.4072596 | CO5: =$CG$27/(1+$CI$7)^CJ5 -> 4.390753 | CP5: =$CG$27/(1+$CI$8)^CJ5 -> 4.2664939 | CQ5: =$CG$27/(1+$CI$9)^CJ5 -> 4.1468796 | CR5: =$CG$27/(1+$CI$10)^CJ5 -> 4.0749566 | CS5: =$CG$27/(1+$CI$11)^CJ5 -> 3.9207374 | CT5: =$CG$27/(1+$CI$12)^CJ5 -> 3.8138142 | CU5: =$CG$27/(1+$CI$13)^CJ5 -> 3.7107438 | CV5: =$CG$27/(1+$CI$14)^CJ5 -> 3.6113542 | CW5: =$CG$27/(1+$CI$15)^CJ5 -> 3.5154826 | CX5: =$CG$27/(1+$CI$16)^CJ5 -> 3.4229748 | CY5: =$CG$27/(1+$CI$17)^CJ5 -> 3.3336843 | CZ5: =$CG$27/(1+$CI$18)^CJ5 -> 3.2474727 | DA5: =SUM(CM3:CM52) -> 125.56522 | DB5: =AVERAGE(CG18:CG27) -> 31.2037 | DC5: =$DB$3/(1+$CI$3)^CJ5 -> 34.247273 | DD5: =$DB$3/(1+$CI$4)^CJ5 -> 33.249844 | DE5: =$DB$3/(1+$CI$5)^CJ5 -> 32.290773 | DF5: =$DB$3/(1+$CI$6)^CJ5 -> 31.486162 | DG5: =$DB$3/(1+$CI$7)^CJ5 -> 31.368237 | DH5: =$DB$3/(1+$CI$8)^CJ5 -> 30.48051 | DI5: =$DB$3/(1+$CI$9)^CJ5 -> 29.625966 | DJ5: =$DB$3/(1+$CI$10)^CJ5 -> 29.112137 | DK5: =$DB$3/(1+$CI$11)^CJ5 -> 28.010371 | DL5: =$DB$3/(1+$CI$12)^CJ5 -> 27.246494 | DM5: =$DB$3/(1+$CI$13)^CJ5 -> 26.510143 | DN5: =$DB$3/(1+$CI$14)^CJ5 -> 25.800088 | DO5: =$DB$3/(1+$CI$15)^CJ5 -> 25.115166 | DP5: =$DB$3/(1+$CI$16)^CJ5 -> 24.454275 | DQ5: =$DB$3/(1+$CI$17)^CJ5 -> 23.81637 | DR5: =$DB$3/(1+$CI$18)^CJ5 -> 23.20046 | DS5: =SUM(DE3:DE52) -> 897.05786 | DT5: =AVERAGE(CG3:CG27) -> 22.11996 | DU5: =$DT$3/(1+$CI$3)^CJ5 -> 38.003845 | DV5: =$DT$3/(1+$CI$4)^CJ5 -> 36.897008 | DW5: =$DT$3/(1+$CI$5)^CJ5 -> 35.832738 | DX5: =$DT$3/(1+$CI$6)^CJ5 -> 34.939869 | DY5: =$DT$3/(1+$CI$7)^CJ5 -> 34.809008 | DZ5: =$DT$3/(1+$CI$8)^CJ5 -> 33.823907 | EA5: =$DT$3/(1+$CI$9)^CJ5 -> 32.875629 | EB5: =$DT$3/(1+$CI$10)^CJ5 -> 32.305438 | EC5: =$DT$3/(1+$CI$11)^CJ5 -> 31.082819 | ED5: =$DT$3/(1+$CI$12)^CJ5 -> 30.235153 | EE5: =$DT$3/(1+$CI$13)^CJ5 -> 29.418032 | EF5: =$DT$3/(1+$CI$14)^CJ5 -> 28.630091 | EG5: =$DT$3/(1+$CI$15)^CJ5 -> 27.87004 | EH5: =$DT$3/(1+$CI$16)^CJ5 -> 27.136656 | EI5: =$DT$3/(1+$CI$17)^CJ5 -> 26.42878 | EJ5: =$DT$3/(1+$CI$18)^CJ5 -> 25.745311 | EK5: =SUM(DW3:DW52) -> 995.45585 | EM5: =$EL$3/(1+$CI$3)^CJ5 -> 30.286004 | EN5: =$EL$3/(1+$CI$4)^CJ5 -> 29.403943 | EO5: =$EL$3/(1+$CI$5)^CJ5 -> 28.555806 | EP5: =$EL$3/(1+$CI$6)^CJ5 -> 27.844261 | EQ5: =$EL$3/(1+$CI$7)^CJ5 -> 27.739976 | ER5: =$EL$3/(1+$CI$8)^CJ5 -> 26.954929 | ES5: =$EL$3/(1+$CI$9)^CJ5 -> 26.199228 | ET5: =$EL$3/(1+$CI$10)^CJ5 -> 25.744832 | EU5: =$EL$3/(1+$CI$11)^CJ5 -> 24.770503 | EV5: =$EL$3/(1+$CI$12)^CJ5 -> 24.094982 | EW5: =$EL$3/(1+$CI$13)^CJ5 -> 23.443802 | EX5: =$EL$3/(1+$CI$14)^CJ5 -> 22.815877 | EY5: =$EL$3/(1+$CI$15)^CJ5 -> 22.210177 | EZ5: =$EL$3/(1+$CI$16)^CJ5 -> 21.625729 | FA5: =$EL$3/(1+$CI$17)^CJ5 -> 21.061609 | FB5: =$EL$3/(1+$CI$18)^CJ5 -> 20.516939 | FC5: =SUM(EO3:EO52) -> 793.29813 | FE5: =$FD$3/(1+$CI$3)^CJ5 -> 21.469415 | FF5: =$FD$3/(1+$CI$4)^CJ5 -> 20.844132 | FG5: =$FD$3/(1+$CI$5)^CJ5 -> 20.242897 | FH5: =$FD$3/(1+$CI$6)^CJ5 -> 19.738491 | FI5: =$FD$3/(1+$CI$7)^CJ5 -> 19.664564 | FJ5: =$FD$3/(1+$CI$8)^CJ5 -> 19.108053 | FK5: =$FD$3/(1+$CI$9)^CJ5 -> 18.572345 | FL5: =$FD$3/(1+$CI$10)^CJ5 -> 18.250228 | FM5: =$FD$3/(1+$CI$11)^CJ5 -> 17.559537 | FN5: =$FD$3/(1+$CI$12)^CJ5 -> 17.080668 | FO5: =$FD$3/(1+$CI$13)^CJ5 -> 16.619053 | FP5: =$FD$3/(1+$CI$14)^CJ5 -> 16.173924 | FQ5: =$FD$3/(1+$CI$15)^CJ5 -> 15.744551 | FR5: =$FD$3/(1+$CI$16)^CJ5 -> 15.330242 | FS5: =$FD$3/(1+$CI$17)^CJ5 -> 14.930343 | FT5: =$FD$3/(1+$CI$18)^CJ5 -> 14.544233 | FU5: =SUM(FG3:FG52) -> 562.36033 | FW5: =$FV$3/(1+$CI$3)^CJ5 -> 0.039496091 | FX5: =$FV$3/(1+$CI$4)^CJ5 -> 0.038345793 | FY5: =$FV$3/(1+$CI$5)^CJ5 -> 0.037239734 | FZ5: =$FV$3/(1+$CI$6)^CJ5 -> 0.036311806 | GA5: =$FV$3/(1+$CI$7)^CJ5 -> 0.036175806 | GB5: =$FV$3/(1+$CI$8)^CJ5 -> 0.035152025 | GC5: =$FV$3/(1+$CI$9)^CJ5 -> 0.034166512 | GD5: =$FV$3/(1+$CI$10)^CJ5 -> 0.033573932 | GE5: =$FV$3/(1+$CI$11)^CJ5 -> 0.032303306 | GF5: =$FV$3/(1+$CI$12)^CJ5 -> 0.031422356 | GG5: =$FV$3/(1+$CI$13)^CJ5 -> 0.03057315 | GH5: =$FV$3/(1+$CI$14)^CJ5 -> 0.02975427 | GI5: =$FV$3/(1+$CI$15)^CJ5 -> 0.028964376 | GJ5: =$FV$3/(1+$CI$16)^CJ5 -> 0.028202195 | GK5: =$FV$3/(1+$CI$17)^CJ5 -> 0.027466523 | GL5: =$FV$3/(1+$CI$18)^CJ5 -> 0.026756218 | GM5: =SUM(FY3:FY52) -> 1.0345431
A6: Microsoft | B6: 37802 | C6: 17.097 | D6: 370.79032 | E6: 32.187 | F6: 1109.6 | G6: 6.022 | H6: =(D6/AI6) -> 49.235204 | I6: =(D6/G6) -> 61.57262 | J6: -1.954 | K6: -2.8 | L6: 1.5 | M6: 0 | N6: =(C6+L6+J6+K6+M6) -> 13.843 | P6: 13186000000 | Q6: =(P6-P5)/P5*100 -> 96.688544 | S6: 28.12 | T6: =(S6*P6) -> 370790320000 | U6: =(D6-D5)/D5*100 -> -23.785561 | V6: 64.912 | W6: =(V6-V5)/V5*100 -> 18.361839 | X6: 61.4 | Y6: =(X6-X5)/X5*100 -> 15.472138 | AA6: 0.1 | AB6: 64.912 | AC6: 54.842 | AD6: =(G5/AA6) -> 82.26 | AE6: =(D6-AC6-AD6) -> 233.68832 | AF6: =((((D6-AD6)/(G6)*AA6)-1)/(1+(D6-AD6)/(G6))) -> 0.077510956 | AG6: =(1+AF6)/(1+AA6) -> 0.97955541 | AI6: 7.531 | AJ6: 6.022 | AL6: 7.531 | AM6: =D6/AL6 -> 49.235204 | AN6: 6.022 | AO6: =D6/AN6 -> 61.57262 | AQ6: =$D$28/AL6 -> 367.93907 | AS6: =$D$28/AN6 -> 460.13769 | AV6: =(D6/AB6) -> 5.7121999 | AW6: =(D6/E6) -> 11.519878 | AX6: 3.512 | AY6: =(AB6-AX6) -> 61.4 | AZ6: =(D6/AY6) -> 6.0389303 | BB6: 13.843 | BC6: 7.506 | BD6: =(BB6/D6)*100 -> 3.7333769 | BE6: =(BC6/D6)*100 -> 2.0243247 | BG6: 28.12 | BH6: 13186000000 | BI6: =(BG6*BH6) -> 370790320000 | BJ6: 64.912 | BK6: =AY6 -> 61.4 | BL6: 58.973 | BM6: 13.974 | BN6: 2.846 | BO6: =(BL6-BM6-BN6) -> 42.153 | BP6: 49.048 | BQ6: =(BP6-BM6-BN6) -> 32.228 | BS6: =D6 -> 370.79032 | BT6: =E6 -> 32.187 | BU6: =N6 -> 13.843 | BV6: =G6 -> 6.022 | CE6: 37802 | CF6: 370.79032 | CG6: 13.843 | CH6: =(CG6/CF6) -> 0.037333769 | CI6: 0.0387 | CJ6: 4 | CK6: =$CG$27/(1+$CI$3)^CJ6 -> 4.7462819 | CL6: =$CG$27/(1+$CI$4)^CJ6 -> 4.5628726 | CM6: =$CG$27/(1+$CI$5)^CJ6 -> 4.3882375 | CN6: =$CG$27/(1+$CI$6)^CJ6 -> 4.2430534 | CO6: =$CG$27/(1+$CI$7)^CJ6 -> 4.2218779 | CP6: =$CG$27/(1+$CI$8)^CJ6 -> 4.0633275 | CQ6: =$CG$27/(1+$CI$9)^CJ6 -> 3.9121506 | CR6: =$CG$27/(1+$CI$10)^CJ6 -> 3.8219439 | CS6: =$CG$27/(1+$CI$11)^CJ6 -> 3.6303124 | CT6: =$CG$27/(1+$CI$12)^CJ6 -> 3.4989121 | CU6: =$CG$27/(1+$CI$13)^CJ6 -> 3.3734035 | CV6: =$CG$27/(1+$CI$14)^CJ6 -> 3.2534723 | CW6: =$CG$27/(1+$CI$15)^CJ6 -> 3.1388238 | CX6: =$CG$27/(1+$CI$16)^CJ6 -> 3.0291812 | CY6: =$CG$27/(1+$CI$17)^CJ6 -> 2.9242845 | CZ6: =$CG$27/(1+$CI$18)^CJ6 -> 2.8238893 | DA6: =SUM(CN3:CN52) -> 107.42414 | DB6: =AVERAGE(CG3:CG27) -> 22.11996 | DC6: =$DB$3/(1+$CI$3)^CJ6 -> 33.908191 | DD6: =$DB$3/(1+$CI$4)^CJ6 -> 32.597886 | DE6: =$DB$3/(1+$CI$5)^CJ6 -> 31.350265 | DF6: =$DB$3/(1+$CI$6)^CJ6 -> 30.313047 | DG6: =$DB$3/(1+$CI$7)^CJ6 -> 30.161766 | DH6: =$DB$3/(1+$CI$8)^CJ6 -> 29.029057 | DI6: =$DB$3/(1+$CI$9)^CJ6 -> 27.949025 | DJ6: =$DB$3/(1+$CI$10)^CJ6 -> 27.304574 | DK6: =$DB$3/(1+$CI$11)^CJ6 -> 25.935528 | DL6: =$DB$3/(1+$CI$12)^CJ6 -> 24.996784 | DM6: =$DB$3/(1+$CI$13)^CJ6 -> 24.10013 | DN6: =$DB$3/(1+$CI$14)^CJ6 -> 23.243322 | DO6: =$DB$3/(1+$CI$15)^CJ6 -> 22.424255 | DP6: =$DB$3/(1+$CI$16)^CJ6 -> 21.640951 | DQ6: =$DB$3/(1+$CI$17)^CJ6 -> 20.891553 | DR6: =$DB$3/(1+$CI$18)^CJ6 -> 20.174313 | DS6: =SUM(DF3:DF52) -> 767.45514 | DU6: =$DT$3/(1+$CI$3)^CJ6 -> 37.62757 | DV6: =$DT$3/(1+$CI$4)^CJ6 -> 36.173537 | DW6: =$DT$3/(1+$CI$5)^CJ6 -> 34.789066 | DX6: =$DT$3/(1+$CI$6)^CJ6 -> 33.638075 | DY6: =$DT$3/(1+$CI$7)^CJ6 -> 33.4702 | DZ6: =$DT$3/(1+$CI$8)^CJ6 -> 32.213244 | EA6: =$DT$3/(1+$CI$9)^CJ6 -> 31.014744 | EB6: =$DT$3/(1+$CI$10)^CJ6 -> 30.299604 | EC6: =$DT$3/(1+$CI$11)^CJ6 -> 28.780388 | ED6: =$DT$3/(1+$CI$12)^CJ6 -> 27.738673 | EE6: =$DT$3/(1+$CI$13)^CJ6 -> 26.743665 | EF6: =$DT$3/(1+$CI$14)^CJ6 -> 25.792875 | EG6: =$DT$3/(1+$CI$15)^CJ6 -> 24.883965 | EH6: =$DT$3/(1+$CI$16)^CJ6 -> 24.01474 | EI6: =$DT$3/(1+$CI$17)^CJ6 -> 23.18314 | EJ6: =$DT$3/(1+$CI$18)^CJ6 -> 22.387227 | EK6: =SUM(DX3:DX52) -> 851.63704 | EM6: =$EL$3/(1+$CI$3)^CJ6 -> 29.986142 | EN6: =$EL$3/(1+$CI$4)^CJ6 -> 28.827396 | EO6: =$EL$3/(1+$CI$5)^CJ6 -> 27.724083 | EP6: =$EL$3/(1+$CI$6)^CJ6 -> 26.806837 | EQ6: =$EL$3/(1+$CI$7)^CJ6 -> 26.673054 | ER6: =$EL$3/(1+$CI$8)^CJ6 -> 25.671361 | ES6: =$EL$3/(1+$CI$9)^CJ6 -> 24.716253 | ET6: =$EL$3/(1+$CI$10)^CJ6 -> 24.146344 | EU6: =$EL$3/(1+$CI$11)^CJ6 -> 22.935651 | EV6: =$EL$3/(1+$CI$12)^CJ6 -> 22.105488 | EW6: =$EL$3/(1+$CI$13)^CJ6 -> 21.312547 | EX6: =$EL$3/(1+$CI$14)^CJ6 -> 20.554844 | EY6: =$EL$3/(1+$CI$15)^CJ6 -> 19.830515 | EZ6: =$EL$3/(1+$CI$16)^CJ6 -> 19.137814 | FA6: =$EL$3/(1+$CI$17)^CJ6 -> 18.475095 | FB6: =$EL$3/(1+$CI$18)^CJ6 -> 17.840817 | FC6: =SUM(EP3:EP52) -> 678.68613 | FE6: =$FD$3/(1+$CI$3)^CJ6 -> 21.256847 | FF6: =$FD$3/(1+$CI$4)^CJ6 -> 20.435424 | FG6: =$FD$3/(1+$CI$5)^CJ6 -> 19.653298 | FH6: =$FD$3/(1+$CI$6)^CJ6 -> 19.003072 | FI6: =$FD$3/(1+$CI$7)^CJ6 -> 18.908235 | FJ6: =$FD$3/(1+$CI$8)^CJ6 -> 18.198146 | FK6: =$FD$3/(1+$CI$9)^CJ6 -> 17.52108 | FL6: =$FD$3/(1+$CI$10)^CJ6 -> 17.117078 | FM6: =$FD$3/(1+$CI$11)^CJ6 -> 16.258831 | FN6: =$FD$3/(1+$CI$12)^CJ6 -> 15.670337 | FO6: =$FD$3/(1+$CI$13)^CJ6 -> 15.10823 | FP6: =$FD$3/(1+$CI$14)^CJ6 -> 14.571103 | FQ6: =$FD$3/(1+$CI$15)^CJ6 -> 14.057634 | FR6: =$FD$3/(1+$CI$16)^CJ6 -> 13.566586 | FS6: =$FD$3/(1+$CI$17)^CJ6 -> 13.096792 | FT6: =$FD$3/(1+$CI$18)^CJ6 -> 12.647159 | FU6: =SUM(FH3:FH52) -> 481.11314 | FW6: =$FV$3/(1+$CI$3)^CJ6 -> 0.039105041 | FX6: =$FV$3/(1+$CI$4)^CJ6 -> 0.037593915 | FY6: =$FV$3/(1+$CI$5)^CJ6 -> 0.036155081 | FZ6: =$FV$3/(1+$CI$6)^CJ6 -> 0.034958896 | GA6: =$FV$3/(1+$CI$7)^CJ6 -> 0.034784429 | GB6: =$FV$3/(1+$CI$8)^CJ6 -> 0.033478119 | GC6: =$FV$3/(1+$CI$9)^CJ6 -> 0.032232558 | GD6: =$FV$3/(1+$CI$10)^CJ6 -> 0.031489338 | GE6: =$FV$3/(1+$CI$11)^CJ6 -> 0.029910469 | GF6: =$FV$3/(1+$CI$12)^CJ6 -> 0.02882785 | GG6: =$FV$3/(1+$CI$13)^CJ6 -> 0.027793773 | GH6: =$FV$3/(1+$CI$14)^CJ6 -> 0.026805649 | GI6: =$FV$3/(1+$CI$15)^CJ6 -> 0.02586105 | GJ6: =$FV$3/(1+$CI$16)^CJ6 -> 0.024957695 | GK6: =$FV$3/(1+$CI$17)^CJ6 -> 0.024093441 | GL6: =$FV$3/(1+$CI$18)^CJ6 -> 0.023266276 | GM6: =SUM(FZ3:FZ52) -> 0.88507713
A7: Microsoft | B7: 38168 | C7: 15.163 | D7: 355.80196 | E7: 36.835 | F7: 1213.5 | G7: 5.006 | H7: =(D7/AI7) -> 43.560476 | I7: =(D7/G7) -> 71.075103 | J7: -1.113 | K7: -2.5 | L7: 1.963 | M7: 0 | N7: =(C7+L7+J7+K7+M7) -> 13.513 | P7: 11875900000 | Q7: =(P7-P6)/P6*100 -> -9.9355377 | S7: 29.96 | T7: =(S7*P7) -> 355801964000 | U7: =(D7-D6)/D6*100 -> -4.0422727 | V7: 74.825 | W7: =(V7-V6)/V6*100 -> 15.271444 | X7: 71.141 | Y7: =(X7-X6)/X6*100 -> 15.864821 | AA7: 0.1 | AB7: 74.825 | AC7: 64.912 | AD7: =(G6/AA7) -> 60.22 | AE7: =(D7-AC7-AD7) -> 230.66996 | AF7: =((((D7-AD7)/(G7)*AA7)-1)/(1+(D7-AD7)/(G7))) -> 0.081680571 | AG7: =(1+AF7)/(1+AA7) -> 0.98334597 | AI7: 8.168 | AJ7: 5.006 | AL7: 8.168 | AM7: =D7/AL7 -> 43.560476 | AN7: 5.006 | AO7: =D7/AN7 -> 71.075103 | AQ7: =$D$28/AL7 -> 339.24451 | AS7: =$D$28/AN7 -> 553.5256 | AV7: =(D7/AB7) -> 4.7551215 | AW7: =(D7/E7) -> 9.6593448 | AX7: 3.684 | AY7: =(AB7-AX7) -> 71.141 | AZ7: =(D7/AY7) -> 5.001363 | BB7: 13.513 | BC7: 9.582 | BD7: =(BB7/D7)*100 -> 3.7978992 | BE7: =(BC7/D7)*100 -> 2.6930711 | BG7: 29.96 | BH7: 11875900000 | BI7: =(BG7*BH7) -> 355801964000 | BJ7: 74.825 | BK7: =AY7 -> 71.141 | BL7: 70.566 | BM7: 14.969 | BN7: 2.595 | BO7: =(BL7-BM7-BN7) -> 53.002 | BP7: 60.592 | BQ7: =(BP7-BM7-BN7) -> 43.028 | BS7: =D7 -> 355.80196 | BT7: =E7 -> 36.835 | BU7: =N7 -> 13.513 | BV7: 8.168 | CE7: 38168 | CF7: 355.80196 | CG7: 13.513 | CH7: =(CG7/CF7) -> 0.037978992 | CI7: 0.04 | CJ7: 5 | CK7: =$CG$27/(1+$CI$3)^CJ7 -> 4.699289 | CL7: =$CG$27/(1+$CI$4)^CJ7 -> 4.4734045 | CM7: =$CG$27/(1+$CI$5)^CJ7 -> 4.2604248 | CN7: =$CG$27/(1+$CI$6)^CJ7 -> 4.0849653 | CO7: =$CG$27/(1+$CI$7)^CJ7 -> 4.059498 | CP7: =$CG$27/(1+$CI$8)^CJ7 -> 3.8698357 | CQ7: =$CG$27/(1+$CI$9)^CJ7 -> 3.6907081 | CR7: =$CG$27/(1+$CI$10)^CJ7 -> 3.5846407 | CS7: =$CG$27/(1+$CI$11)^CJ7 -> 3.3614004 | CT7: =$CG$27/(1+$CI$12)^CJ7 -> 3.2100111 | CU7: =$CG$27/(1+$CI$13)^CJ7 -> 3.0667304 | CV7: =$CG$27/(1+$CI$14)^CJ7 -> 2.9310561 | CW7: =$CG$27/(1+$CI$15)^CJ7 -> 2.8025212 | CX7: =$CG$27/(1+$CI$16)^CJ7 -> 2.6806913 | CY7: =$CG$27/(1+$CI$17)^CJ7 -> 2.5651618 | CZ7: =$CG$27/(1+$CI$18)^CJ7 -> 2.4555559 | DA7: =SUM(CO3:CO52) -> 105.07177 | DC7: =$DB$3/(1+$CI$3)^CJ7 -> 33.572467 | DD7: =$DB$3/(1+$CI$4)^CJ7 -> 31.958712 | DE7: =$DB$3/(1+$CI$5)^CJ7 -> 30.437151 | DF7: =$DB$3/(1+$CI$6)^CJ7 -> 29.18364 | DG7: =$DB$3/(1+$CI$7)^CJ7 -> 29.001698 | DH7: =$DB$3/(1+$CI$8)^CJ7 -> 27.646721 | DI7: =$DB$3/(1+$CI$9)^CJ7 -> 26.367005 | DJ7: =$DB$3/(1+$CI$10)^CJ7 -> 25.609242 | DK7: =$DB$3/(1+$CI$11)^CJ7 -> 24.014378 | DL7: =$DB$3/(1+$CI$12)^CJ7 -> 22.932829 | DM7: =$DB$3/(1+$CI$13)^CJ7 -> 21.909209 | DN7: =$DB$3/(1+$CI$14)^CJ7 -> 20.93993 | DO7: =$DB$3/(1+$CI$15)^CJ7 -> 20.021657 | DP7: =$DB$3/(1+$CI$16)^CJ7 -> 19.151284 | DQ7: =$DB$3/(1+$CI$17)^CJ7 -> 18.325923 | DR7: =$DB$3/(1+$CI$18)^CJ7 -> 17.542881 | DS7: =SUM(DG3:DG52) -> 750.64941 | DU7: =$DT$3/(1+$CI$3)^CJ7 -> 37.25502 | DV7: =$DT$3/(1+$CI$4)^CJ7 -> 35.464252 | DW7: =$DT$3/(1+$CI$5)^CJ7 -> 33.775792 | DX7: =$DT$3/(1+$CI$6)^CJ7 -> 32.384784 | DY7: =$DT$3/(1+$CI$7)^CJ7 -> 32.182885 | DZ7: =$DT$3/(1+$CI$8)^CJ7 -> 30.67928 | EA7: =$DT$3/(1+$CI$9)^CJ7 -> 29.259193 | EB7: =$DT$3/(1+$CI$10)^CJ7 -> 28.418312 | EC7: =$DT$3/(1+$CI$11)^CJ7 -> 26.648507 | ED7: =$DT$3/(1+$CI$12)^CJ7 -> 25.448323 | EE7: =$DT$3/(1+$CI$13)^CJ7 -> 24.312423 | EF7: =$DT$3/(1+$CI$14)^CJ7 -> 23.236824 | EG7: =$DT$3/(1+$CI$15)^CJ7 -> 22.217826 | EH7: =$DT$3/(1+$CI$16)^CJ7 -> 21.251982 | EI7: =$DT$3/(1+$CI$17)^CJ7 -> 20.336088 | EJ7: =$DT$3/(1+$CI$18)^CJ7 -> 19.467154 | EK7: =SUM(DY3:DY52) -> 832.98789 | EM7: =$EL$3/(1+$CI$3)^CJ7 -> 29.68925 | EN7: =$EL$3/(1+$CI$4)^CJ7 -> 28.262152 | EO7: =$EL$3/(1+$CI$5)^CJ7 -> 26.916586 | EP7: =$EL$3/(1+$CI$6)^CJ7 -> 25.808065 | EQ7: =$EL$3/(1+$CI$7)^CJ7 -> 25.647167 | ER7: =$EL$3/(1+$CI$8)^CJ7 -> 24.448915 | ES7: =$EL$3/(1+$CI$9)^CJ7 -> 23.31722 | ET7: =$EL$3/(1+$CI$10)^CJ7 -> 22.647105 | EU7: =$EL$3/(1+$CI$11)^CJ7 -> 21.236714 | EV7: =$EL$3/(1+$CI$12)^CJ7 -> 20.280264 | EW7: =$EL$3/(1+$CI$13)^CJ7 -> 19.375043 | EX7: =$EL$3/(1+$CI$14)^CJ7 -> 18.517877 | EY7: =$EL$3/(1+$CI$15)^CJ7 -> 17.705817 | EZ7: =$EL$3/(1+$CI$16)^CJ7 -> 16.936118 | FA7: =$EL$3/(1+$CI$17)^CJ7 -> 16.206224 | FB7: =$EL$3/(1+$CI$18)^CJ7 -> 15.513754 | FC7: =SUM(EQ3:EQ52) -> 663.82426 | FE7: =$FD$3/(1+$CI$3)^CJ7 -> 21.046383 | FF7: =$FD$3/(1+$CI$4)^CJ7 -> 20.034729 | FG7: =$FD$3/(1+$CI$5)^CJ7 -> 19.080872 | FH7: =$FD$3/(1+$CI$6)^CJ7 -> 18.295053 | FI7: =$FD$3/(1+$CI$7)^CJ7 -> 18.180995 | FJ7: =$FD$3/(1+$CI$8)^CJ7 -> 17.331567 | FK7: =$FD$3/(1+$CI$9)^CJ7 -> 16.529321 | FL7: =$FD$3/(1+$CI$10)^CJ7 -> 16.054284 | FM7: =$FD$3/(1+$CI$11)^CJ7 -> 15.054473 | FN7: =$FD$3/(1+$CI$12)^CJ7 -> 14.376456 | FO7: =$FD$3/(1+$CI$13)^CJ7 -> 13.734755 | FP7: =$FD$3/(1+$CI$14)^CJ7 -> 13.12712 | FQ7: =$FD$3/(1+$CI$15)^CJ7 -> 12.551459 | FR7: =$FD$3/(1+$CI$16)^CJ7 -> 12.005828 | FS7: =$FD$3/(1+$CI$17)^CJ7 -> 11.488414 | FT7: =$FD$3/(1+$CI$18)^CJ7 -> 10.997529 | FU7: =SUM(FI3:FI52) -> 470.57772 | FW7: =$FV$3/(1+$CI$3)^CJ7 -> 0.038717862 | FX7: =$FV$3/(1+$CI$4)^CJ7 -> 0.036856779 | FY7: =$FV$3/(1+$CI$5)^CJ7 -> 0.035102021 | FZ7: =$FV$3/(1+$CI$6)^CJ7 -> 0.033656394 | GA7: =$FV$3/(1+$CI$7)^CJ7 -> 0.033446567 | GB7: =$FV$3/(1+$CI$8)^CJ7 -> 0.031883922 | GC7: =$FV$3/(1+$CI$9)^CJ7 -> 0.030408074 | GD7: =$FV$3/(1+$CI$10)^CJ7 -> 0.029534175 | GE7: =$FV$3/(1+$CI$11)^CJ7 -> 0.027694878 | GF7: =$FV$3/(1+$CI$12)^CJ7 -> 0.026447568 | GG7: =$FV$3/(1+$CI$13)^CJ7 -> 0.025267066 | GH7: =$FV$3/(1+$CI$14)^CJ7 -> 0.024149233 | GI7: =$FV$3/(1+$CI$15)^CJ7 -> 0.023090223 | GJ7: =$FV$3/(1+$CI$16)^CJ7 -> 0.022086455 | GK7: =$FV$3/(1+$CI$17)^CJ7 -> 0.021134598 | GL7: =$FV$3/(1+$CI$18)^CJ7 -> 0.020231544 | GM7: =SUM(GA3:GA52) -> 0.8656957
A8: Microsoft | B8: 38533 | C8: 20.731 | D8: 350.18439 | E8: 39.788 | F8: 1254.4 | G8: 10.187 | H8: =(D8/AI8) -> 28.577149 | I8: =(D8/G8) -> 34.375615 | J8: -1.019 | K8: -4.3 | L8: 0.174 | M8: 0 | N8: =(C8+L8+J8+K8+M8) -> 15.586 | P8: 11680600000 | Q8: =(P8-P7)/P7*100 -> -1.6445069 | S8: 29.98 | T8: =(S8*P8) -> 350184388000 | U8: =(D8-D7)/D7*100 -> -1.5788491 | V8: 48.115 | W8: =(V8-V7)/V7*100 -> -35.696625 | X8: 44.307 | Y8: =(X8-X7)/X7*100 -> -37.719459 | AA8: 0.1 | AB8: 48.115 | AC8: 74.825 | AD8: =(G7/AA8) -> 50.06 | AE8: =(D8-AC8-AD8) -> 225.29939 | AF8: =((((D8-AD8)/(G8)*AA8)-1)/(1+(D8-AD8)/(G8))) -> 0.063888853 | AG8: =(1+AF8)/(1+AA8) -> 0.96717168 | AI8: 12.254 | AJ8: 10.187 | AL8: 12.254 | AM8: =D8/AL8 -> 28.577149 | AN8: 10.187 | AO8: =D8/AN8 -> 34.375615 | AQ8: =$D$28/AL8 -> 226.12609 | AS8: =$D$28/AN8 -> 272.00836 | AV8: =(D8/AB8) -> 7.278071 | AW8: =(D8/E8) -> 8.8012564 | AX8: 3.808 | AY8: =(AB8-AX8) -> 44.307 | AZ8: =(D8/AY8) -> 7.9035906 | BB8: 15.586 | BC8: -4.487 | BD8: =(BB8/D8)*100 -> 4.4507981 | BE8: =(BC8/D8)*100 -> -1.281325 | BG8: 29.98 | BH8: 11680600000 | BI8: =(BG8*BH8) -> 350184388000 | BJ8: 48.115 | BK8: =AY8 -> 44.307 | BL8: 48.737 | BM8: 16.877 | BN8: 5.823 | BO8: =(BL8-BM8-BN8) -> 26.037 | BP8: 37.751 | BQ8: =(BP8-BM8-BN8) -> 15.051 | BS8: =D8 -> 350.18439 | BT8: =E8 -> 39.788 | BU8: =N8 -> 15.586 | BV8: =G8 -> 10.187 | CE8: 38533 | CF8: 350.18439 | CG8: 15.586 | CH8: =(CG8/CF8) -> 0.044507981 | CI8: 0.05 | CJ8: 6 | CK8: =$CG$27/(1+$CI$3)^CJ8 -> 4.6527614 | CL8: =$CG$27/(1+$CI$4)^CJ8 -> 4.3856907 | CM8: =$CG$27/(1+$CI$5)^CJ8 -> 4.1363347 | CN8: =$CG$27/(1+$CI$6)^CJ8 -> 3.9327672 | CO8: =$CG$27/(1+$CI$7)^CJ8 -> 3.9033634 | CP8: =$CG$27/(1+$CI$8)^CJ8 -> 3.6855578 | CQ8: =$CG$27/(1+$CI$9)^CJ8 -> 3.4818001 | CR8: =$CG$27/(1+$CI$10)^CJ8 -> 3.3620716 | CS8: =$CG$27/(1+$CI$11)^CJ8 -> 3.1124078 | CT8: =$CG$27/(1+$CI$12)^CJ8 -> 2.9449643 | CU8: =$CG$27/(1+$CI$13)^CJ8 -> 2.7879367 | CV8: =$CG$27/(1+$CI$14)^CJ8 -> 2.6405911 | CW8: =$CG$27/(1+$CI$15)^CJ8 -> 2.5022511 | CX8: =$CG$27/(1+$CI$16)^CJ8 -> 2.3722932 | CY8: =$CG$27/(1+$CI$17)^CJ8 -> 2.250142 | CZ8: =$CG$27/(1+$CI$18)^CJ8 -> 2.135266 | DA8: =SUM(CP3:CP52) -> 89.464452 | DC8: =$DB$3/(1+$CI$3)^CJ8 -> 33.240066 | DD8: =$DB$3/(1+$CI$4)^CJ8 -> 31.33207 | DE8: =$DB$3/(1+$CI$5)^CJ8 -> 29.550632 | DF8: =$DB$3/(1+$CI$6)^CJ8 -> 28.096313 | DG8: =$DB$3/(1+$CI$7)^CJ8 -> 27.886248 | DH8: =$DB$3/(1+$CI$8)^CJ8 -> 26.33021 | DI8: =$DB$3/(1+$CI$9)^CJ8 -> 24.874533 | DJ8: =$DB$3/(1+$CI$10)^CJ8 -> 24.019173 | DK8: =$DB$3/(1+$CI$11)^CJ8 -> 22.235535 | DL8: =$DB$3/(1+$CI$12)^CJ8 -> 21.039293 | DM8: =$DB$3/(1+$CI$13)^CJ8 -> 19.917463 | DN8: =$DB$3/(1+$CI$14)^CJ8 -> 18.864802 | DO8: =$DB$3/(1+$CI$15)^CJ8 -> 17.876479 | DP8: =$DB$3/(1+$CI$16)^CJ8 -> 16.948039 | DQ8: =$DB$3/(1+$CI$17)^CJ8 -> 16.075371 | DR8: =$DB$3/(1+$CI$18)^CJ8 -> 15.254679 | DS8: =SUM(DH3:DH52) -> 639.14825 | DU8: =$DT$3/(1+$CI$3)^CJ8 -> 36.886158 | DV8: =$DT$3/(1+$CI$4)^CJ8 -> 34.768875 | DW8: =$DT$3/(1+$CI$5)^CJ8 -> 32.792031 | DX8: =$DT$3/(1+$CI$6)^CJ8 -> 31.178188 | DY8: =$DT$3/(1+$CI$7)^CJ8 -> 30.945081 | DZ8: =$DT$3/(1+$CI$8)^CJ8 -> 29.218362 | EA8: =$DT$3/(1+$CI$9)^CJ8 -> 27.603012 | EB8: =$DT$3/(1+$CI$10)^CJ8 -> 26.653828 | EC8: =$DT$3/(1+$CI$11)^CJ8 -> 24.674544 | ED8: =$DT$3/(1+$CI$12)^CJ8 -> 23.347086 | EE8: =$DT$3/(1+$CI$13)^CJ8 -> 22.102203 | EF8: =$DT$3/(1+$CI$14)^CJ8 -> 20.934076 | EG8: =$DT$3/(1+$CI$15)^CJ8 -> 19.837344 | EH8: =$DT$3/(1+$CI$16)^CJ8 -> 18.807064 | EI8: =$DT$3/(1+$CI$17)^CJ8 -> 17.838674 | EJ8: =$DT$3/(1+$CI$18)^CJ8 -> 16.92796 | EK8: =SUM(DZ3:DZ52) -> 709.25621 | EM8: =$EL$3/(1+$CI$3)^CJ8 -> 29.395297 | EN8: =$EL$3/(1+$CI$4)^CJ8 -> 27.707993 | EO8: =$EL$3/(1+$CI$5)^CJ8 -> 26.132608 | EP8: =$EL$3/(1+$CI$6)^CJ8 -> 24.846505 | EQ8: =$EL$3/(1+$CI$7)^CJ8 -> 24.660737 | ER8: =$EL$3/(1+$CI$8)^CJ8 -> 23.284681 | ES8: =$EL$3/(1+$CI$9)^CJ8 -> 21.997377 | ET8: =$EL$3/(1+$CI$10)^CJ8 -> 21.240954 | EU8: =$EL$3/(1+$CI$11)^CJ8 -> 19.663624 | EV8: =$EL$3/(1+$CI$12)^CJ8 -> 18.605747 | EW8: =$EL$3/(1+$CI$13)^CJ8 -> 17.613675 | EX8: =$EL$3/(1+$CI$14)^CJ8 -> 16.682772 | EY8: =$EL$3/(1+$CI$15)^CJ8 -> 15.808766 | EZ8: =$EL$3/(1+$CI$16)^CJ8 -> 14.987715 | FA8: =$EL$3/(1+$CI$17)^CJ8 -> 14.215986 | FB8: =$EL$3/(1+$CI$18)^CJ8 -> 13.490221 | FC8: =SUM(ER3:ER52) -> 565.22007 | FE8: =$FD$3/(1+$CI$3)^CJ8 -> 20.838003 | FF8: =$FD$3/(1+$CI$4)^CJ8 -> 19.641891 | FG8: =$FD$3/(1+$CI$5)^CJ8 -> 18.525118 | FH8: =$FD$3/(1+$CI$6)^CJ8 -> 17.613414 | FI8: =$FD$3/(1+$CI$7)^CJ8 -> 17.481726 | FJ8: =$FD$3/(1+$CI$8)^CJ8 -> 16.506255 | FK8: =$FD$3/(1+$CI$9)^CJ8 -> 15.593699 | FL8: =$FD$3/(1+$CI$10)^CJ8 -> 15.057479 | FM8: =$FD$3/(1+$CI$11)^CJ8 -> 13.939327 | FN8: =$FD$3/(1+$CI$12)^CJ8 -> 13.189409 | FO8: =$FD$3/(1+$CI$13)^CJ8 -> 12.486141 | FP8: =$FD$3/(1+$CI$14)^CJ8 -> 11.826234 | FQ8: =$FD$3/(1+$CI$15)^CJ8 -> 11.20666 | FR8: =$FD$3/(1+$CI$16)^CJ8 -> 10.624627 | FS8: =$FD$3/(1+$CI$17)^CJ8 -> 10.077556 | FT8: =$FD$3/(1+$CI$18)^CJ8 -> 9.5630691 | FU8: =SUM(FJ3:FJ52) -> 400.6783 | FW8: =$FV$3/(1+$CI$3)^CJ8 -> 0.038334517 | FX8: =$FV$3/(1+$CI$4)^CJ8 -> 0.036134097 | FY8: =$FV$3/(1+$CI$5)^CJ8 -> 0.034079632 | FZ8: =$FV$3/(1+$CI$6)^CJ8 -> 0.03240242 | GA8: =$FV$3/(1+$CI$7)^CJ8 -> 0.03216016 | GB8: =$FV$3/(1+$CI$8)^CJ8 -> 0.03036564 | GC8: =$FV$3/(1+$CI$9)^CJ8 -> 0.028686862 | GD8: =$FV$3/(1+$CI$10)^CJ8 -> 0.027700408 | GE8: =$FV$3/(1+$CI$11)^CJ8 -> 0.025643406 | GF8: =$FV$3/(1+$CI$12)^CJ8 -> 0.024263824 | GG8: =$FV$3/(1+$CI$13)^CJ8 -> 0.02297006 | GH8: =$FV$3/(1+$CI$14)^CJ8 -> 0.021756066 | GI8: =$FV$3/(1+$CI$15)^CJ8 -> 0.02061627 | GJ8: =$FV$3/(1+$CI$16)^CJ8 -> 0.019545536 | GK8: =$FV$3/(1+$CI$17)^CJ8 -> 0.018539121 | GL8: =$FV$3/(1+$CI$18)^CJ8 -> 0.017592647 | GM8: =SUM(GB3:GB52) -> 0.73710562
A9: Microsoft | B9: 38898 | C9: 21.69 | D9: 308.25907 | E9: 44.282 | F9: 1424.7 | G9: 10.809 | H9: =(D9/AI9) -> 24.466948 | I9: =(D9/G9) -> 28.518741 | J9: -2.227 | K9: -4.8 | L9: -2.397 | M9: 0 | N9: =(C9+L9+J9+K9+M9) -> 12.266 | P9: 10946700000 | Q9: =(P9-P8)/P8*100 -> -6.2830677 | S9: 28.16 | T9: =(S9*P9) -> 308259072000 | U9: =(D9-D8)/D8*100 -> -11.972354 | V9: 40.104 | W9: =(V9-V8)/V8*100 -> -16.649693 | X9: 35.699 | Y9: =(X9-X8)/X8*100 -> -19.428081 | AA9: 0.1 | AB9: 40.104 | AC9: 48.115 | AD9: =(G8/AA9) -> 101.87 | AE9: =(D9-AC9-AD9) -> 158.27407 | AF9: =((((D9-AD9)/(G9)*AA9)-1)/(1+(D9-AD9)/(G9))) -> 0.045257801 | AG9: =(1+AF9)/(1+AA9) -> 0.95023436 | AI9: 12.599 | AJ9: 10.809 | AL9: 12.599 | AM9: =D9/AL9 -> 24.466948 | AN9: 10.809 | AO9: =D9/AN9 -> 28.518741 | AQ9: =$D$28/AL9 -> 219.93406 | AS9: =$D$28/AN9 -> 256.35574 | AV9: =(D9/AB9) -> 7.6864919 | AW9: =(D9/E9) -> 6.9612726 | AX9: 4.405 | AY9: =(AB9-AX9) -> 35.699 | AZ9: =(D9/AY9) -> 8.6349498 | BB9: 12.177 | BC9: 18.88 | BD9: =(BB9/D9)*100 -> 3.9502487 | BE9: =(BC9/D9)*100 -> 6.1247184 | BG9: 28.16 | BH9: 10946700000 | BI9: =(BG9*BH9) -> 308259072000 | BJ9: 40.104 | BK9: =AY9 -> 35.699 | BL9: 49.01 | BM9: 22.442 | BN9: 7.051 | BO9: =(BL9-BM9-BN9) -> 19.517 | BP9: 34.161 | BQ9: =(BP9-BM9-BN9) -> 4.668 | BS9: =D9 -> 308.25907 | BT9: =E9 -> 44.282 | BU9: =N9 -> 12.266 | BV9: =G9 -> 10.809 | BW9: =((BS9/BS4)^(1/5)-1)*100 -> -11.259158 | BX9: =((BT9/BT4)^(1/5)-1)*100 -> 11.849765 | BY9: =((BU9/BU4)^(1/5)-1)*100 -> -0.086194407 | BZ9: =((BV9/BV4)^(1/5)-1)*100 -> 6.4280111 | CE9: 38898 | CF9: 308.25907 | CG9: 12.177 | CH9: =(CG9/CF9) -> 0.039502487 | CI9: 0.06 | CJ9: 7 | CK9: =$CG$27/(1+$CI$3)^CJ9 -> 4.6066945 | CL9: =$CG$27/(1+$CI$4)^CJ9 -> 4.2996967 | CM9: =$CG$27/(1+$CI$5)^CJ9 -> 4.015859 | CN9: =$CG$27/(1+$CI$6)^CJ9 -> 3.7862397 | CO9: =$CG$27/(1+$CI$7)^CJ9 -> 3.7532341 | CP9: =$CG$27/(1+$CI$8)^CJ9 -> 3.5100551 | CQ9: =$CG$27/(1+$CI$9)^CJ9 -> 3.2847171 | CR9: =$CG$27/(1+$CI$10)^CJ9 -> 3.1533217 | CS9: =$CG$27/(1+$CI$11)^CJ9 -> 2.8818591 | CT9: =$CG$27/(1+$CI$12)^CJ9 -> 2.7018021 | CU9: =$CG$27/(1+$CI$13)^CJ9 -> 2.5344879 | CV9: =$CG$27/(1+$CI$14)^CJ9 -> 2.3789109 | CW9: =$CG$27/(1+$CI$15)^CJ9 -> 2.2341528 | CX9: =$CG$27/(1+$CI$16)^CJ9 -> 2.0993745 | CY9: =$CG$27/(1+$CI$17)^CJ9 -> 1.9738087 | CZ9: =$CG$27/(1+$CI$18)^CJ9 -> 1.856753 | DA9: =SUM(CQ3:CQ52) -> 77.367649 | DC9: =$DB$3/(1+$CI$3)^CJ9 -> 32.910957 | DD9: =$DB$3/(1+$CI$4)^CJ9 -> 30.717716 | DE9: =$DB$3/(1+$CI$5)^CJ9 -> 28.689934 | DF9: =$DB$3/(1+$CI$6)^CJ9 -> 27.049497 | DG9: =$DB$3/(1+$CI$7)^CJ9 -> 26.8137 | DH9: =$DB$3/(1+$CI$8)^CJ9 -> 25.076391 | DI9: =$DB$3/(1+$CI$9)^CJ9 -> 23.46654 | DJ9: =$DB$3/(1+$CI$10)^CJ9 -> 22.527831 | DK9: =$DB$3/(1+$CI$11)^CJ9 -> 20.588459 | DL9: =$DB$3/(1+$CI$12)^CJ9 -> 19.302103 | DM9: =$DB$3/(1+$CI$13)^CJ9 -> 18.106784 | DN9: =$DB$3/(1+$CI$14)^CJ9 -> 16.995317 | DO9: =$DB$3/(1+$CI$15)^CJ9 -> 15.961142 | DP9: =$DB$3/(1+$CI$16)^CJ9 -> 14.998265 | DQ9: =$DB$3/(1+$CI$17)^CJ9 -> 14.101203 | DR9: =$DB$3/(1+$CI$18)^CJ9 -> 13.264938 | DS9: =SUM(DI3:DI52) -> 552.72677 | DU9: =$DT$3/(1+$CI$3)^CJ9 -> 36.520949 | DV9: =$DT$3/(1+$CI$4)^CJ9 -> 34.087132 | DW9: =$DT$3/(1+$CI$5)^CJ9 -> 31.836923 | DX9: =$DT$3/(1+$CI$6)^CJ9 -> 30.016548 | DY9: =$DT$3/(1+$CI$7)^CJ9 -> 29.754886 | DZ9: =$DT$3/(1+$CI$8)^CJ9 -> 27.827012 | EA9: =$DT$3/(1+$CI$9)^CJ9 -> 26.040577 | EB9: =$DT$3/(1+$CI$10)^CJ9 -> 24.998901 | EC9: =$DT$3/(1+$CI$11)^CJ9 -> 22.8468 | ED9: =$DT$3/(1+$CI$12)^CJ9 -> 21.419345 | EE9: =$DT$3/(1+$CI$13)^CJ9 -> 20.092911 | EF9: =$DT$3/(1+$CI$14)^CJ9 -> 18.859528 | EG9: =$DT$3/(1+$CI$15)^CJ9 -> 17.711914 | EH9: =$DT$3/(1+$CI$16)^CJ9 -> 16.64342 | EI9: =$DT$3/(1+$CI$17)^CJ9 -> 15.647959 | EJ9: =$DT$3/(1+$CI$18)^CJ9 -> 14.719965 | EK9: =SUM(EA3:EA52) -> 613.35518 | EM9: =$EL$3/(1+$CI$3)^CJ9 -> 29.104254 | EN9: =$EL$3/(1+$CI$4)^CJ9 -> 27.164699 | EO9: =$EL$3/(1+$CI$5)^CJ9 -> 25.371464 | EP9: =$EL$3/(1+$CI$6)^CJ9 -> 23.920771 | EQ9: =$EL$3/(1+$CI$7)^CJ9 -> 23.712247 | ER9: =$EL$3/(1+$CI$8)^CJ9 -> 22.175887 | ES9: =$EL$3/(1+$CI$9)^CJ9 -> 20.752243 | ET9: =$EL$3/(1+$CI$10)^CJ9 -> 19.922111 | EU9: =$EL$3/(1+$CI$11)^CJ9 -> 18.207059 | EV9: =$EL$3/(1+$CI$12)^CJ9 -> 17.069492 | EW9: =$EL$3/(1+$CI$13)^CJ9 -> 16.012432 | EX9: =$EL$3/(1+$CI$14)^CJ9 -> 15.029525 | EY9: =$EL$3/(1+$CI$15)^CJ9 -> 14.114969 | EZ9: =$EL$3/(1+$CI$16)^CJ9 -> 13.263465 | FA9: =$EL$3/(1+$CI$17)^CJ9 -> 12.470163 | FB9: =$EL$3/(1+$CI$18)^CJ9 -> 11.730627 | FC9: =SUM(ES3:ES52) -> 488.79468 | FE9: =$FD$3/(1+$CI$3)^CJ9 -> 20.631686 | FF9: =$FD$3/(1+$CI$4)^CJ9 -> 19.256756 | FG9: =$FD$3/(1+$CI$5)^CJ9 -> 17.985552 | FH9: =$FD$3/(1+$CI$6)^CJ9 -> 16.957172 | FI9: =$FD$3/(1+$CI$7)^CJ9 -> 16.809352 | FJ9: =$FD$3/(1+$CI$8)^CJ9 -> 15.720243 | FK9: =$FD$3/(1+$CI$9)^CJ9 -> 14.711037 | FL9: =$FD$3/(1+$CI$10)^CJ9 -> 14.122565 | FM9: =$FD$3/(1+$CI$11)^CJ9 -> 12.906784 | FN9: =$FD$3/(1+$CI$12)^CJ9 -> 12.100376 | FO9: =$FD$3/(1+$CI$13)^CJ9 -> 11.351037 | FP9: =$FD$3/(1+$CI$14)^CJ9 -> 10.654265 | FQ9: =$FD$3/(1+$CI$15)^CJ9 -> 10.005947 | FR9: =$FD$3/(1+$CI$16)^CJ9 -> 9.4023244 | FS9: =$FD$3/(1+$CI$17)^CJ9 -> 8.8399616 | FT9: =$FD$3/(1+$CI$18)^CJ9 -> 8.3157123 | FU9: =SUM(FK3:FK52) -> 346.50118 | FW9: =$FV$3/(1+$CI$3)^CJ9 -> 0.037954967 | FX9: =$FV$3/(1+$CI$4)^CJ9 -> 0.035425586 | FY9: =$FV$3/(1+$CI$5)^CJ9 -> 0.033087021 | FZ9: =$FV$3/(1+$CI$6)^CJ9 -> 0.031195167 | GA9: =$FV$3/(1+$CI$7)^CJ9 -> 0.030923231 | GB9: =$FV$3/(1+$CI$8)^CJ9 -> 0.028919658 | GC9: =$FV$3/(1+$CI$9)^CJ9 -> 0.027063078 | GD9: =$FV$3/(1+$CI$10)^CJ9 -> 0.025980499 | GE9: =$FV$3/(1+$CI$11)^CJ9 -> 0.023743894 | GF9: =$FV$3/(1+$CI$12)^CJ9 -> 0.022260389 | GG9: =$FV$3/(1+$CI$13)^CJ9 -> 0.020881873 | GH9: =$FV$3/(1+$CI$14)^CJ9 -> 0.019600059 | GI9: =$FV$3/(1+$CI$15)^CJ9 -> 0.018407384 | GJ9: =$FV$3/(1+$CI$16)^CJ9 -> 0.017296934 | GK9: =$FV$3/(1+$CI$17)^CJ9 -> 0.016262387 | GL9: =$FV$3/(1+$CI$18)^CJ9 -> 0.015297954 | GM9: =SUM(GC3:GC52) -> 0.63743898
A10: Microsoft | B10: 39263 | C10: 24.034 | D10: 316.72028 | E10: 51.122 | F10: 1475.2 | G10: 12.488 | H10: =(D10/AI10) -> 22.518328 | I10: =(D10/G10) -> 25.36197 | J10: -3.414 | K10: -5.2 | L10: -0.961 | M10: 0 | N10: =(C10+L10+J10+K10+M10) -> 14.459 | P10: 10061000000 | Q10: =(P10-P9)/P9*100 -> -8.0910229 | S10: 31.48 | T10: =(S10*P10) -> 316720280000 | U10: =(D10-D9)/D9*100 -> 2.7448367 | V10: 31.097 | W10: =(V10-V9)/V9*100 -> -22.459106 | X10: 25.459 | Y10: =(X10-X9)/X9*100 -> -28.684277 | AA10: 0.1 | AB10: 31.097 | AC10: 40.104 | AD10: =(G9/AA10) -> 108.09 | AE10: =(D10-AC10-AD10) -> 168.52628 | AF10: =((((D10-AD10)/(G10)*AA10)-1)/(1+(D10-AD10)/(G10))) -> 0.037875783 | AG10: =(1+AF10)/(1+AA10) -> 0.94352344 | AI10: 14.065 | AJ10: 12.488 | AL10: 14.065 | AM10: =D10/AL10 -> 22.518328 | AN10: 12.488 | AO10: =D10/AN10 -> 25.36197 | AQ10: =$D$28/AL10 -> 197.01025 | AS10: =$D$28/AN10 -> 221.88895 | AV10: =(D10/AB10) -> 10.184914 | AW10: =(D10/E10) -> 6.1953812 | AX10: 5.638 | AY10: =(AB10-AX10) -> 25.459 | AZ10: =(D10/AY10) -> 12.440405 | BB10: 14.382 | BC10: 20.136 | BD10: =(BB10/D10)*100 -> 4.5409154 | BE10: =(BC10/D10)*100 -> 6.3576605 | BG10: 31.48 | BH10: 10061000000 | BI10: =(BG10*BH10) -> 316720280000 | BJ10: 31.097 | BK10: =AY10 -> 25.459 | BL10: 40.168 | BM10: 23.754 | BN10: 8.32 | BO10: =(BL10-BM10-BN10) -> 8.094 | BP10: 23.411 | BQ10: =(BP10-BM10-BN10) -> -8.663 | BS10: =D10 -> 316.72028 | BT10: =E10 -> 51.122 | BU10: =N10 -> 14.459 | BV10: =G10 -> 12.488 | BW10: =((BS10/BS5)^(1/5)-1)*100 -> -8.2265731 | BX10: =((BT10/BT5)^(1/5)-1)*100 -> 12.503235 | BY10: =((BU10/BU5)^(1/5)-1)*100 -> 1.0268069 | BZ10: =((BV10/BV5)^(1/5)-1)*100 -> 8.7078326 | CE10: 39263 | CF10: 316.72028 | CG10: 14.382 | CH10: =(CG10/CF10) -> 0.045409154 | CI10: 0.0662 | CJ10: 8 | CK10: =$CG$27/(1+$CI$3)^CJ10 -> 4.5610836 | CL10: =$CG$27/(1+$CI$4)^CJ10 -> 4.2153889 | CM10: =$CG$27/(1+$CI$5)^CJ10 -> 3.8988922 | CN10: =$CG$27/(1+$CI$6)^CJ10 -> 3.6451716 | CO10: =$CG$27/(1+$CI$7)^CJ10 -> 3.6088789 | CP10: =$CG$27/(1+$CI$8)^CJ10 -> 3.3429096 | CQ10: =$CG$27/(1+$CI$9)^CJ10 -> 3.0987897 | CR10: =$CG$27/(1+$CI$10)^CJ10 -> 2.957533 | CS10: =$CG$27/(1+$CI$11)^CJ10 -> 2.668388 | CT10: =$CG$27/(1+$CI$12)^CJ10 -> 2.4787176 | CU10: =$CG$27/(1+$CI$13)^CJ10 -> 2.30408 | CV10: =$CG$27/(1+$CI$14)^CJ10 -> 2.143163 | CW10: =$CG$27/(1+$CI$15)^CJ10 -> 1.9947793 | CX10: =$CG$27/(1+$CI$16)^CJ10 -> 1.8578536 | CY10: =$CG$27/(1+$CI$17)^CJ10 -> 1.7314112 | CZ10: =$CG$27/(1+$CI$18)^CJ10 -> 1.6145679 | DA10: =SUM(CR3:CR52) -> 71.201133 | DC10: =$DB$3/(1+$CI$3)^CJ10 -> 32.585106 | DD10: =$DB$3/(1+$CI$4)^CJ10 -> 30.115408 | DE10: =$DB$3/(1+$CI$5)^CJ10 -> 27.854305 | DF10: =$DB$3/(1+$CI$6)^CJ10 -> 26.041684 | DG10: =$DB$3/(1+$CI$7)^CJ10 -> 25.782404 | DH10: =$DB$3/(1+$CI$8)^CJ10 -> 23.882277 | DI10: =$DB$3/(1+$CI$9)^CJ10 -> 22.138246 | DJ10: =$DB$3/(1+$CI$10)^CJ10 -> 21.129085 | DK10: =$DB$3/(1+$CI$11)^CJ10 -> 19.063388 | DL10: =$DB$3/(1+$CI$12)^CJ10 -> 17.708352 | DM10: =$DB$3/(1+$CI$13)^CJ10 -> 16.460713 | DN10: =$DB$3/(1+$CI$14)^CJ10 -> 15.311096 | DO10: =$DB$3/(1+$CI$15)^CJ10 -> 14.25102 | DP10: =$DB$3/(1+$CI$16)^CJ10 -> 13.272801 | DQ10: =$DB$3/(1+$CI$17)^CJ10 -> 12.369476 | DR10: =$DB$3/(1+$CI$18)^CJ10 -> 11.534729 | DS10: =SUM(DJ3:DJ52) -> 508.67219 | DU10: =$DT$3/(1+$CI$3)^CJ10 -> 36.159355 | DV10: =$DT$3/(1+$CI$4)^CJ10 -> 33.418757 | DW10: =$DT$3/(1+$CI$5)^CJ10 -> 30.909634 | DX10: =$DT$3/(1+$CI$6)^CJ10 -> 28.898188 | DY10: =$DT$3/(1+$CI$7)^CJ10 -> 28.610467 | DZ10: =$DT$3/(1+$CI$8)^CJ10 -> 26.501916 | EA10: =$DT$3/(1+$CI$9)^CJ10 -> 24.566582 | EB10: =$DT$3/(1+$CI$10)^CJ10 -> 23.446728 | EC10: =$DT$3/(1+$CI$11)^CJ10 -> 21.154444 | ED10: =$DT$3/(1+$CI$12)^CJ10 -> 19.650775 | EE10: =$DT$3/(1+$CI$13)^CJ10 -> 18.266283 | EF10: =$DT$3/(1+$CI$14)^CJ10 -> 16.990566 | EG10: =$DT$3/(1+$CI$15)^CJ10 -> 15.814209 | EH10: =$DT$3/(1+$CI$16)^CJ10 -> 14.72869 | EI10: =$DT$3/(1+$CI$17)^CJ10 -> 13.72628 | EJ10: =$DT$3/(1+$CI$18)^CJ10 -> 12.79997 | EK10: =SUM(EB3:EB52) -> 564.46828 | EM10: =$EL$3/(1+$CI$3)^CJ10 -> 28.816093 | EN10: =$EL$3/(1+$CI$4)^CJ10 -> 26.632057 | EO10: =$EL$3/(1+$CI$5)^CJ10 -> 24.632489 | EP10: =$EL$3/(1+$CI$6)^CJ10 -> 23.029528 | EQ10: =$EL$3/(1+$CI$7)^CJ10 -> 22.800238 | ER10: =$EL$3/(1+$CI$8)^CJ10 -> 21.119892 | ES10: =$EL$3/(1+$CI$9)^CJ10 -> 19.577587 | ET10: =$EL$3/(1+$CI$10)^CJ10 -> 18.685153 | EU10: =$EL$3/(1+$CI$11)^CJ10 -> 16.858388 | EV10: =$EL$3/(1+$CI$12)^CJ10 -> 15.660085 | EW10: =$EL$3/(1+$CI$13)^CJ10 -> 14.556756 | EX10: =$EL$3/(1+$CI$14)^CJ10 -> 13.540112 | EY10: =$EL$3/(1+$CI$15)^CJ10 -> 12.602651 | EZ10: =$EL$3/(1+$CI$16)^CJ10 -> 11.737579 | FA10: =$EL$3/(1+$CI$17)^CJ10 -> 10.93874 | FB10: =$EL$3/(1+$CI$18)^CJ10 -> 10.200545 | FC10: =SUM(ET3:ET52) -> 449.83575 | FE10: =$FD$3/(1+$CI$3)^CJ10 -> 20.427412 | FF10: =$FD$3/(1+$CI$4)^CJ10 -> 18.879173 | FG10: =$FD$3/(1+$CI$5)^CJ10 -> 17.461701 | FH10: =$FD$3/(1+$CI$6)^CJ10 -> 16.325379 | FI10: =$FD$3/(1+$CI$7)^CJ10 -> 16.162838 | FJ10: =$FD$3/(1+$CI$8)^CJ10 -> 14.97166 | FK10: =$FD$3/(1+$CI$9)^CJ10 -> 13.878337 | FL10: =$FD$3/(1+$CI$10)^CJ10 -> 13.2457 | FM10: =$FD$3/(1+$CI$11)^CJ10 -> 11.950726 | FN10: =$FD$3/(1+$CI$12)^CJ10 -> 11.101262 | FO10: =$FD$3/(1+$CI$13)^CJ10 -> 10.319125 | FP10: =$FD$3/(1+$CI$14)^CJ10 -> 9.5984367 | FQ10: =$FD$3/(1+$CI$15)^CJ10 -> 8.9338808 | FR10: =$FD$3/(1+$CI$16)^CJ10 -> 8.3206411 | FS10: =$FD$3/(1+$CI$17)^CJ10 -> 7.7543523 | FT10: =$FD$3/(1+$CI$18)^CJ10 -> 7.2310542 | FU10: =SUM(FL3:FL52) -> 318.88362 | FW10: =$FV$3/(1+$CI$3)^CJ10 -> 0.037579176 | FX10: =$FV$3/(1+$CI$4)^CJ10 -> 0.034730966 | FY10: =$FV$3/(1+$CI$5)^CJ10 -> 0.032123321 | FZ10: =$FV$3/(1+$CI$6)^CJ10 -> 0.030032894 | GA10: =$FV$3/(1+$CI$7)^CJ10 -> 0.029733876 | GB10: =$FV$3/(1+$CI$8)^CJ10 -> 0.027542531 | GC10: =$FV$3/(1+$CI$9)^CJ10 -> 0.025531205 | GD10: =$FV$3/(1+$CI$10)^CJ10 -> 0.024367379 | GE10: =$FV$3/(1+$CI$11)^CJ10 -> 0.021985087 | GF10: =$FV$3/(1+$CI$12)^CJ10 -> 0.020422375 | GG10: =$FV$3/(1+$CI$13)^CJ10 -> 0.018983521 | GH10: =$FV$3/(1+$CI$14)^CJ10 -> 0.017657711 | GI10: =$FV$3/(1+$CI$15)^CJ10 -> 0.016435165 | GJ10: =$FV$3/(1+$CI$16)^CJ10 -> 0.015307021 | GK10: =$FV$3/(1+$CI$17)^CJ10 -> 0.014265251 | GL10: =$FV$3/(1+$CI$18)^CJ10 -> 0.013302569 | GM10: =SUM(GD3:GD52) -> 0.5866325
A11: Microsoft | B11: 39629 | C11: 29.567 | D11: 363.9 | E11: 60.42 | F11: 890.6 | G11: 16.359 | H11: =(D11/AI11) -> 20.581415 | I11: =(D11/G11) -> 22.244636 | J11: -11.235 | K11: -5.4 | L11: -2.435 | M11: 0 | N11: =(C11+L11+J11+K11+M11) -> 10.497 | P11: 9704000000 | Q11: =(P11-P10)/P10*100 -> -3.548355 | S11: 37.5 | T11: =(S11*P11) -> 363900000000 | U11: =(D11-D10)/D10*100 -> 14.896337 | V11: 36.286 | W11: =(V11-V10)/V10*100 -> 16.686497 | X11: 22.205 | Y11: =(X11-X10)/X10*100 -> -12.781335 | AA11: 0.1 | AB11: 36.286 | AC11: 31.097 | AD11: =(G10/AA11) -> 124.88 | AE11: =(D11-AC11-AD11) -> 207.923 | AF11: =((((D11-AD11)/(G11)*AA11)-1)/(1+(D11-AD11)/(G11))) -> 0.029536493 | AG11: =(1+AF11)/(1+AA11) -> 0.93594227 | AI11: 17.681 | AJ11: 16.359 | AL11: 17.681 | AM11: =D11/AL11 -> 20.581415 | AN11: 16.359 | AO11: =D11/AN11 -> 22.244636 | AQ11: =$D$28/AL11 -> 156.71903 | AS11: =$D$28/AN11 -> 169.38377 | AV11: =(D11/AB11) -> 10.028661 | AW11: =(D11/E11) -> 6.0228401 | AX11: 14.081 | AY11: =(AB11-AX11) -> 22.205 | AZ11: =(D11/AY11) -> 16.388201 | BB11: 10.377 | BC11: 13.147 | BD11: =(BB11/D11)*100 -> 2.8516076 | BE11: =(BC11/D11)*100 -> 3.6128057 | BG11: 37.5 | BH11: 9704000000 | BI11: =(BG11*BH11) -> 363900000000 | BJ11: 36.286 | BK11: =AY11 -> 22.205 | BL11: 43.242 | BM11: 29.886 | BN11: 6.621 | BO11: =(BL11-BM11-BN11) -> 6.735 | BP11: 23.662 | BQ11: =(BP11-BM11-BN11) -> -12.845 | BS11: =D11 -> 363.9 | BT11: =E11 -> 60.42 | BU11: =N11 -> 10.497 | BV11: =G11 -> 16.359 | CE11: 39629 | CF11: 363.9 | CG11: 10.377 | CH11: =(CG11/CF11) -> 0.028516076 | CI11: 0.08 | CJ11: 9 | CK11: =$CG$27/(1+$CI$3)^CJ11 -> 4.5159244 | CL11: =$CG$27/(1+$CI$4)^CJ11 -> 4.1327343 | CM11: =$CG$27/(1+$CI$5)^CJ11 -> 3.7853322 | CN11: =$CG$27/(1+$CI$6)^CJ11 -> 3.5093594 | CO11: =$CG$27/(1+$CI$7)^CJ11 -> 3.4700759 | CP11: =$CG$27/(1+$CI$8)^CJ11 -> 3.1837234 | CQ11: =$CG$27/(1+$CI$9)^CJ11 -> 2.9233865 | CR11: =$CG$27/(1+$CI$10)^CJ11 -> 2.7739008 | CS11: =$CG$27/(1+$CI$11)^CJ11 -> 2.4707296 | CT11: =$CG$27/(1+$CI$12)^CJ11 -> 2.2740528 | CU11: =$CG$27/(1+$CI$13)^CJ11 -> 2.0946181 | CV11: =$CG$27/(1+$CI$14)^CJ11 -> 1.9307774 | CW11: =$CG$27/(1+$CI$15)^CJ11 -> 1.7810529 | CX11: =$CG$27/(1+$CI$16)^CJ11 -> 1.6441182 | CY11: =$CG$27/(1+$CI$17)^CJ11 -> 1.5187817 | CZ11: =$CG$27/(1+$CI$18)^CJ11 -> 1.4039721 | DA11: =SUM(CS3:CS52) -> 60.193834 | DC11: =$DB$3/(1+$CI$3)^CJ11 -> 32.262481 | DD11: =$DB$3/(1+$CI$4)^CJ11 -> 29.52491 | DE11: =$DB$3/(1+$CI$5)^CJ11 -> 27.043014 | DF11: =$DB$3/(1+$CI$6)^CJ11 -> 25.07142 | DG11: =$DB$3/(1+$CI$7)^CJ11 -> 24.790773 | DH11: =$DB$3/(1+$CI$8)^CJ11 -> 22.745026 | DI11: =$DB$3/(1+$CI$9)^CJ11 -> 20.885137 | DJ11: =$DB$3/(1+$CI$10)^CJ11 -> 19.817187 | DK11: =$DB$3/(1+$CI$11)^CJ11 -> 17.651285 | DL11: =$DB$3/(1+$CI$12)^CJ11 -> 16.246194 | DM11: =$DB$3/(1+$CI$13)^CJ11 -> 14.964284 | DN11: =$DB$3/(1+$CI$14)^CJ11 -> 13.793781 | DO11: =$DB$3/(1+$CI$15)^CJ11 -> 12.724125 | DP11: =$DB$3/(1+$CI$16)^CJ11 -> 11.745841 | DQ11: =$DB$3/(1+$CI$17)^CJ11 -> 10.850418 | DR11: =$DB$3/(1+$CI$18)^CJ11 -> 10.030199 | DS11: =SUM(DK3:DK52) -> 430.0343 | DU11: =$DT$3/(1+$CI$3)^CJ11 -> 35.801342 | DV11: =$DT$3/(1+$CI$4)^CJ11 -> 32.763487 | DW11: =$DT$3/(1+$CI$5)^CJ11 -> 30.009354 | DX11: =$DT$3/(1+$CI$6)^CJ11 -> 27.821496 | DY11: =$DT$3/(1+$CI$7)^CJ11 -> 27.510065 | DZ11: =$DT$3/(1+$CI$8)^CJ11 -> 25.23992 | EA11: =$DT$3/(1+$CI$9)^CJ11 -> 23.176021 | EB11: =$DT$3/(1+$CI$10)^CJ11 -> 21.990928 | EC11: =$DT$3/(1+$CI$11)^CJ11 -> 19.587448 | ED11: =$DT$3/(1+$CI$12)^CJ11 -> 18.028234 | EE11: =$DT$3/(1+$CI$13)^CJ11 -> 16.605712 | EF11: =$DT$3/(1+$CI$14)^CJ11 -> 15.306816 | EG11: =$DT$3/(1+$CI$15)^CJ11 -> 14.11983 | EH11: =$DT$3/(1+$CI$16)^CJ11 -> 13.034239 | EI11: =$DT$3/(1+$CI$17)^CJ11 -> 12.040597 | EJ11: =$DT$3/(1+$CI$18)^CJ11 -> 11.130408 | EK11: =SUM(EC3:EC52) -> 477.20462 | EM11: =$EL$3/(1+$CI$3)^CJ11 -> 28.530786 | EN11: =$EL$3/(1+$CI$4)^CJ11 -> 26.10986 | EO11: =$EL$3/(1+$CI$5)^CJ11 -> 23.915038 | EP11: =$EL$3/(1+$CI$6)^CJ11 -> 22.171491 | EQ11: =$EL$3/(1+$CI$7)^CJ11 -> 21.923306 | ER11: =$EL$3/(1+$CI$8)^CJ11 -> 20.114183 | ES11: =$EL$3/(1+$CI$9)^CJ11 -> 18.469422 | ET11: =$EL$3/(1+$CI$10)^CJ11 -> 17.524999 | EU11: =$EL$3/(1+$CI$11)^CJ11 -> 15.609619 | EV11: =$EL$3/(1+$CI$12)^CJ11 -> 14.36705 | EW11: =$EL$3/(1+$CI$13)^CJ11 -> 13.233415 | EX11: =$EL$3/(1+$CI$14)^CJ11 -> 12.198299 | EY11: =$EL$3/(1+$CI$15)^CJ11 -> 11.252367 | EZ11: =$EL$3/(1+$CI$16)^CJ11 -> 10.387238 | FA11: =$EL$3/(1+$CI$17)^CJ11 -> 9.5953856 | FB11: =$EL$3/(1+$CI$18)^CJ11 -> 8.870039 | FC11: =SUM(EU3:EU52) -> 380.29365 | FE11: =$FD$3/(1+$CI$3)^CJ11 -> 20.22516 | FF11: =$FD$3/(1+$CI$4)^CJ11 -> 18.508993 | FG11: =$FD$3/(1+$CI$5)^CJ11 -> 16.953107 | FH11: =$FD$3/(1+$CI$6)^CJ11 -> 15.717127 | FI11: =$FD$3/(1+$CI$7)^CJ11 -> 15.54119 | FJ11: =$FD$3/(1+$CI$8)^CJ11 -> 14.258723 | FK11: =$FD$3/(1+$CI$9)^CJ11 -> 13.09277 | FL11: =$FD$3/(1+$CI$10)^CJ11 -> 12.423279 | FM11: =$FD$3/(1+$CI$11)^CJ11 -> 11.065487 | FN11: =$FD$3/(1+$CI$12)^CJ11 -> 10.184644 | FO11: =$FD$3/(1+$CI$13)^CJ11 -> 9.3810224 | FP11: =$FD$3/(1+$CI$14)^CJ11 -> 8.6472403 | FQ11: =$FD$3/(1+$CI$15)^CJ11 -> 7.9766793 | FR11: =$FD$3/(1+$CI$16)^CJ11 -> 7.3633992 | FS11: =$FD$3/(1+$CI$17)^CJ11 -> 6.8020634 | FT11: =$FD$3/(1+$CI$18)^CJ11 -> 6.2878732 | FU11: =SUM(FM3:FM52) -> 269.58599 | FW11: =$FV$3/(1+$CI$3)^CJ11 -> 0.037207105 | FX11: =$FV$3/(1+$CI$4)^CJ11 -> 0.034049967 | FY11: =$FV$3/(1+$CI$5)^CJ11 -> 0.031187691 | FZ11: =$FV$3/(1+$CI$6)^CJ11 -> 0.028913925 | GA11: =$FV$3/(1+$CI$7)^CJ11 -> 0.028590265 | GB11: =$FV$3/(1+$CI$8)^CJ11 -> 0.026230982 | GC11: =$FV$3/(1+$CI$9)^CJ11 -> 0.024086043 | GD11: =$FV$3/(1+$CI$10)^CJ11 -> 0.022854416 | GE11: =$FV$3/(1+$CI$11)^CJ11 -> 0.020356562 | GF11: =$FV$3/(1+$CI$12)^CJ11 -> 0.018736124 | GG11: =$FV$3/(1+$CI$13)^CJ11 -> 0.017257746 | GH11: =$FV$3/(1+$CI$14)^CJ11 -> 0.015907848 | GI11: =$FV$3/(1+$CI$15)^CJ11 -> 0.014674254 | GJ11: =$FV$3/(1+$CI$16)^CJ11 -> 0.013546037 | GK11: =$FV$3/(1+$CI$17)^CJ11 -> 0.012513378 | GL11: =$FV$3/(1+$CI$18)^CJ11 -> 0.011567451 | GM11: =SUM(GE3:GE52) -> 0.49594238
A12: Microsoft | B12: 39994 | C12: 25.867 | D12: 269.5245 | E12: 57.933 | F12: 1126.6 | G12: 14.569 | H12: =(D12/AI12) -> 18.499863 | I12: =(D12/G12) -> 18.499863 | J12: -3.987 | K12: -6.6 | L12: -0.178 | M12: 0 | N12: =(C12+L12+J12+K12+M12) -> 15.102 | P12: 9457000000 | Q12: =(P12-P11)/P11*100 -> -2.5453421 | S12: 28.5 | T12: =(S12*P12) -> 269524500000 | U12: =(D12-D11)/D11*100 -> -25.93446 | V12: 39.558 | W12: =(V12-V11)/V11*100 -> 9.0172518 | X12: 25.296 | Y12: =(X12-X11)/X11*100 -> 13.920288 | AA12: 0.1 | AB12: 39.558 | AC12: 36.286 | AD12: =(G11/AA12) -> 163.59 | AE12: =(D12-AC12-AD12) -> 69.6485 | AF12: =((((D12-AD12)/(G12)*AA12)-1)/(1+(D12-AD12)/(G12))) -> -0.032991158 | AG12: =(1+AF12)/(1+AA12) -> 0.87909895 | AI12: 14.569 | AJ12: 14.569 | AL12: 14.569 | AM12: =D12/AL12 -> 18.499863 | AN12: 14.569 | AO12: =D12/AN12 -> 18.499863 | AQ12: =$D$28/AL12 -> 190.19488 | AS12: =$D$28/AN12 -> 190.19488 | AV12: =(D12/AB12) -> 6.8134006 | AW12: =(D12/E12) -> 4.6523484 | AX12: 14.262 | AY12: =(AB12-AX12) -> 25.296 | AZ12: =(D12/AY12) -> 10.654827 | BB12: 15.05 | BC12: -1.268 | BD12: =(BB12/D12)*100 -> 5.583908 | BE12: =(BC12/D12)*100 -> -0.47045816 | BG12: 28.5 | BH12: 9457000000 | BI12: =(BG12*BH12) -> 269524500000 | BJ12: 39.558 | BK12: =AY12 -> 25.296 | BL12: 49.28 | BM12: 27.034 | BN12: 11.296 | BO12: =(BL12-BM12-BN12) -> 10.95 | BP12: 31.447 | BQ12: =(BP12-BM12-BN12) -> -6.883 | BS12: =D12 -> 269.5245 | BT12: =E12 -> 57.933 | BU12: =N12 -> 15.102 | BV12: =G12 -> 14.569 | CE12: 39994 | CF12: 269.5245 | CG12: 15.05 | CH12: =(CG12/CF12) -> 0.05583908 | CI12: 0.09 | CJ12: 10 | CK12: =$CG$27/(1+$CI$3)^CJ12 -> 4.4712123 | CL12: =$CG$27/(1+$CI$4)^CJ12 -> 4.0517003 | CM12: =$CG$27/(1+$CI$5)^CJ12 -> 3.6750798 | CN12: =$CG$27/(1+$CI$6)^CJ12 -> 3.3786073 | CO12: =$CG$27/(1+$CI$7)^CJ12 -> 3.3366114 | CP12: =$CG$27/(1+$CI$8)^CJ12 -> 3.0321176 | CQ12: =$CG$27/(1+$CI$9)^CJ12 -> 2.7579118 | CR12: =$CG$27/(1+$CI$10)^CJ12 -> 2.6016702 | CS12: =$CG$27/(1+$CI$11)^CJ12 -> 2.2877126 | CT12: =$CG$27/(1+$CI$12)^CJ12 -> 2.086287 | CU12: =$CG$27/(1+$CI$13)^CJ12 -> 1.9041983 | CV12: =$CG$27/(1+$CI$14)^CJ12 -> 1.7394391 | CW12: =$CG$27/(1+$CI$15)^CJ12 -> 1.5902258 | CX12: =$CG$27/(1+$CI$16)^CJ12 -> 1.4549719 | CY12: =$CG$27/(1+$CI$17)^CJ12 -> 1.3322647 | CZ12: =$CG$27/(1+$CI$18)^CJ12 -> 1.2208453 | DA12: =SUM(CT3:CT52) -> 53.982506 | DC12: =$DB$3/(1+$CI$3)^CJ12 -> 31.94305 | DD12: =$DB$3/(1+$CI$4)^CJ12 -> 28.94599 | DE12: =$DB$3/(1+$CI$5)^CJ12 -> 26.255354 | DF12: =$DB$3/(1+$CI$6)^CJ12 -> 24.137307 | DG12: =$DB$3/(1+$CI$7)^CJ12 -> 23.837282 | DH12: =$DB$3/(1+$CI$8)^CJ12 -> 21.661929 | DI12: =$DB$3/(1+$CI$9)^CJ12 -> 19.70296 | DJ12: =$DB$3/(1+$CI$10)^CJ12 -> 18.586745 | DK12: =$DB$3/(1+$CI$11)^CJ12 -> 16.343782 | DL12: =$DB$3/(1+$CI$12)^CJ12 -> 14.904765 | DM12: =$DB$3/(1+$CI$13)^CJ12 -> 13.603895 | DN12: =$DB$3/(1+$CI$14)^CJ12 -> 12.426829 | DO12: =$DB$3/(1+$CI$15)^CJ12 -> 11.360826 | DP12: =$DB$3/(1+$CI$16)^CJ12 -> 10.39455 | DQ12: =$DB$3/(1+$CI$17)^CJ12 -> 9.5179103 | DR12: =$DB$3/(1+$CI$18)^CJ12 -> 8.7219124 | DS12: =SUM(DL3:DL52) -> 385.65959 | DU12: =$DT$3/(1+$CI$3)^CJ12 -> 35.446873 | DV12: =$DT$3/(1+$CI$4)^CJ12 -> 32.121066 | DW12: =$DT$3/(1+$CI$5)^CJ12 -> 29.135295 | DX12: =$DT$3/(1+$CI$6)^CJ12 -> 26.78492 | DY12: =$DT$3/(1+$CI$7)^CJ12 -> 26.451985 | DZ12: =$DT$3/(1+$CI$8)^CJ12 -> 24.038019 | EA12: =$DT$3/(1+$CI$9)^CJ12 -> 21.864171 | EB12: =$DT$3/(1+$CI$10)^CJ12 -> 20.625519 | EC12: =$DT$3/(1+$CI$11)^CJ12 -> 18.136526 | ED12: =$DT$3/(1+$CI$12)^CJ12 -> 16.539664 | EE12: =$DT$3/(1+$CI$13)^CJ12 -> 15.096102 | EF12: =$DT$3/(1+$CI$14)^CJ12 -> 13.789924 | EG12: =$DT$3/(1+$CI$15)^CJ12 -> 12.606991 | EH12: =$DT$3/(1+$CI$16)^CJ12 -> 11.534725 | EI12: =$DT$3/(1+$CI$17)^CJ12 -> 10.561927 | EJ12: =$DT$3/(1+$CI$18)^CJ12 -> 9.678616 | EK12: =SUM(ED3:ED52) -> 427.96247 | EM12: =$EL$3/(1+$CI$3)^CJ12 -> 28.248303 | EN12: =$EL$3/(1+$CI$4)^CJ12 -> 25.597902 | EO12: =$EL$3/(1+$CI$5)^CJ12 -> 23.218483 | EP12: =$EL$3/(1+$CI$6)^CJ12 -> 21.345424 | EQ12: =$EL$3/(1+$CI$7)^CJ12 -> 21.080102 | ER12: =$EL$3/(1+$CI$8)^CJ12 -> 19.156365 | ES12: =$EL$3/(1+$CI$9)^CJ12 -> 17.423983 | ET12: =$EL$3/(1+$CI$10)^CJ12 -> 16.436877 | EU12: =$EL$3/(1+$CI$11)^CJ12 -> 14.453351 | EV12: =$EL$3/(1+$CI$12)^CJ12 -> 13.18078 | EW12: =$EL$3/(1+$CI$13)^CJ12 -> 12.030377 | EX12: =$EL$3/(1+$CI$14)^CJ12 -> 10.989459 | EY12: =$EL$3/(1+$CI$15)^CJ12 -> 10.046756 | EZ12: =$EL$3/(1+$CI$16)^CJ12 -> 9.1922464 | FA12: =$EL$3/(1+$CI$17)^CJ12 -> 8.4170049 | FB12: =$EL$3/(1+$CI$18)^CJ12 -> 7.7130774 | FC12: =SUM(EV3:EV52) -> 341.05161 | FE12: =$FD$3/(1+$CI$3)^CJ12 -> 20.024911 | FF12: =$FD$3/(1+$CI$4)^CJ12 -> 18.146072 | FG12: =$FD$3/(1+$CI$5)^CJ12 -> 16.459328 | FH12: =$FD$3/(1+$CI$6)^CJ12 -> 15.131536 | FI12: =$FD$3/(1+$CI$7)^CJ12 -> 14.943452 | FJ12: =$FD$3/(1+$CI$8)^CJ12 -> 13.579737 | FK12: =$FD$3/(1+$CI$9)^CJ12 -> 12.35167 | FL12: =$FD$3/(1+$CI$10)^CJ12 -> 11.651922 | FM12: =$FD$3/(1+$CI$11)^CJ12 -> 10.245821 | FN12: =$FD$3/(1+$CI$12)^CJ12 -> 9.3437102 | FO12: =$FD$3/(1+$CI$13)^CJ12 -> 8.5282021 | FP12: =$FD$3/(1+$CI$14)^CJ12 -> 7.7903066 | FQ12: =$FD$3/(1+$CI$15)^CJ12 -> 7.1220351 | FR12: =$FD$3/(1+$CI$16)^CJ12 -> 6.5162825 | FS12: =$FD$3/(1+$CI$17)^CJ12 -> 5.9667223 | FT12: =$FD$3/(1+$CI$18)^CJ12 -> 5.4677158 | FU12: =SUM(FN3:FN52) -> 241.76774 | FW12: =$FV$3/(1+$CI$3)^CJ12 -> 0.036838717 | FX12: =$FV$3/(1+$CI$4)^CJ12 -> 0.03338232 | FY12: =$FV$3/(1+$CI$5)^CJ12 -> 0.030279311 | FZ12: =$FV$3/(1+$CI$6)^CJ12 -> 0.027836647 | GA12: =$FV$3/(1+$CI$7)^CJ12 -> 0.02749064 | GB12: =$FV$3/(1+$CI$8)^CJ12 -> 0.024981888 | GC12: =$FV$3/(1+$CI$9)^CJ12 -> 0.022722682 | GD12: =$FV$3/(1+$CI$10)^CJ12 -> 0.021435393 | GE12: =$FV$3/(1+$CI$11)^CJ12 -> 0.018848669 | GF12: =$FV$3/(1+$CI$12)^CJ12 -> 0.017189105 | GG12: =$FV$3/(1+$CI$13)^CJ12 -> 0.01568886 | GH12: =$FV$3/(1+$CI$14)^CJ12 -> 0.014331395 | GI12: =$FV$3/(1+$CI$15)^CJ12 -> 0.013102013 | GJ12: =$FV$3/(1+$CI$16)^CJ12 -> 0.011987643 | GK12: =$FV$3/(1+$CI$17)^CJ12 -> 0.010976648 | GL12: =$FV$3/(1+$CI$18)^CJ12 -> 0.010058653 | GM12: =SUM(GF3:GF52) -> 0.44476669
A13: Microsoft | B13: 40359 | C13: 27.702 | D13: 287.63064 | E13: 63.55 | F13: 1256.8 | G13: 18.76 | H13: =(D13/AI13) -> 15.332124 | I13: =(D13/G13) -> 15.332124 | J13: -2.222 | K13: -4.1 | L13: 0.661 | M13: -0.145 | N13: =(C13+L13+J13+K13+M13) -> 21.896 | P13: 9108000000 | Q13: =(P13-P12)/P12*100 -> -3.6903881 | S13: 31.58 | T13: =(S13*P13) -> 287630640000 | U13: =(D13-D12)/D12*100 -> 6.7178086 | V13: 46.175 | W13: =(V13-V12)/V12*100 -> 16.727337 | X13: 32.623 | Y13: =(X13-X12)/X12*100 -> 28.965054 | AA13: 0.1 | AB13: 46.175 | AC13: 39.558 | AD13: =(G12/AA13) -> 145.69 | AE13: =(D13-AC13-AD13) -> 102.38264 | AF13: =((((D13-AD13)/(G13)*AA13)-1)/(1+(D13-AD13)/(G13))) -> -0.028412681 | AG13: =(1+AF13)/(1+AA13) -> 0.8832612 | AI13: 18.76 | AJ13: 18.76 | AL13: 18.76 | AM13: =D13/AL13 -> 15.332124 | AN13: 18.76 | AO13: =D13/AN13 -> 15.332124 | AQ13: =$D$28/AL13 -> 147.70518 | AS13: =$D$28/AN13 -> 147.70518 | AV13: =(D13/AB13) -> 6.2291422 | AW13: =(D13/E13) -> 4.5260526 | AX13: 13.552 | AY13: =(AB13-AX13) -> 32.623 | AZ13: =(D13/AY13) -> 8.8168053 | BB13: 21.996 | BC13: 8.142 | BD13: =(BB13/D13)*100 -> 7.6473077 | BE13: =(BC13/D13)*100 -> 2.8307137 | BG13: 31.58 | BH13: 9108000000 | BI13: =(BG13*BH13) -> 287630640000 | BJ13: 46.175 | BK13: =AY13 -> 32.623 | BL13: 55.676 | BM13: 26.147 | BN13: 13.791 | BO13: =(BL13-BM13-BN13) -> 15.738 | BP13: 36.788 | BQ13: =(BP13-BM13-BN13) -> -3.15 | BS13: =D13 -> 287.63064 | BT13: =E13 -> 63.55 | BU13: =N13 -> 21.896 | BV13: =G13 -> 18.76 | CE13: 40359 | CF13: 287.63064 | CG13: 21.851 | CH13: =(CG13/CF13) -> 0.075968958 | CI13: 0.1 | CJ13: 11 | CK13: =$CG$27/(1+$CI$3)^CJ13 -> 4.4269428 | CL13: =$CG$27/(1+$CI$4)^CJ13 -> 3.9722552 | CM13: =$CG$27/(1+$CI$5)^CJ13 -> 3.5680387 | CN13: =$CG$27/(1+$CI$6)^CJ13 -> 3.2527267 | CO13: =$CG$27/(1+$CI$7)^CJ13 -> 3.2082802 | CP13: =$CG$27/(1+$CI$8)^CJ13 -> 2.887731 | CQ13: =$CG$27/(1+$CI$9)^CJ13 -> 2.6018036 | CR13: =$CG$27/(1+$CI$10)^CJ13 -> 2.4401334 | CS13: =$CG$27/(1+$CI$11)^CJ13 -> 2.1182524 | CT13: =$CG$27/(1+$CI$12)^CJ13 -> 1.9140247 | CU13: =$CG$27/(1+$CI$13)^CJ13 -> 1.7310894 | CV13: =$CG$27/(1+$CI$14)^CJ13 -> 1.5670623 | CW13: =$CG$27/(1+$CI$15)^CJ13 -> 1.4198445 | CX13: =$CG$27/(1+$CI$16)^CJ13 -> 1.2875857 | CY13: =$CG$27/(1+$CI$17)^CJ13 -> 1.1686532 | CZ13: =$CG$27/(1+$CI$18)^CJ13 -> 1.0616046 | DA13: =SUM(CU3:CU52) -> 48.860142 | DC13: =$DB$3/(1+$CI$3)^CJ13 -> 31.626782 | DD13: =$DB$3/(1+$CI$4)^CJ13 -> 28.378421 | DE13: =$DB$3/(1+$CI$5)^CJ13 -> 25.490635 | DF13: =$DB$3/(1+$CI$6)^CJ13 -> 23.237996 | DG13: =$DB$3/(1+$CI$7)^CJ13 -> 22.920463 | DH13: =$DB$3/(1+$CI$8)^CJ13 -> 20.630409 | DI13: =$DB$3/(1+$CI$9)^CJ13 -> 18.587698 | DJ13: =$DB$3/(1+$CI$10)^CJ13 -> 17.4327 | DK13: =$DB$3/(1+$CI$11)^CJ13 -> 15.133132 | DL13: =$DB$3/(1+$CI$12)^CJ13 -> 13.674097 | DM13: =$DB$3/(1+$CI$13)^CJ13 -> 12.367177 | DN13: =$DB$3/(1+$CI$14)^CJ13 -> 11.195342 | DO13: =$DB$3/(1+$CI$15)^CJ13 -> 10.143594 | DP13: =$DB$3/(1+$CI$16)^CJ13 -> 9.1987167 | DQ13: =$DB$3/(1+$CI$17)^CJ13 -> 8.3490441 | DR13: =$DB$3/(1+$CI$18)^CJ13 -> 7.5842716 | DS13: =SUM(DM3:DM52) -> 349.06461 | DU13: =$DT$3/(1+$CI$3)^CJ13 -> 35.095914 | DV13: =$DT$3/(1+$CI$4)^CJ13 -> 31.491241 | DW13: =$DT$3/(1+$CI$5)^CJ13 -> 28.286694 | DX13: =$DT$3/(1+$CI$6)^CJ13 -> 25.786964 | DY13: =$DT$3/(1+$CI$7)^CJ13 -> 25.434601 | DZ13: =$DT$3/(1+$CI$8)^CJ13 -> 22.893351 | EA13: =$DT$3/(1+$CI$9)^CJ13 -> 20.626576 | EB13: =$DT$3/(1+$CI$10)^CJ13 -> 19.344887 | EC13: =$DT$3/(1+$CI$11)^CJ13 -> 16.79308 | ED13: =$DT$3/(1+$CI$12)^CJ13 -> 15.174004 | EE13: =$DT$3/(1+$CI$13)^CJ13 -> 13.723729 | EF13: =$DT$3/(1+$CI$14)^CJ13 -> 12.423355 | EG13: =$DT$3/(1+$CI$15)^CJ13 -> 11.256242 | EH13: =$DT$3/(1+$CI$16)^CJ13 -> 10.207721 | EI13: =$DT$3/(1+$CI$17)^CJ13 -> 9.264848 | EJ13: =$DT$3/(1+$CI$18)^CJ13 -> 8.4161879 | EK13: =SUM(EE3:EE52) -> 387.35339 | EM13: =$EL$3/(1+$CI$3)^CJ13 -> 27.968616 | EN13: =$EL$3/(1+$CI$4)^CJ13 -> 25.095983 | EO13: =$EL$3/(1+$CI$5)^CJ13 -> 22.542217 | EP13: =$EL$3/(1+$CI$6)^CJ13 -> 20.550133 | EQ13: =$EL$3/(1+$CI$7)^CJ13 -> 20.269329 | ER13: =$EL$3/(1+$CI$8)^CJ13 -> 18.244157 | ES13: =$EL$3/(1+$CI$9)^CJ13 -> 16.43772 | ET13: =$EL$3/(1+$CI$10)^CJ13 -> 15.416317 | EU13: =$EL$3/(1+$CI$11)^CJ13 -> 13.382732 | EV13: =$EL$3/(1+$CI$12)^CJ13 -> 12.092459 | EW13: =$EL$3/(1+$CI$13)^CJ13 -> 10.936706 | EX13: =$EL$3/(1+$CI$14)^CJ13 -> 9.9004134 | EY13: =$EL$3/(1+$CI$15)^CJ13 -> 8.9703181 | EZ13: =$EL$3/(1+$CI$16)^CJ13 -> 8.1347314 | FA13: =$EL$3/(1+$CI$17)^CJ13 -> 7.3833376 | FB13: =$EL$3/(1+$CI$18)^CJ13 -> 6.7070238 | FC13: =SUM(EW3:EW52) -> 308.68945 | FE13: =$FD$3/(1+$CI$3)^CJ13 -> 19.826645 | FF13: =$FD$3/(1+$CI$4)^CJ13 -> 17.790266 | FG13: =$FD$3/(1+$CI$5)^CJ13 -> 15.97993 | FH13: =$FD$3/(1+$CI$6)^CJ13 -> 14.567764 | FI13: =$FD$3/(1+$CI$7)^CJ13 -> 14.368704 | FJ13: =$FD$3/(1+$CI$8)^CJ13 -> 12.933082 | FK13: =$FD$3/(1+$CI$9)^CJ13 -> 11.652519 | FL13: =$FD$3/(1+$CI$10)^CJ13 -> 10.928458 | FM13: =$FD$3/(1+$CI$11)^CJ13 -> 9.4868717 | FN13: =$FD$3/(1+$CI$12)^CJ13 -> 8.5722111 | FO13: =$FD$3/(1+$CI$13)^CJ13 -> 7.752911 | FP13: =$FD$3/(1+$CI$14)^CJ13 -> 7.0182942 | FQ13: =$FD$3/(1+$CI$15)^CJ13 -> 6.3589599 | FR13: =$FD$3/(1+$CI$16)^CJ13 -> 5.7666217 | FS13: =$FD$3/(1+$CI$17)^CJ13 -> 5.2339669 | FT13: =$FD$3/(1+$CI$18)^CJ13 -> 4.7545355 | FU13: =SUM(FO3:FO52) -> 218.82656 | FW13: =$FV$3/(1+$CI$3)^CJ13 -> 0.036473978 | FX13: =$FV$3/(1+$CI$4)^CJ13 -> 0.032727765 | FY13: =$FV$3/(1+$CI$5)^CJ13 -> 0.02939739 | FZ13: =$FV$3/(1+$CI$6)^CJ13 -> 0.026799506 | GA13: =$FV$3/(1+$CI$7)^CJ13 -> 0.026433307 | GB13: =$FV$3/(1+$CI$8)^CJ13 -> 0.023792274 | GC13: =$FV$3/(1+$CI$9)^CJ13 -> 0.021436492 | GD13: =$FV$3/(1+$CI$10)^CJ13 -> 0.020104477 | GE13: =$FV$3/(1+$CI$11)^CJ13 -> 0.017452471 | GF13: =$FV$3/(1+$CI$12)^CJ13 -> 0.015769821 | GG13: =$FV$3/(1+$CI$13)^CJ13 -> 0.0142626 | GH13: =$FV$3/(1+$CI$14)^CJ13 -> 0.012911166 | GI13: =$FV$3/(1+$CI$15)^CJ13 -> 0.011698226 | GJ13: =$FV$3/(1+$CI$16)^CJ13 -> 0.010608534 | GK13: =$FV$3/(1+$CI$17)^CJ13 -> 0.0096286383 | GL13: =$FV$3/(1+$CI$18)^CJ13 -> 0.008746655 | GM13: =SUM(GG3:GG52) -> 0.40256308
A14: Microsoft | B14: 40724 | C14: 35.511 | D14: 262.72428 | E14: 71.148 | F14: 1262.8 | G14: 23.15 | H14: =(D14/AI14) -> 11.348781 | I14: =(D14/G14) -> 11.348781 | J14: -2.426 | K14: -5.3 | L14: -3.003 | M14: -0.197 | N14: =(C14+L14+J14+K14+M14) -> 24.585 | P14: 8918000000 | Q14: =(P14-P13)/P13*100 -> -2.0860782 | S14: 29.46 | T14: =(S14*P14) -> 262724280000 | U14: =(D14-D13)/D13*100 -> -8.659147 | V14: 57.083 | W14: =(V14-V13)/V13*100 -> 23.623173 | X14: 43.758 | Y14: =(X14-X13)/X13*100 -> 34.132361 | AA14: 0.1 | AB14: 57.083 | AC14: 46.175 | AD14: =(G13/AA14) -> 187.6 | AE14: =(D14-AC14-AD14) -> 28.94928 | AF14: =((((D14-AD14)/(G14)*AA14)-1)/(1+(D14-AD14)/(G14))) -> -0.15912172 | AG14: =(1+AF14)/(1+AA14) -> 0.7644348 | AI14: 23.15 | AJ14: 23.15 | AL14: 23.15 | AM14: =D14/AL14 -> 11.348781 | AN14: 23.15 | AO14: =D14/AN14 -> 11.348781 | AQ14: =$D$28/AL14 -> 119.69543 | AS14: =$D$28/AN14 -> 119.69543 | AV14: =(D14/AB14) -> 4.602496 | AW14: =(D14/E14) -> 3.6926446 | AX14: 13.325 | AY14: =(AB14-AX14) -> 43.758 | AZ14: =(D14/AY14) -> 6.0040285 | BB14: 24.765 | BC14: 7.301 | BD14: =(BB14/D14)*100 -> 9.4262319 | BE14: =(BC14/D14)*100 -> 2.778959 | BG14: 29.46 | BH14: 8918000000 | BI14: =(BG14*BH14) -> 262724280000 | BJ14: 57.083 | BK14: =AY14 -> 43.758 | BL14: 74.918 | BM14: 28.774 | BN14: 22.847 | BO14: =(BL14-BM14-BN14) -> 23.297 | BP14: 52.772 | BQ14: =(BP14-BM14-BN14) -> 1.151 | BS14: =D14 -> 262.72428 | BT14: =E14 -> 71.148 | BU14: =N14 -> 24.585 | BV14: =G14 -> 23.15 | CE14: 40724 | CF14: 262.72428 | CG14: 24.568 | CH14: =(CG14/CF14) -> 0.093512484 | CI14: 0.11 | CJ14: 12 | CK14: =$CG$27/(1+$CI$3)^CJ14 -> 4.3831117 | CL14: =$CG$27/(1+$CI$4)^CJ14 -> 3.8943678 | CM14: =$CG$27/(1+$CI$5)^CJ14 -> 3.4641152 | CN14: =$CG$27/(1+$CI$6)^CJ14 -> 3.1315363 | CO14: =$CG$27/(1+$CI$7)^CJ14 -> 3.0848848 | CP14: =$CG$27/(1+$CI$8)^CJ14 -> 2.75022 | CQ14: =$CG$27/(1+$CI$9)^CJ14 -> 2.4545317 | CR14: =$CG$27/(1+$CI$10)^CJ14 -> 2.2886263 | CS14: =$CG$27/(1+$CI$11)^CJ14 -> 1.9613449 | CT14: =$CG$27/(1+$CI$12)^CJ14 -> 1.755986 | CU14: =$CG$27/(1+$CI$13)^CJ14 -> 1.5737176 | CV14: =$CG$27/(1+$CI$14)^CJ14 -> 1.4117678 | CW14: =$CG$27/(1+$CI$15)^CJ14 -> 1.2677183 | CX14: =$CG$27/(1+$CI$16)^CJ14 -> 1.1394564 | CY14: =$CG$27/(1+$CI$17)^CJ14 -> 1.0251344 | CZ14: =$CG$27/(1+$CI$18)^CJ14 -> 0.92313441 | DA14: =SUM(CV3:CV52) -> 44.580741 | DC14: =$DB$3/(1+$CI$3)^CJ14 -> 31.313646 | DD14: =$DB$3/(1+$CI$4)^CJ14 -> 27.821982 | DE14: =$DB$3/(1+$CI$5)^CJ14 -> 24.748189 | DF14: =$DB$3/(1+$CI$6)^CJ14 -> 22.372192 | DG14: =$DB$3/(1+$CI$7)^CJ14 -> 22.038907 | DH14: =$DB$3/(1+$CI$8)^CJ14 -> 19.648008 | DI14: =$DB$3/(1+$CI$9)^CJ14 -> 17.535564 | DJ14: =$DB$3/(1+$CI$10)^CJ14 -> 16.35031 | DK14: =$DB$3/(1+$CI$11)^CJ14 -> 14.012159 | DL14: =$DB$3/(1+$CI$12)^CJ14 -> 12.545043 | DM14: =$DB$3/(1+$CI$13)^CJ14 -> 11.242888 | DN14: =$DB$3/(1+$CI$14)^CJ14 -> 10.085893 | DO14: =$DB$3/(1+$CI$15)^CJ14 -> 9.0567807 | DP14: =$DB$3/(1+$CI$16)^CJ14 -> 8.1404573 | DQ14: =$DB$3/(1+$CI$17)^CJ14 -> 7.3237229 | DR14: =$DB$3/(1+$CI$18)^CJ14 -> 6.5950188 | DS14: =SUM(DN3:DN52) -> 318.49189 | DU14: =$DT$3/(1+$CI$3)^CJ14 -> 34.748429 | DV14: =$DT$3/(1+$CI$4)^CJ14 -> 30.873766 | DW14: =$DT$3/(1+$CI$5)^CJ14 -> 27.46281 | DX14: =$DT$3/(1+$CI$6)^CJ14 -> 24.826191 | DY14: =$DT$3/(1+$CI$7)^CJ14 -> 24.456347 | DZ14: =$DT$3/(1+$CI$8)^CJ14 -> 21.803192 | EA14: =$DT$3/(1+$CI$9)^CJ14 -> 19.459034 | EB14: =$DT$3/(1+$CI$10)^CJ14 -> 18.14377 | EC14: =$DT$3/(1+$CI$11)^CJ14 -> 15.549148 | ED14: =$DT$3/(1+$CI$12)^CJ14 -> 13.921104 | EE14: =$DT$3/(1+$CI$13)^CJ14 -> 12.476117 | EF14: =$DT$3/(1+$CI$14)^CJ14 -> 11.192212 | EG14: =$DT$3/(1+$CI$15)^CJ14 -> 10.050216 | EH14: =$DT$3/(1+$CI$16)^CJ14 -> 9.0333813 | EI14: =$DT$3/(1+$CI$17)^CJ14 -> 8.1270597 | EJ14: =$DT$3/(1+$CI$18)^CJ14 -> 7.3184242 | EK14: =SUM(EF3:EF52) -> 353.42716 | EM14: =$EL$3/(1+$CI$3)^CJ14 -> 27.691699 | EN14: =$EL$3/(1+$CI$4)^CJ14 -> 24.603905 | EO14: =$EL$3/(1+$CI$5)^CJ14 -> 21.885647 | EP14: =$EL$3/(1+$CI$6)^CJ14 -> 19.784474 | EQ14: =$EL$3/(1+$CI$7)^CJ14 -> 19.489739 | ER14: =$EL$3/(1+$CI$8)^CJ14 -> 17.375388 | ES14: =$EL$3/(1+$CI$9)^CJ14 -> 15.507283 | ET14: =$EL$3/(1+$CI$10)^CJ14 -> 14.459123 | EU14: =$EL$3/(1+$CI$11)^CJ14 -> 12.391419 | EV14: =$EL$3/(1+$CI$12)^CJ14 -> 11.093999 | EW14: =$EL$3/(1+$CI$13)^CJ14 -> 9.9424604 | EX14: =$EL$3/(1+$CI$14)^CJ14 -> 8.9192913 | EY14: =$EL$3/(1+$CI$15)^CJ14 -> 8.0092126 | EZ14: =$EL$3/(1+$CI$16)^CJ14 -> 7.1988773 | FA14: =$EL$3/(1+$CI$17)^CJ14 -> 6.476612 | FB14: =$EL$3/(1+$CI$18)^CJ14 -> 5.8321946 | FC14: =SUM(EX3:EX52) -> 281.65298 | FE14: =$FD$3/(1+$CI$3)^CJ14 -> 19.630341 | FF14: =$FD$3/(1+$CI$4)^CJ14 -> 17.441438 | FG14: =$FD$3/(1+$CI$5)^CJ14 -> 15.514495 | FH14: =$FD$3/(1+$CI$6)^CJ14 -> 14.024996 | FI14: =$FD$3/(1+$CI$7)^CJ14 -> 13.816062 | FJ14: =$FD$3/(1+$CI$8)^CJ14 -> 12.317221 | FK14: =$FD$3/(1+$CI$9)^CJ14 -> 10.992942 | FL14: =$FD$3/(1+$CI$10)^CJ14 -> 10.249913 | FM14: =$FD$3/(1+$CI$11)^CJ14 -> 8.7841405 | FN14: =$FD$3/(1+$CI$12)^CJ14 -> 7.8644139 | FO14: =$FD$3/(1+$CI$13)^CJ14 -> 7.0481009 | FP14: =$FD$3/(1+$CI$14)^CJ14 -> 6.3227876 | FQ14: =$FD$3/(1+$CI$15)^CJ14 -> 5.6776428 | FR14: =$FD$3/(1+$CI$16)^CJ14 -> 5.103205 | FS14: =$FD$3/(1+$CI$17)^CJ14 -> 4.591199 | FT14: =$FD$3/(1+$CI$18)^CJ14 -> 4.1343787 | FU14: =SUM(FP3:FP52) -> 199.6607 | FW14: =$FV$3/(1+$CI$3)^CJ14 -> 0.036112849 | FX14: =$FV$3/(1+$CI$4)^CJ14 -> 0.032086044 | FY14: =$FV$3/(1+$CI$5)^CJ14 -> 0.028541155 | FZ14: =$FV$3/(1+$CI$6)^CJ14 -> 0.025801007 | GA14: =$FV$3/(1+$CI$7)^CJ14 -> 0.025416642 | GB14: =$FV$3/(1+$CI$8)^CJ14 -> 0.022659308 | GC14: =$FV$3/(1+$CI$9)^CJ14 -> 0.020223106 | GD14: =$FV$3/(1+$CI$10)^CJ14 -> 0.018856197 | GE14: =$FV$3/(1+$CI$11)^CJ14 -> 0.016159696 | GF14: =$FV$3/(1+$CI$12)^CJ14 -> 0.014467726 | GG14: =$FV$3/(1+$CI$13)^CJ14 -> 0.012966 | GH14: =$FV$3/(1+$CI$14)^CJ14 -> 0.011631681 | GI14: =$FV$3/(1+$CI$15)^CJ14 -> 0.010444844 | GJ14: =$FV$3/(1+$CI$16)^CJ14 -> 0.0093880829 | GK14: =$FV$3/(1+$CI$17)^CJ14 -> 0.008446174 | GL14: =$FV$3/(1+$CI$18)^CJ14 -> 0.0076057869 | GM14: =SUM(GH3:GH52) -> 0.36730471
A15: Microsoft | B15: 41090 | C15: 35.737 | D15: 286.1378 | E15: 74.607 | F15: 1402.4 | G15: 16.978 | H15: =(D15/AI15) -> 16.853446 | I15: =(D15/G15) -> 16.853446 | J15: -12.417 | K15: -3.5 | L15: -0.174 | M15: -0.344 | N15: =(C15+L15+J15+K15+M15) -> 19.302 | P15: 8684000000 | Q15: =(P15-P14)/P14*100 -> -2.6239067 | S15: 32.95 | T15: =(S15*P15) -> 286137800000 | U15: =(D15-D14)/D14*100 -> 8.9118219 | V15: 66.363 | W15: =(V15-V14)/V14*100 -> 16.257029 | X15: 49.741 | Y15: =(X15-X14)/X14*100 -> 13.672928 | AA15: 0.1 | AB15: 66.363 | AC15: 57.083 | AD15: =(G14/AA15) -> 231.5 | AE15: =(D15-AC15-AD15) -> -2.4452 | AF15: =((((D15-AD15)/(G15)*AA15)-1)/(1+(D15-AD15)/(G15))) -> -0.16077765 | AG15: =(1+AF15)/(1+AA15) -> 0.76292941 | AI15: 16.978 | AJ15: 16.978 | AL15: 16.978 | AM15: =D15/AL15 -> 16.853446 | AN15: 16.978 | AO15: =D15/AN15 -> 16.853446 | AQ15: =$D$28/AL15 -> 163.20822 | AS15: =$D$28/AN15 -> 163.20822 | AV15: =(D15/AB15) -> 4.3117068 | AW15: =(D15/E15) -> 3.8352675 | AX15: 16.622 | AY15: =(AB15-AX15) -> 49.741 | AZ15: =(D15/AY15) -> 5.7525542 | BB15: 19.553 | BC15: 0.351 | BD15: =(BB15/D15)*100 -> 6.8334208 | BE15: =(BC15/D15)*100 -> 0.12266817 | BG15: 32.95 | BH15: 8684000000 | BI15: =(BG15*BH15) -> 286137800000 | BJ15: 66.363 | BK15: =AY15 -> 49.741 | BL15: 85.084 | BM15: 32.688 | BN15: 22.22 | BO15: =(BL15-BM15-BN15) -> 30.176 | BP15: 63.04 | BQ15: =(BP15-BM15-BN15) -> 8.132 | BS15: =D15 -> 286.1378 | BT15: =E15 -> 74.607 | BU15: =N15 -> 19.302 | BV15: =G15 -> 16.978 | BW15: =((BS15/BS10)^(1/5)-1)*100 -> -2.0104254 | BX15: =((BT15/BT10)^(1/5)-1)*100 -> 7.8535261 | BY15: =((BU15/BU10)^(1/5)-1)*100 -> 5.9480117 | BZ15: =((BV15/BV10)^(1/5)-1)*100 -> 6.3356103 | CE15: 41090 | CF15: 286.1378 | CG15: 19.209 | CH15: =(CG15/CF15) -> 0.06713199 | CI15: 0.12 | CJ15: 13 | CK15: =$CG$27/(1+$CI$3)^CJ15 -> 4.3397146 | CL15: =$CG$27/(1+$CI$4)^CJ15 -> 3.8180076 | CM15: =$CG$27/(1+$CI$5)^CJ15 -> 3.3632187 | CN15: =$CG$27/(1+$CI$6)^CJ15 -> 3.0148611 | CO15: =$CG$27/(1+$CI$7)^CJ15 -> 2.9662354 | CP15: =$CG$27/(1+$CI$8)^CJ15 -> 2.6192572 | CQ15: =$CG$27/(1+$CI$9)^CJ15 -> 2.3155959 | CR15: =$CG$27/(1+$CI$10)^CJ15 -> 2.1465263 | CS15: =$CG$27/(1+$CI$11)^CJ15 -> 1.81606 | CT15: =$CG$27/(1+$CI$12)^CJ15 -> 1.6109963 | CU15: =$CG$27/(1+$CI$13)^CJ15 -> 1.4306524 | CV15: =$CG$27/(1+$CI$14)^CJ15 -> 1.2718629 | CW15: =$CG$27/(1+$CI$15)^CJ15 -> 1.1318913 | CX15: =$CG$27/(1+$CI$16)^CJ15 -> 1.0083685 | CY15: =$CG$27/(1+$CI$17)^CJ15 -> 0.89924071 | CZ15: =$CG$27/(1+$CI$18)^CJ15 -> 0.80272558 | DA15: =SUM(CW3:CW52) -> 40.96284 | DC15: =$DB$3/(1+$CI$3)^CJ15 -> 31.00361 | DD15: =$DB$3/(1+$CI$4)^CJ15 -> 27.276453 | DE15: =$DB$3/(1+$CI$5)^CJ15 -> 24.027368 | DF15: =$DB$3/(1+$CI$6)^CJ15 -> 21.538647 | DG15: =$DB$3/(1+$CI$7)^CJ15 -> 21.191257 | DH15: =$DB$3/(1+$CI$8)^CJ15 -> 18.712389 | DI15: =$DB$3/(1+$CI$9)^CJ15 -> 16.542985 | DJ15: =$DB$3/(1+$CI$10)^CJ15 -> 15.335124 | DK15: =$DB$3/(1+$CI$11)^CJ15 -> 12.974221 | DL15: =$DB$3/(1+$CI$12)^CJ15 -> 11.509214 | DM15: =$DB$3/(1+$CI$13)^CJ15 -> 10.220808 | DN15: =$DB$3/(1+$CI$14)^CJ15 -> 9.0863905 | DO15: =$DB$3/(1+$CI$15)^CJ15 -> 8.0864113 | DP15: =$DB$3/(1+$CI$16)^CJ15 -> 7.2039445 | DQ15: =$DB$3/(1+$CI$17)^CJ15 -> 6.4243184 | DR15: =$DB$3/(1+$CI$18)^CJ15 -> 5.734799 | DS15: =SUM(DO3:DO52) -> 292.64503 | DU15: =$DT$3/(1+$CI$3)^CJ15 -> 34.404386 | DV15: =$DT$3/(1+$CI$4)^CJ15 -> 30.268398 | DW15: =$DT$3/(1+$CI$5)^CJ15 -> 26.662922 | DX15: =$DT$3/(1+$CI$6)^CJ15 -> 23.901214 | DY15: =$DT$3/(1+$CI$7)^CJ15 -> 23.515719 | DZ15: =$DT$3/(1+$CI$8)^CJ15 -> 20.764945 | EA15: =$DT$3/(1+$CI$9)^CJ15 -> 18.357579 | EB15: =$DT$3/(1+$CI$10)^CJ15 -> 17.017229 | EC15: =$DT$3/(1+$CI$11)^CJ15 -> 14.397359 | ED15: =$DT$3/(1+$CI$12)^CJ15 -> 12.771655 | EE15: =$DT$3/(1+$CI$13)^CJ15 -> 11.341925 | EF15: =$DT$3/(1+$CI$14)^CJ15 -> 10.083074 | EG15: =$DT$3/(1+$CI$15)^CJ15 -> 8.9734071 | EH15: =$DT$3/(1+$CI$16)^CJ15 -> 7.9941428 | EI15: =$DT$3/(1+$CI$17)^CJ15 -> 7.1289997 | EJ15: =$DT$3/(1+$CI$18)^CJ15 -> 6.3638472 | EK15: =SUM(EG3:EG52) -> 324.74516 | EM15: =$EL$3/(1+$CI$3)^CJ15 -> 27.417524 | EN15: =$EL$3/(1+$CI$4)^CJ15 -> 24.121475 | EO15: =$EL$3/(1+$CI$5)^CJ15 -> 21.248201 | EP15: =$EL$3/(1+$CI$6)^CJ15 -> 19.047342 | EQ15: =$EL$3/(1+$CI$7)^CJ15 -> 18.740134 | ER15: =$EL$3/(1+$CI$8)^CJ15 -> 16.547988 | ES15: =$EL$3/(1+$CI$9)^CJ15 -> 14.629512 | ET15: =$EL$3/(1+$CI$10)^CJ15 -> 13.561361 | EU15: =$EL$3/(1+$CI$11)^CJ15 -> 11.473536 | EV15: =$EL$3/(1+$CI$12)^CJ15 -> 10.177981 | EW15: =$EL$3/(1+$CI$13)^CJ15 -> 9.0386004 | EX15: =$EL$3/(1+$CI$14)^CJ15 -> 8.0353976 | EY15: =$EL$3/(1+$CI$15)^CJ15 -> 7.1510827 | EZ15: =$EL$3/(1+$CI$16)^CJ15 -> 6.3706879 | FA15: =$EL$3/(1+$CI$17)^CJ15 -> 5.6812386 | FB15: =$EL$3/(1+$CI$18)^CJ15 -> 5.0714736 | FC15: =SUM(EY3:EY52) -> 258.79574 | FE15: =$FD$3/(1+$CI$3)^CJ15 -> 19.435982 | FF15: =$FD$3/(1+$CI$4)^CJ15 -> 17.099449 | FG15: =$FD$3/(1+$CI$5)^CJ15 -> 15.062616 | FH15: =$FD$3/(1+$CI$6)^CJ15 -> 13.502452 | FI15: =$FD$3/(1+$CI$7)^CJ15 -> 13.284675 | FJ15: =$FD$3/(1+$CI$8)^CJ15 -> 11.730687 | FK15: =$FD$3/(1+$CI$9)^CJ15 -> 10.3707 | FL15: =$FD$3/(1+$CI$10)^CJ15 -> 9.6134998 | FM15: =$FD$3/(1+$CI$11)^CJ15 -> 8.1334634 | FN15: =$FD$3/(1+$CI$12)^CJ15 -> 7.2150586 | FO15: =$FD$3/(1+$CI$13)^CJ15 -> 6.4073645 | FP15: =$FD$3/(1+$CI$14)^CJ15 -> 5.696205 | FQ15: =$FD$3/(1+$CI$15)^CJ15 -> 5.0693239 | FR15: =$FD$3/(1+$CI$16)^CJ15 -> 4.5161106 | FS15: =$FD$3/(1+$CI$17)^CJ15 -> 4.0273676 | FT15: =$FD$3/(1+$CI$18)^CJ15 -> 3.5951119 | FU15: =SUM(FQ3:FQ52) -> 183.45746 | FW15: =$FV$3/(1+$CI$3)^CJ15 -> 0.035755296 | FX15: =$FV$3/(1+$CI$4)^CJ15 -> 0.031456906 | FY15: =$FV$3/(1+$CI$5)^CJ15 -> 0.027709859 | FZ15: =$FV$3/(1+$CI$6)^CJ15 -> 0.02483971 | GA15: =$FV$3/(1+$CI$7)^CJ15 -> 0.024439079 | GB15: =$FV$3/(1+$CI$8)^CJ15 -> 0.021580294 | GC15: =$FV$3/(1+$CI$9)^CJ15 -> 0.019078402 | GD15: =$FV$3/(1+$CI$10)^CJ15 -> 0.017685422 | GE15: =$FV$3/(1+$CI$11)^CJ15 -> 0.014962681 | GF15: =$FV$3/(1+$CI$12)^CJ15 -> 0.013273143 | GG15: =$FV$3/(1+$CI$13)^CJ15 -> 0.011787273 | GH15: =$FV$3/(1+$CI$14)^CJ15 -> 0.010478992 | GI15: =$FV$3/(1+$CI$15)^CJ15 -> 0.0093257538 | GJ15: =$FV$3/(1+$CI$16)^CJ15 -> 0.008308038 | GK15: =$FV$3/(1+$CI$17)^CJ15 -> 0.0074089246 | GL15: =$FV$3/(1+$CI$18)^CJ15 -> 0.0066137278 | GM15: =SUM(GI3:GI52) -> 0.3374965
A16: Microsoft | B16: 41455 | C16: 34.688 | D16: 307.8869 | E16: 78.566 | F16: 1842.6 | G16: 21.863 | H16: =(D16/AI16) -> 14.082555 | I16: =(D16/G16) -> 14.082555 | J16: -5.841 | K16: -3.9 | L16: -1.375 | M16: -0.371 | N16: =(C16+L16+J16+K16+M16) -> 23.201 | P16: 8605000000 | Q16: =(P16-P15)/P15*100 -> -0.90971902 | S16: 35.78 | T16: =(S16*P16) -> 307886900000 | U16: =(D16-D15)/D15*100 -> 7.6009182 | V16: 78.944 | W16: =(V16-V15)/V15*100 -> 18.957853 | X16: 61.206 | Y16: =(X16-X15)/X15*100 -> 23.049396 | AA16: 0.1 | AB16: 78.944 | AC16: 66.363 | AD16: =(G15/AA16) -> 169.78 | AE16: =(D16-AC16-AD16) -> 71.7439 | AF16: =((((D16-AD16)/(G16)*AA16)-1)/(1+(D16-AD16)/(G16))) -> -0.050336407 | AG16: =(1+AF16)/(1+AA16) -> 0.86333054 | AI16: 21.863 | AJ16: 21.863 | AL16: 21.863 | AM16: =D16/AL16 -> 14.082555 | AN16: 21.863 | AO16: =D16/AN16 -> 14.082555 | AQ16: =$D$28/AL16 -> 126.74149 | AS16: =$D$28/AN16 -> 126.74149 | AV16: =(D16/AB16) -> 3.9000671 | AW16: =(D16/E16) -> 3.9188313 | AX16: 17.738 | AY16: =(AB16-AX16) -> 61.206 | AZ16: =(D16/AY16) -> 5.0303385 | BB16: 23.363 | BC16: -2.441 | BD16: =(BB16/D16)*100 -> 7.588176 | BE16: =(BC16/D16)*100 -> -0.7928236 | BG16: 35.78 | BH16: 8605000000 | BI16: =(BG16*BH16) -> 307886900000 | BJ16: 78.944 | BK16: =AY16 -> 61.206 | BL16: 101.466 | BM16: 37.417 | BN16: 26.07 | BO16: =(BL16-BM16-BN16) -> 37.979 | BP16: 77.022 | BQ16: =(BP16-BM16-BN16) -> 13.535 | BS16: =D16 -> 307.8869 | BT16: =E16 -> 78.566 | BU16: =N16 -> 23.201 | BV16: =G16 -> 21.863 | BW16: =((BS16/BS11)^(1/5)-1)*100 -> -3.2876734 | BX16: =((BT16/BT11)^(1/5)-1)*100 -> 5.3927616 | BY16: =((BU16/BU11)^(1/5)-1)*100 -> 17.189392 | BZ16: =((BV16/BV11)^(1/5)-1)*100 -> 5.9718706 | CA16: =((BS16/BS6)^(1/10)-1)*100 -> -1.8418686 | CB16: =((BT16/BT6)^(1/10)-1)*100 -> 9.3340446 | CC16: =((BU16/BU6)^(1/10)-1)*100 -> 5.2998248 | CD16: =((BV16/BV6)^(1/10)-1)*100 -> 13.761917 | CE16: 41455 | CF16: 307.8869 | CG16: 22.992 | CH16: =(CG16/CF16) -> 0.074676773 | CI16: 0.13 | CJ16: 14 | CK16: =$CG$27/(1+$CI$3)^CJ16 -> 4.2967471 | CL16: =$CG$27/(1+$CI$4)^CJ16 -> 3.7431447 | CM16: =$CG$27/(1+$CI$5)^CJ16 -> 3.2652608 | CN16: =$CG$27/(1+$CI$6)^CJ16 -> 2.9025331 | CO16: =$CG$27/(1+$CI$7)^CJ16 -> 2.8521494 | CP16: =$CG$27/(1+$CI$8)^CJ16 -> 2.4945306 | CQ16: =$CG$27/(1+$CI$9)^CJ16 -> 2.1845245 | CR16: =$CG$27/(1+$CI$10)^CJ16 -> 2.0132492 | CS16: =$CG$27/(1+$CI$11)^CJ16 -> 1.6815371 | CT16: =$CG$27/(1+$CI$12)^CJ16 -> 1.4779783 | CU16: =$CG$27/(1+$CI$13)^CJ16 -> 1.3005931 | CV16: =$CG$27/(1+$CI$14)^CJ16 -> 1.1458224 | CW16: =$CG$27/(1+$CI$15)^CJ16 -> 1.0106173 | CX16: =$CG$27/(1+$CI$16)^CJ16 -> 0.89236148 | CY16: =$CG$27/(1+$CI$17)^CJ16 -> 0.78880764 | CZ16: =$CG$27/(1+$CI$18)^CJ16 -> 0.69802224 | DA16: =SUM(CX3:CX52) -> 37.870822 | DC16: =$DB$3/(1+$CI$3)^CJ16 -> 30.696643 | DD16: =$DB$3/(1+$CI$4)^CJ16 -> 26.74162 | DE16: =$DB$3/(1+$CI$5)^CJ16 -> 23.327542 | DF16: =$DB$3/(1+$CI$6)^CJ16 -> 20.736157 | DG16: =$DB$3/(1+$CI$7)^CJ16 -> 20.376208 | DH16: =$DB$3/(1+$CI$8)^CJ16 -> 17.821323 | DI16: =$DB$3/(1+$CI$9)^CJ16 -> 15.60659 | DJ16: =$DB$3/(1+$CI$10)^CJ16 -> 14.382972 | DK16: =$DB$3/(1+$CI$11)^CJ16 -> 12.013168 | DL16: =$DB$3/(1+$CI$12)^CJ16 -> 10.558912 | DM16: =$DB$3/(1+$CI$13)^CJ16 -> 9.2916433 | DN16: =$DB$3/(1+$CI$14)^CJ16 -> 8.1859374 | DO16: =$DB$3/(1+$CI$15)^CJ16 -> 7.2200101 | DP16: =$DB$3/(1+$CI$16)^CJ16 -> 6.3751721 | DQ16: =$DB$3/(1+$CI$17)^CJ16 -> 5.635367 | DR16: =$DB$3/(1+$CI$18)^CJ16 -> 4.9867817 | DS16: =SUM(DP3:DP52) -> 270.55516 | DU16: =$DT$3/(1+$CI$3)^CJ16 -> 34.063748 | DV16: =$DT$3/(1+$CI$4)^CJ16 -> 29.6749 | DW16: =$DT$3/(1+$CI$5)^CJ16 -> 25.886332 | DX16: =$DT$3/(1+$CI$6)^CJ16 -> 23.0107 | DY16: =$DT$3/(1+$CI$7)^CJ16 -> 22.611268 | DZ16: =$DT$3/(1+$CI$8)^CJ16 -> 19.776138 | EA16: =$DT$3/(1+$CI$9)^CJ16 -> 17.318471 | EB16: =$DT$3/(1+$CI$10)^CJ16 -> 15.960635 | EC16: =$DT$3/(1+$CI$11)^CJ16 -> 13.330888 | ED16: =$DT$3/(1+$CI$12)^CJ16 -> 11.717115 | EE16: =$DT$3/(1+$CI$13)^CJ16 -> 10.310841 | EF16: =$DT$3/(1+$CI$14)^CJ16 -> 9.0838502 | EG16: =$DT$3/(1+$CI$15)^CJ16 -> 8.0119706 | EH16: =$DT$3/(1+$CI$16)^CJ16 -> 7.0744626 | EI16: =$DT$3/(1+$CI$17)^CJ16 -> 6.2535085 | EJ16: =$DT$3/(1+$CI$18)^CJ16 -> 5.5337801 | EK16: =SUM(EH3:EH52) -> 300.23227 | EM16: =$EL$3/(1+$CI$3)^CJ16 -> 27.146064 | EN16: =$EL$3/(1+$CI$4)^CJ16 -> 23.648505 | EO16: =$EL$3/(1+$CI$5)^CJ16 -> 20.629322 | EP16: =$EL$3/(1+$CI$6)^CJ16 -> 18.337674 | EQ16: =$EL$3/(1+$CI$7)^CJ16 -> 18.019359 | ER16: =$EL$3/(1+$CI$8)^CJ16 -> 15.759989 | ES16: =$EL$3/(1+$CI$9)^CJ16 -> 13.801427 | ET16: =$EL$3/(1+$CI$10)^CJ16 -> 12.719341 | EU16: =$EL$3/(1+$CI$11)^CJ16 -> 10.623644 | EV16: =$EL$3/(1+$CI$12)^CJ16 -> 9.3375969 | EW16: =$EL$3/(1+$CI$13)^CJ16 -> 8.2169095 | EX16: =$EL$3/(1+$CI$14)^CJ16 -> 7.2390969 | EY16: =$EL$3/(1+$CI$15)^CJ16 -> 6.3848952 | EZ16: =$EL$3/(1+$CI$16)^CJ16 -> 5.6377769 | FA16: =$EL$3/(1+$CI$17)^CJ16 -> 4.9835426 | FB16: =$EL$3/(1+$CI$18)^CJ16 -> 4.409977 | FC16: =SUM(EZ3:EZ52) -> 239.26094 | FE16: =$FD$3/(1+$CI$3)^CJ16 -> 19.243546 | FF16: =$FD$3/(1+$CI$4)^CJ16 -> 16.764165 | FG16: =$FD$3/(1+$CI$5)^CJ16 -> 14.623899 | FH16: =$FD$3/(1+$CI$6)^CJ16 -> 12.999376 | FI16: =$FD$3/(1+$CI$7)^CJ16 -> 12.773726 | FJ16: =$FD$3/(1+$CI$8)^CJ16 -> 11.172083 | FK16: =$FD$3/(1+$CI$9)^CJ16 -> 9.7836796 | FL16: =$FD$3/(1+$CI$10)^CJ16 -> 9.0166008 | FM16: =$FD$3/(1+$CI$11)^CJ16 -> 7.5309846 | FN16: =$FD$3/(1+$CI$12)^CJ16 -> 6.6193198 | FO16: =$FD$3/(1+$CI$13)^CJ16 -> 5.8248768 | FP16: =$FD$3/(1+$CI$14)^CJ16 -> 5.1317162 | FQ16: =$FD$3/(1+$CI$15)^CJ16 -> 4.5261821 | FR16: =$FD$3/(1+$CI$16)^CJ16 -> 3.9965581 | FS16: =$FD$3/(1+$CI$17)^CJ16 -> 3.5327786 | FT16: =$FD$3/(1+$CI$18)^CJ16 -> 3.1261843 | FU16: =SUM(FR3:FR52) -> 169.60945 | FW16: =$FV$3/(1+$CI$3)^CJ16 -> 0.035401283 | FX16: =$FV$3/(1+$CI$4)^CJ16 -> 0.030840104 | FY16: =$FV$3/(1+$CI$5)^CJ16 -> 0.026902776 | FZ16: =$FV$3/(1+$CI$6)^CJ16 -> 0.02391423 | GA16: =$FV$3/(1+$CI$7)^CJ16 -> 0.023499114 | GB16: =$FV$3/(1+$CI$8)^CJ16 -> 0.020552661 | GC16: =$FV$3/(1+$CI$9)^CJ16 -> 0.017998492 | GD16: =$FV$3/(1+$CI$10)^CJ16 -> 0.01658734 | GE16: =$FV$3/(1+$CI$11)^CJ16 -> 0.013854334 | GF16: =$FV$3/(1+$CI$12)^CJ16 -> 0.012177195 | GG16: =$FV$3/(1+$CI$13)^CJ16 -> 0.010715702 | GH16: =$FV$3/(1+$CI$14)^CJ16 -> 0.0094405335 | GI16: =$FV$3/(1+$CI$15)^CJ16 -> 0.0083265659 | GJ16: =$FV$3/(1+$CI$16)^CJ16 -> 0.007352246 | GK16: =$FV$3/(1+$CI$17)^CJ16 -> 0.0064990566 | GL16: =$FV$3/(1+$CI$18)^CJ16 -> 0.0057510676 | GM16: =SUM(GJ3:GJ52) -> 0.31202108
A17: Microsoft | B17: 41820 | C17: 37.887 | D17: 370.16499 | E17: 87.491 | F17: 2082.1 | G17: 22.074 | H17: =(D17/AI17) -> 16.769276 | I17: =(D17/G17) -> 16.769276 | J17: -11.422 | K17: -5.5 | L17: 0.624 | M17: -0.509 | N17: =(C17+L17+J17+K17+M17) -> 21.08 | P17: 8671000000 | Q17: =(P17-P16)/P16*100 -> 0.76699593 | S17: 42.69 | T17: =(S17*P17) -> 370164990000 | U17: =(D17-D16)/D16*100 -> 20.227587 | V17: 89.784 | W17: =(V17-V16)/V16*100 -> 13.731253 | X17: 62.676 | Y17: =(X17-X16)/X16*100 -> 2.4017253 | AA17: 0.1 | AB17: 89.784 | AC17: 78.944 | AD17: =(G16/AA17) -> 218.63 | AE17: =(D17-AC17-AD17) -> 72.59099 | AF17: =((((D17-AD17)/(G17)*AA17)-1)/(1+(D17-AD17)/(G17))) -> -0.039862573 | AG17: =(1+AF17)/(1+AA17) -> 0.87285221 | AI17: 22.074 | AJ17: 22.074 | AL17: 22.074 | AM17: =D17/AL17 -> 16.769276 | AN17: 22.074 | AO17: =D17/AN17 -> 16.769276 | AQ17: =$D$28/AL17 -> 125.53 | AS17: =$D$28/AN17 -> 125.53 | AV17: =(D17/AB17) -> 4.1228391 | AW17: =(D17/E17) -> 4.2308922 | AX17: 27.108 | AY17: =(AB17-AX17) -> 62.676 | AZ17: =(D17/AY17) -> 5.9060085 | BB17: 21.318 | BC17: 4.38 | BD17: =(BB17/D17)*100 -> 5.7590536 | BE17: =(BC17/D17)*100 -> 1.1832561 | BG17: 42.69 | BH17: 8671000000 | BI17: =(BG17*BH17) -> 370164990000 | BJ17: 89.784 | BK17: =AY17 -> 62.676 | BL17: 114.246 | BM17: 45.625 | BN17: 36.975 | BO17: =(BL17-BM17-BN17) -> 31.646 | BP17: 85.709 | BQ17: =(BP17-BM17-BN17) -> 3.109 | BS17: =D17 -> 370.16499 | BT17: =E17 -> 87.491 | BU17: =N17 -> 21.08 | BV17: =G17 -> 22.074 | CD17: =((BV17/BV7)^(1/10)-1)*100 -> 10.452749 | CE17: 41820 | CF17: 370.16499 | CG17: 20.809 | CH17: =(CG17/CF17) -> 0.056215473 | CI17: 0.14 | CJ17: 15 | CK17: =$CG$27/(1+$CI$3)^CJ17 -> 4.2542051 | CL17: =$CG$27/(1+$CI$4)^CJ17 -> 3.6697498 | CM17: =$CG$27/(1+$CI$5)^CJ17 -> 3.1701562 | CN17: =$CG$27/(1+$CI$6)^CJ17 -> 2.7943902 | CO17: =$CG$27/(1+$CI$7)^CJ17 -> 2.7424514 | CP17: =$CG$27/(1+$CI$8)^CJ17 -> 2.3757434 | CQ17: =$CG$27/(1+$CI$9)^CJ17 -> 2.0608721 | CR17: =$CG$27/(1+$CI$10)^CJ17 -> 1.8882472 | CS17: =$CG$27/(1+$CI$11)^CJ17 -> 1.5569788 | CT17: =$CG$27/(1+$CI$12)^CJ17 -> 1.3559434 | CU17: =$CG$27/(1+$CI$13)^CJ17 -> 1.1823573 | CV17: =$CG$27/(1+$CI$14)^CJ17 -> 1.0322725 | CW17: =$CG$27/(1+$CI$15)^CJ17 -> 0.90233683 | CX17: =$CG$27/(1+$CI$16)^CJ17 -> 0.78970043 | CY17: =$CG$27/(1+$CI$17)^CJ17 -> 0.69193652 | CZ17: =$CG$27/(1+$CI$18)^CJ17 -> 0.60697586 | DA17: =SUM(CY3:CY52) -> 35.202042 | DC17: =$DB$3/(1+$CI$3)^CJ17 -> 30.392716 | DD17: =$DB$3/(1+$CI$4)^CJ17 -> 26.217275 | DE17: =$DB$3/(1+$CI$5)^CJ17 -> 22.648099 | DF17: =$DB$3/(1+$CI$6)^CJ17 -> 19.963567 | DG17: =$DB$3/(1+$CI$7)^CJ17 -> 19.592508 | DH17: =$DB$3/(1+$CI$8)^CJ17 -> 16.972688 | DI17: =$DB$3/(1+$CI$9)^CJ17 -> 14.723198 | DJ17: =$DB$3/(1+$CI$10)^CJ17 -> 13.489938 | DK17: =$DB$3/(1+$CI$11)^CJ17 -> 11.123304 | DL17: =$DB$3/(1+$CI$12)^CJ17 -> 9.6870748 | DM17: =$DB$3/(1+$CI$13)^CJ17 -> 8.4469485 | DN17: =$DB$3/(1+$CI$14)^CJ17 -> 7.3747184 | DO17: =$DB$3/(1+$CI$15)^CJ17 -> 6.4464376 | DP17: =$DB$3/(1+$CI$16)^CJ17 -> 5.6417452 | DQ17: =$DB$3/(1+$CI$17)^CJ17 -> 4.9433044 | DR17: =$DB$3/(1+$CI$18)^CJ17 -> 4.3363319 | DS17: =SUM(DQ3:DQ52) -> 251.48897 | DU17: =$DT$3/(1+$CI$3)^CJ17 -> 33.726483 | DV17: =$DT$3/(1+$CI$4)^CJ17 -> 29.093039 | DW17: =$DT$3/(1+$CI$5)^CJ17 -> 25.132361 | DX17: =$DT$3/(1+$CI$6)^CJ17 -> 22.153364 | DY17: =$DT$3/(1+$CI$7)^CJ17 -> 21.741604 | DZ17: =$DT$3/(1+$CI$8)^CJ17 -> 18.834417 | EA17: =$DT$3/(1+$CI$9)^CJ17 -> 16.33818 | EB17: =$DT$3/(1+$CI$10)^CJ17 -> 14.969645 | EC17: =$DT$3/(1+$CI$11)^CJ17 -> 12.343415 | ED17: =$DT$3/(1+$CI$12)^CJ17 -> 10.749647 | EE17: =$DT$3/(1+$CI$13)^CJ17 -> 9.3734914 | EF17: =$DT$3/(1+$CI$14)^CJ17 -> 8.1836488 | EG17: =$DT$3/(1+$CI$15)^CJ17 -> 7.1535452 | EH17: =$DT$3/(1+$CI$16)^CJ17 -> 6.2605864 | EI17: =$DT$3/(1+$CI$17)^CJ17 -> 5.4855338 | EJ17: =$DT$3/(1+$CI$18)^CJ17 -> 4.8119827 | EK17: =SUM(EI3:EI52) -> 279.07472 | EM17: =$EL$3/(1+$CI$3)^CJ17 -> 26.877291 | EN17: =$EL$3/(1+$CI$4)^CJ17 -> 23.184809 | EO17: =$EL$3/(1+$CI$5)^CJ17 -> 20.028468 | EP17: =$EL$3/(1+$CI$6)^CJ17 -> 17.654447 | EQ17: =$EL$3/(1+$CI$7)^CJ17 -> 17.326307 | ER17: =$EL$3/(1+$CI$8)^CJ17 -> 15.009513 | ES17: =$EL$3/(1+$CI$9)^CJ17 -> 13.020214 | ET17: =$EL$3/(1+$CI$10)^CJ17 -> 11.929601 | EU17: =$EL$3/(1+$CI$11)^CJ17 -> 9.8367076 | EV17: =$EL$3/(1+$CI$12)^CJ17 -> 8.5666027 | EW17: =$EL$3/(1+$CI$13)^CJ17 -> 7.4699177 | EX17: =$EL$3/(1+$CI$14)^CJ17 -> 6.5217089 | EY17: =$EL$3/(1+$CI$15)^CJ17 -> 5.7007993 | EZ17: =$EL$3/(1+$CI$16)^CJ17 -> 4.9891831 | FA17: =$EL$3/(1+$CI$17)^CJ17 -> 4.3715286 | FB17: =$EL$3/(1+$CI$18)^CJ17 -> 3.8347626 | FC17: =SUM(FA3:FA52) -> 222.40007 | FE17: =$FD$3/(1+$CI$3)^CJ17 -> 19.053016 | FF17: =$FD$3/(1+$CI$4)^CJ17 -> 16.435456 | FG17: =$FD$3/(1+$CI$5)^CJ17 -> 14.197961 | FH17: =$FD$3/(1+$CI$6)^CJ17 -> 12.515043 | FI17: =$FD$3/(1+$CI$7)^CJ17 -> 12.282429 | FJ17: =$FD$3/(1+$CI$8)^CJ17 -> 10.640079 | FK17: =$FD$3/(1+$CI$9)^CJ17 -> 9.2298865 | FL17: =$FD$3/(1+$CI$10)^CJ17 -> 8.4567631 | FM17: =$FD$3/(1+$CI$11)^CJ17 -> 6.9731339 | FN17: =$FD$3/(1+$CI$12)^CJ17 -> 6.0727705 | FO17: =$FD$3/(1+$CI$13)^CJ17 -> 5.2953426 | FP17: =$FD$3/(1+$CI$14)^CJ17 -> 4.6231678 | FQ17: =$FD$3/(1+$CI$15)^CJ17 -> 4.041234 | FR17: =$FD$3/(1+$CI$16)^CJ17 -> 3.5367771 | FS17: =$FD$3/(1+$CI$17)^CJ17 -> 3.0989286 | FT17: =$FD$3/(1+$CI$18)^CJ17 -> 2.7184211 | FU17: =SUM(FS3:FS52) -> 157.65697 | FW17: =$FV$3/(1+$CI$3)^CJ17 -> 0.035050776 | FX17: =$FV$3/(1+$CI$4)^CJ17 -> 0.030235396 | FY17: =$FV$3/(1+$CI$5)^CJ17 -> 0.0261192 | FZ17: =$FV$3/(1+$CI$6)^CJ17 -> 0.023023231 | GA17: =$FV$3/(1+$CI$7)^CJ17 -> 0.022595302 | GB17: =$FV$3/(1+$CI$8)^CJ17 -> 0.019573963 | GC17: =$FV$3/(1+$CI$9)^CJ17 -> 0.01697971 | GD17: =$FV$3/(1+$CI$10)^CJ17 -> 0.015557438 | GE17: =$FV$3/(1+$CI$11)^CJ17 -> 0.012828087 | GF17: =$FV$3/(1+$CI$12)^CJ17 -> 0.011171739 | GG17: =$FV$3/(1+$CI$13)^CJ17 -> 0.0097415477 | GH17: =$FV$3/(1+$CI$14)^CJ17 -> 0.0085049851 | GI17: =$FV$3/(1+$CI$15)^CJ17 -> 0.0074344338 | GJ17: =$FV$3/(1+$CI$16)^CJ17 -> 0.0065064124 | GK17: =$FV$3/(1+$CI$17)^CJ17 -> 0.0057009269 | GL17: =$FV$3/(1+$CI$18)^CJ17 -> 0.0050009284 | GM17: =SUM(GK3:GK52) -> 0.29003277
A18: Microsoft | B18: 42185 | C18: 33.175 | D18: 370.86 | E18: 96.148 | F18: 2060.6 | G18: 12.193 | H18: =(D18/AI18) -> 30.415812 | I18: =(D18/G18) -> 30.415812 | J18: -9.667 | K18: -4.4 | L18: 1.513 | M18: -0.62 | N18: =(C18+L18+J18+K18+M18) -> 20.001 | P18: 8400000000 | Q18: =(P18-P17)/P17*100 -> -3.1253604 | S18: 50.05 | T18: =(S18*P18) -> 420420000000 | U18: =(D18-D17)/D17*100 -> 0.18775682 | V18: 80.083 | W18: =(V18-V17)/V17*100 -> -10.80482 | X18: 58.309 | Y18: =(X18-X17)/X17*100 -> -6.9675793 | AA18: 0.1 | AB18: 80.083 | AC18: 89.784 | AD18: =(G17/AA18) -> 220.74 | AE18: =(D18-AC18-AD18) -> 60.336 | AF18: =((((D18-AD18)/(G18)*AA18)-1)/(1+(D18-AD18)/(G18))) -> 0.017367678 | AG18: =(1+AF18)/(1+AA18) -> 0.92487971 | AI18: 12.193 | AJ18: 12.193 | AL18: 12.193 | AM18: =D18/AL18 -> 30.415812 | AN18: 12.193 | AO18: =D18/AN18 -> 30.415812 | AQ18: =$D$28/AL18 -> 227.25737 | AR18: =AVERAGE(AQ18:AQ27) -> 97.636132 | AS18: =$D$28/AN18 -> 227.25737 | AT18: =AVERAGE(AS18:AS27) -> 97.636132 | AV18: =(D18/AB18) -> 4.6309454 | AW18: =(D18/E18) -> 3.8571785 | AX18: 21.774 | AY18: =(AB18-AX18) -> 58.309 | AZ18: =(D18/AY18) -> 6.3602531 | BB18: 20.621 | BC18: -3.288 | BD18: =(BB18/D18)*100 -> 5.5603193 | BE18: =(BC18/D18)*100 -> -0.88658793 | BG18: 50.05 | BH18: 8400000000 | BI18: =(BG18*BH18) -> 420420000000 | BJ18: 80.083 | BK18: =AY18 -> 58.309 | BL18: 124.712 | BM18: 49.858 | BN18: 46.282 | BO18: =(BL18-BM18-BN18) -> 28.572 | BP18: 96.526 | BQ18: =(BP18-BM18-BN18) -> 0.386 | BS18: =D18 -> 370.86 | BT18: =E18 -> 96.148 | BU18: =N18 -> 20.001 | BV18: =G18 -> 12.193 | CE18: 42185 | CF18: 370.86 | CG18: 20.001 | CH18: =(CG18/CF18) -> 0.053931403 | CI18: 0.15 | CJ18: 16 | CK18: =$CG$27/(1+$CI$3)^CJ18 -> 4.2120842 | CL18: =$CG$27/(1+$CI$4)^CJ18 -> 3.5977939 | CM18: =$CG$27/(1+$CI$5)^CJ18 -> 3.0778215 | CN18: =$CG$27/(1+$CI$6)^CJ18 -> 2.6902765 | CO18: =$CG$27/(1+$CI$7)^CJ18 -> 2.6369725 | CP18: =$CG$27/(1+$CI$8)^CJ18 -> 2.2626128 | CQ18: =$CG$27/(1+$CI$9)^CJ18 -> 1.944219 | CR18: =$CG$27/(1+$CI$10)^CJ18 -> 1.7710066 | CS18: =$CG$27/(1+$CI$11)^CJ18 -> 1.441647 | CT18: =$CG$27/(1+$CI$12)^CJ18 -> 1.2439848 | CU18: =$CG$27/(1+$CI$13)^CJ18 -> 1.0748703 | CV18: =$CG$27/(1+$CI$14)^CJ18 -> 0.9299752 | CW18: =$CG$27/(1+$CI$15)^CJ18 -> 0.80565789 | CX18: =$CG$27/(1+$CI$16)^CJ18 -> 0.69884994 | CY18: =$CG$27/(1+$CI$17)^CJ18 -> 0.60696186 | CZ18: =$CG$27/(1+$CI$18)^CJ18 -> 0.5278051 | DA18: =SUM(CZ3:CZ52) -> 32.877843 | DC18: =$DB$3/(1+$CI$3)^CJ18 -> 30.091798 | DD18: =$DB$3/(1+$CI$4)^CJ18 -> 25.703211 | DE18: =$DB$3/(1+$CI$5)^CJ18 -> 21.988445 | DF18: =$DB$3/(1+$CI$6)^CJ18 -> 19.219762 | DG18: =$DB$3/(1+$CI$7)^CJ18 -> 18.83895 | DH18: =$DB$3/(1+$CI$8)^CJ18 -> 16.164465 | DI18: =$DB$3/(1+$CI$9)^CJ18 -> 13.889809 | DJ18: =$DB$3/(1+$CI$10)^CJ18 -> 12.652352 | DK18: =$DB$3/(1+$CI$11)^CJ18 -> 10.299355 | DL18: =$DB$3/(1+$CI$12)^CJ18 -> 8.8872246 | DM18: =$DB$3/(1+$CI$13)^CJ18 -> 7.6790441 | DN18: =$DB$3/(1+$CI$14)^CJ18 -> 6.6438904 | DO18: =$DB$3/(1+$CI$15)^CJ18 -> 5.7557478 | DP18: =$DB$3/(1+$CI$16)^CJ18 -> 4.9926949 | DQ18: =$DB$3/(1+$CI$17)^CJ18 -> 4.3362319 | DR18: =$DB$3/(1+$CI$18)^CJ18 -> 3.7707234 | DS18: =SUM(DR3:DR52) -> 234.88453 | DU18: =$DT$3/(1+$CI$3)^CJ18 -> 33.392558 | DV18: =$DT$3/(1+$CI$4)^CJ18 -> 28.522587 | DW18: =$DT$3/(1+$CI$5)^CJ18 -> 24.400351 | DX18: =$DT$3/(1+$CI$6)^CJ18 -> 21.327972 | DY18: =$DT$3/(1+$CI$7)^CJ18 -> 20.905388 | DZ18: =$DT$3/(1+$CI$8)^CJ18 -> 17.93754 | EA18: =$DT$3/(1+$CI$9)^CJ18 -> 15.413378 | EB18: =$DT$3/(1+$CI$10)^CJ18 -> 14.040184 | EC18: =$DT$3/(1+$CI$11)^CJ18 -> 11.429088 | ED18: =$DT$3/(1+$CI$12)^CJ18 -> 9.8620613 | EE18: =$DT$3/(1+$CI$13)^CJ18 -> 8.5213559 | EF18: =$DT$3/(1+$CI$14)^CJ18 -> 7.3726566 | EG18: =$DT$3/(1+$CI$15)^CJ18 -> 6.3870939 | EH18: =$DT$3/(1+$CI$16)^CJ18 -> 5.5403419 | EI18: =$DT$3/(1+$CI$17)^CJ18 -> 4.8118717 | EJ18: =$DT$3/(1+$CI$18)^CJ18 -> 4.1843328 | EK18: =SUM(EJ3:EJ52) -> 260.64894 | EM18: =$EL$3/(1+$CI$3)^CJ18 -> 26.611179 | EN18: =$EL$3/(1+$CI$4)^CJ18 -> 22.730205 | EO18: =$EL$3/(1+$CI$5)^CJ18 -> 19.445114 | EP18: =$EL$3/(1+$CI$6)^CJ18 -> 16.996676 | EQ18: =$EL$3/(1+$CI$7)^CJ18 -> 16.659911 | ER18: =$EL$3/(1+$CI$8)^CJ18 -> 14.294774 | ES18: =$EL$3/(1+$CI$9)^CJ18 -> 12.283221 | ET18: =$EL$3/(1+$CI$10)^CJ18 -> 11.188896 | EU18: =$EL$3/(1+$CI$11)^CJ18 -> 9.1080626 | EV18: =$EL$3/(1+$CI$12)^CJ18 -> 7.8592685 | EW18: =$EL$3/(1+$CI$13)^CJ18 -> 6.7908343 | EX18: =$EL$3/(1+$CI$14)^CJ18 -> 5.8754135 | EY18: =$EL$3/(1+$CI$15)^CJ18 -> 5.0899994 | EZ18: =$EL$3/(1+$CI$16)^CJ18 -> 4.4152063 | FA18: =$EL$3/(1+$CI$17)^CJ18 -> 3.8346742 | FB18: =$EL$3/(1+$CI$18)^CJ18 -> 3.3345762 | FC18: =SUM(FB3:FB52) -> 207.71621 | FE18: =$FD$3/(1+$CI$3)^CJ18 -> 18.864372 | FF18: =$FD$3/(1+$CI$4)^CJ18 -> 16.113192 | FG18: =$FD$3/(1+$CI$5)^CJ18 -> 13.784428 | FH18: =$FD$3/(1+$CI$6)^CJ18 -> 12.048757 | FI18: =$FD$3/(1+$CI$7)^CJ18 -> 11.810027 | FJ18: =$FD$3/(1+$CI$8)^CJ18 -> 10.133409 | FK18: =$FD$3/(1+$CI$9)^CJ18 -> 8.70744 | FL18: =$FD$3/(1+$CI$10)^CJ18 -> 7.9316855 | FM18: =$FD$3/(1+$CI$11)^CJ18 -> 6.4566055 | FN18: =$FD$3/(1+$CI$12)^CJ18 -> 5.5713491 | FO18: =$FD$3/(1+$CI$13)^CJ18 -> 4.8139478 | FP18: =$FD$3/(1+$CI$14)^CJ18 -> 4.165016 | FQ18: =$FD$3/(1+$CI$15)^CJ18 -> 3.6082446 | FR18: =$FD$3/(1+$CI$16)^CJ18 -> 3.1298912 | FS18: =$FD$3/(1+$CI$17)^CJ18 -> 2.7183584 | FT18: =$FD$3/(1+$CI$18)^CJ18 -> 2.3638444 | FU18: =SUM(FT3:FT52) -> 147.24774 | FW18: =$FV$3/(1+$CI$3)^CJ18 -> 0.034703738 | FX18: =$FV$3/(1+$CI$4)^CJ18 -> 0.029642545 | FY18: =$FV$3/(1+$CI$5)^CJ18 -> 0.025358446 | FZ18: =$FV$3/(1+$CI$6)^CJ18 -> 0.022165429 | GA18: =$FV$3/(1+$CI$7)^CJ18 -> 0.021726252 | GB18: =$FV$3/(1+$CI$8)^CJ18 -> 0.018641869 | GC18: =$FV$3/(1+$CI$9)^CJ18 -> 0.016018594 | GD18: =$FV$3/(1+$CI$10)^CJ18 -> 0.014591481 | GE18: =$FV$3/(1+$CI$11)^CJ18 -> 0.011877859 | GF18: =$FV$3/(1+$CI$12)^CJ18 -> 0.010249302 | GG18: =$FV$3/(1+$CI$13)^CJ18 -> 0.0088559525 | GH18: =$FV$3/(1+$CI$14)^CJ18 -> 0.0076621488 | GI18: =$FV$3/(1+$CI$15)^CJ18 -> 0.0066378873 | GJ18: =$FV$3/(1+$CI$16)^CJ18 -> 0.0057578871 | GK18: =$FV$3/(1+$CI$17)^CJ18 -> 0.005000813 | GL18: =$FV$3/(1+$CI$18)^CJ18 -> 0.0043486334 | GM18: =SUM(GL3:GL52) -> 0.27088349
A19: Microsoft | B19: 42551 | C19: 40.401 | D19: 416.72848 | E19: 86.132 | F19: 2251.6 | G19: 16.798 | H19: =(D19/AI19) -> 24.80822 | I19: =(D19/G19) -> 24.80822 | J19: -9.736 | K19: -3.9 | L19: -2.076 | M19: -1.1 | N19: =(C19+L19+J19+K19+M19) -> 23.589 | P19: 8144000000 | Q19: =(P19-P18)/P18*100 -> -3.047619 | S19: 56.85 | T19: =(S19*P19) -> 462986400000 | U19: =(D19-D18)/D18*100 -> 12.368139 | V19: 71.997 | W19: =(V19-V18)/V18*100 -> -10.097024 | X19: 50.392 | Y19: =(X19-X18)/X18*100 -> -13.577664 | AA19: 0.1 | AB19: 71.997 | AC19: 80.083 | AD19: =(G18/AA19) -> 121.93 | AE19: =(D19-AC19-AD19) -> 214.71548 | AF19: =((((D19-AD19)/(G19)*AA19)-1)/(1+(D19-AD19)/(G19))) -> 0.040699587 | AG19: =(1+AF19)/(1+AA19) -> 0.94609053 | AI19: 16.798 | AJ19: 16.798 | AL19: 16.798 | AM19: =D19/AL19 -> 24.80822 | AN19: 16.798 | AO19: =D19/AN19 -> 24.80822 | AQ19: =$D$28/AL19 -> 164.95709 | AS19: =$D$28/AN19 -> 164.95709 | AV19: =(D19/AB19) -> 5.7881367 | AW19: =(D19/E19) -> 4.8382538 | AX19: 21.605 | AY19: =(AB19-AX19) -> 50.392 | AZ19: =(D19/AY19) -> 8.2697349 | BB19: 24.689 | BC19: -1.698 | BD19: =(BB19/D19)*100 -> 5.9244811 | BE19: =(BC19/D19)*100 -> -0.40745955 | BG19: 56.85 | BH19: 8144000000 | BI19: =(BG19*BH19) -> 462986400000 | BJ19: 71.997 | BK19: =AY19 -> 50.392 | BL19: 139.66 | BM19: 59.357 | BN19: 62.114 | BO19: =(BL19-BM19-BN19) -> 18.189 | BP19: 113.24 | BQ19: =(BP19-BM19-BN19) -> -8.231 | BS19: =D19 -> 416.72848 | BT19: =E19 -> 86.132 | BU19: =N19 -> 23.589 | BV19: =G19 -> 16.798 | CE19: 42551 | CF19: 416.72848 | CG19: 23.589 | CH19: =(CG19/CF19) -> 0.056605203 | CJ19: 17 | CK19: =$CG$27/(1+$CI$3)^CJ19 -> 4.1703804 | CL19: =$CG$27/(1+$CI$4)^CJ19 -> 3.5272489 | CM19: =$CG$27/(1+$CI$5)^CJ19 -> 2.9881762 | CN19: =$CG$27/(1+$CI$6)^CJ19 -> 2.5900419 | CO19: =$CG$27/(1+$CI$7)^CJ19 -> 2.5355505 | CP19: =$CG$27/(1+$CI$8)^CJ19 -> 2.1548693 | CQ19: =$CG$27/(1+$CI$9)^CJ19 -> 1.8341689 | CR19: =$CG$27/(1+$CI$10)^CJ19 -> 1.6610454 | CS19: =$CG$27/(1+$CI$11)^CJ19 -> 1.3348584 | CT19: =$CG$27/(1+$CI$12)^CJ19 -> 1.1412704 | CU19: =$CG$27/(1+$CI$13)^CJ19 -> 0.97715482 | CV19: =$CG$27/(1+$CI$14)^CJ19 -> 0.83781549 | CW19: =$CG$27/(1+$CI$15)^CJ19 -> 0.7193374 | CX19: =$CG$27/(1+$CI$16)^CJ19 -> 0.61845127 | CY19: =$CG$27/(1+$CI$17)^CJ19 -> 0.53242269 | CZ19: =$CG$27/(1+$CI$18)^CJ19 -> 0.45896095 | DC19: =$DB$3/(1+$CI$3)^CJ19 -> 29.79386 | DD19: =$DB$3/(1+$CI$4)^CJ19 -> 25.199226 | DE19: =$DB$3/(1+$CI$5)^CJ19 -> 21.348005 | DF19: =$DB$3/(1+$CI$6)^CJ19 -> 18.50367 | DG19: =$DB$3/(1+$CI$7)^CJ19 -> 18.114375 | DH19: =$DB$3/(1+$CI$8)^CJ19 -> 15.394729 | DI19: =$DB$3/(1+$CI$9)^CJ19 -> 13.103594 | DJ19: =$DB$3/(1+$CI$10)^CJ19 -> 11.866772 | DK19: =$DB$3/(1+$CI$11)^CJ19 -> 9.53644 | DL19: =$DB$3/(1+$CI$12)^CJ19 -> 8.153417 | DM19: =$DB$3/(1+$CI$13)^CJ19 -> 6.9809491 | DN19: =$DB$3/(1+$CI$14)^CJ19 -> 5.9854869 | DO19: =$DB$3/(1+$CI$15)^CJ19 -> 5.1390606 | DP19: =$DB$3/(1+$CI$16)^CJ19 -> 4.4183141 | DQ19: =$DB$3/(1+$CI$17)^CJ19 -> 3.8037122 | DR19: =$DB$3/(1+$CI$18)^CJ19 -> 3.2788899 | DU19: =$DT$3/(1+$CI$3)^CJ19 -> 33.061938 | DV19: =$DT$3/(1+$CI$4)^CJ19 -> 27.963321 | DW19: =$DT$3/(1+$CI$5)^CJ19 -> 23.689661 | DX19: =$DT$3/(1+$CI$6)^CJ19 -> 20.533332 | DY19: =$DT$3/(1+$CI$7)^CJ19 -> 20.101335 | DZ19: =$DT$3/(1+$CI$8)^CJ19 -> 17.083371 | EA19: =$DT$3/(1+$CI$9)^CJ19 -> 14.540922 | EB19: =$DT$3/(1+$CI$10)^CJ19 -> 13.168434 | EC19: =$DT$3/(1+$CI$11)^CJ19 -> 10.582489 | ED19: =$DT$3/(1+$CI$12)^CJ19 -> 9.0477627 | EE19: =$DT$3/(1+$CI$13)^CJ19 -> 7.7466871 | EF19: =$DT$3/(1+$CI$14)^CJ19 -> 6.6420329 | EG19: =$DT$3/(1+$CI$15)^CJ19 -> 5.7027624 | EH19: =$DT$3/(1+$CI$16)^CJ19 -> 4.9029575 | EI19: =$DT$3/(1+$CI$17)^CJ19 -> 4.2209401 | EJ19: =$DT$3/(1+$CI$18)^CJ19 -> 3.6385503 | EM19: =$EL$3/(1+$CI$3)^CJ19 -> 26.347702 | EN19: =$EL$3/(1+$CI$4)^CJ19 -> 22.284514 | EO19: =$EL$3/(1+$CI$5)^CJ19 -> 18.878752 | EP19: =$EL$3/(1+$CI$6)^CJ19 -> 16.363412 | EQ19: =$EL$3/(1+$CI$7)^CJ19 -> 16.019145 | ER19: =$EL$3/(1+$CI$8)^CJ19 -> 13.614071 | ES19: =$EL$3/(1+$CI$9)^CJ19 -> 11.587944 | ET19: =$EL$3/(1+$CI$10)^CJ19 -> 10.494181 | EU19: =$EL$3/(1+$CI$11)^CJ19 -> 8.4333913 | EV19: =$EL$3/(1+$CI$12)^CJ19 -> 7.2103381 | EW19: =$EL$3/(1+$CI$13)^CJ19 -> 6.1734857 | EX19: =$EL$3/(1+$CI$14)^CJ19 -> 5.2931653 | EY19: =$EL$3/(1+$CI$15)^CJ19 -> 4.5446423 | EZ19: =$EL$3/(1+$CI$16)^CJ19 -> 3.9072622 | FA19: =$EL$3/(1+$CI$17)^CJ19 -> 3.3637493 | FB19: =$EL$3/(1+$CI$18)^CJ19 -> 2.8996315 | FE19: =$FD$3/(1+$CI$3)^CJ19 -> 18.677596 | FF19: =$FD$3/(1+$CI$4)^CJ19 -> 15.797247 | FG19: =$FD$3/(1+$CI$5)^CJ19 -> 13.38294 | FH19: =$FD$3/(1+$CI$6)^CJ19 -> 11.599843 | FI19: =$FD$3/(1+$CI$7)^CJ19 -> 11.355796 | FJ19: =$FD$3/(1+$CI$8)^CJ19 -> 9.6508653 | FK19: =$FD$3/(1+$CI$9)^CJ19 -> 8.2145661 | FL19: =$FD$3/(1+$CI$10)^CJ19 -> 7.4392098 | FM19: =$FD$3/(1+$CI$11)^CJ19 -> 5.9783384 | FN19: =$FD$3/(1+$CI$12)^CJ19 -> 5.1113294 | FO19: =$FD$3/(1+$CI$13)^CJ19 -> 4.3763162 | FP19: =$FD$3/(1+$CI$14)^CJ19 -> 3.7522667 | FQ19: =$FD$3/(1+$CI$15)^CJ19 -> 3.221647 | FR19: =$FD$3/(1+$CI$16)^CJ19 -> 2.7698152 | FS19: =$FD$3/(1+$CI$17)^CJ19 -> 2.3845249 | FT19: =$FD$3/(1+$CI$18)^CJ19 -> 2.0555169 | FW19: =$FV$3/(1+$CI$3)^CJ19 -> 0.034360137 | FX19: =$FV$3/(1+$CI$4)^CJ19 -> 0.029061319 | FY19: =$FV$3/(1+$CI$5)^CJ19 -> 0.024619851 | FZ19: =$FV$3/(1+$CI$6)^CJ19 -> 0.021339587 | GA19: =$FV$3/(1+$CI$7)^CJ19 -> 0.020890627 | GB19: =$FV$3/(1+$CI$8)^CJ19 -> 0.017754161 | GC19: =$FV$3/(1+$CI$9)^CJ19 -> 0.015111881 | GD19: =$FV$3/(1+$CI$10)^CJ19 -> 0.013685501 | GE19: =$FV$3/(1+$CI$11)^CJ19 -> 0.010998017 | GF19: =$FV$3/(1+$CI$12)^CJ19 -> 0.009403029 | GG19: =$FV$3/(1+$CI$13)^CJ19 -> 0.0080508659 | GH19: =$FV$3/(1+$CI$14)^CJ19 -> 0.0069028367 | GI19: =$FV$3/(1+$CI$15)^CJ19 -> 0.0059266851 | GJ19: =$FV$3/(1+$CI$16)^CJ19 -> 0.0050954753 | GK19: =$FV$3/(1+$CI$17)^CJ19 -> 0.0043866781 | GL19: =$FV$3/(1+$CI$18)^CJ19 -> 0.0037814203
A20: Microsoft | B20: 42916 | C20: 41.855 | D20: 554.05934 | E20: 92.995 | F20: 2689.2 | G20: 21.204 | H20: =(D20/AI20) -> 26.129944 | I20: =(D20/G20) -> 26.129944 | J20: -34.073 | K20: -2.4 | L20: 1.652 | M20: -1.6 | N20: =(C20+L20+J20+K20+M20) -> 5.434 | P20: 8038000000 | Q20: =(P20-P19)/P19*100 -> -1.3015717 | S20: 72.89 | T20: =(S20*P20) -> 585889820000 | U20: =(D20-D19)/D19*100 -> 32.954518 | V20: 87.711 | W20: =(V20-V19)/V19*100 -> 21.825909 | X20: 42.483 | Y20: =(X20-X19)/X19*100 -> -15.694952 | AA20: 0.1 | AB20: 87.711 | AC20: 71.997 | AD20: =(G19/AA20) -> 167.98 | AE20: =(D20-AC20-AD20) -> 314.08234 | AF20: =((((D20-AD20)/(G20)*AA20)-1)/(1+(D20-AD20)/(G20))) -> 0.04273176 | AG20: =(1+AF20)/(1+AA20) -> 0.94793796 | AI20: 21.204 | AJ20: 21.204 | AL20: 21.204 | AM20: =D20/AL20 -> 26.129944 | AN20: 21.204 | AO20: =D20/AN20 -> 26.129944 | AQ20: =$D$28/AL20 -> 130.68049 | AS20: =$D$28/AN20 -> 130.68049 | AV20: =(D20/AB20) -> 6.3168741 | AW20: =(D20/E20) -> 5.9579476 | AX20: 45.228 | AY20: =(AB20-AX20) -> 42.483 | AZ20: =(D20/AY20) -> 13.041907 | BB20: 7.034 | BC20: -19.1 | BD20: =(BB20/D20)*100 -> 1.2695391 | BE20: =(BC20/D20)*100 -> -3.4472842 | BG20: 72.89 | BH20: 8038000000 | BI20: =(BG20*BH20) -> 585889820000 | BJ20: 87.711 | BK20: =AY20 -> 42.483 | BL20: 162.696 | BM20: 55.745 | BN20: 106.856 | BO20: =(BL20-BM20-BN20) -> 0.095 | BP20: 132.981 | BQ20: =(BP20-BM20-BN20) -> -29.62 | BS20: =D20 -> 554.05934 | BT20: =E20 -> 92.995 | BU20: =N20 -> 5.434 | BV20: =G20 -> 21.204 | CE20: 42916 | CF20: 554.05934 | CG20: 5.434 | CH20: =(CG20/CF20) -> 0.0098076137 | CJ20: 18 | CK20: =$CG$27/(1+$CI$3)^CJ20 -> 4.1290895 | CL20: =$CG$27/(1+$CI$4)^CJ20 -> 3.4580872 | CM20: =$CG$27/(1+$CI$5)^CJ20 -> 2.901142 | CN20: =$CG$27/(1+$CI$6)^CJ20 -> 2.4935418 | CO20: =$CG$27/(1+$CI$7)^CJ20 -> 2.4380293 | CP20: =$CG$27/(1+$CI$8)^CJ20 -> 2.0522565 | CQ20: =$CG$27/(1+$CI$9)^CJ20 -> 1.730348 | CR20: =$CG$27/(1+$CI$10)^CJ20 -> 1.5579116 | CS20: =$CG$27/(1+$CI$11)^CJ20 -> 1.23598 | CT20: =$CG$27/(1+$CI$12)^CJ20 -> 1.0470371 | CU20: =$CG$27/(1+$CI$13)^CJ20 -> 0.88832256 | CV20: =$CG$27/(1+$CI$14)^CJ20 -> 0.75478873 | CW20: =$CG$27/(1+$CI$15)^CJ20 -> 0.64226554 | CX20: =$CG$27/(1+$CI$16)^CJ20 -> 0.54730201 | CY20: =$CG$27/(1+$CI$17)^CJ20 -> 0.46703745 | CZ20: =$CG$27/(1+$CI$18)^CJ20 -> 0.39909648 | DC20: =$DB$3/(1+$CI$3)^CJ20 -> 29.498871 | DD20: =$DB$3/(1+$CI$4)^CJ20 -> 24.705124 | DE20: =$DB$3/(1+$CI$5)^CJ20 -> 20.726219 | DF20: =$DB$3/(1+$CI$6)^CJ20 -> 17.814259 | DG20: =$DB$3/(1+$CI$7)^CJ20 -> 17.417668 | DH20: =$DB$3/(1+$CI$8)^CJ20 -> 14.661646 | DI20: =$DB$3/(1+$CI$9)^CJ20 -> 12.361881 | DJ20: =$DB$3/(1+$CI$10)^CJ20 -> 11.129968 | DK20: =$DB$3/(1+$CI$11)^CJ20 -> 8.830037 | DL20: =$DB$3/(1+$CI$12)^CJ20 -> 7.4801991 | DM20: =$DB$3/(1+$CI$13)^CJ20 -> 6.3463174 | DN20: =$DB$3/(1+$CI$14)^CJ20 -> 5.3923305 | DO20: =$DB$3/(1+$CI$15)^CJ20 -> 4.5884469 | DP20: =$DB$3/(1+$CI$16)^CJ20 -> 3.9100124 | DQ20: =$DB$3/(1+$CI$17)^CJ20 -> 3.3365896 | DR20: =$DB$3/(1+$CI$18)^CJ20 -> 2.8512086 | DU20: =$DT$3/(1+$CI$3)^CJ20 -> 32.734592 | DV20: =$DT$3/(1+$CI$4)^CJ20 -> 27.41502 | DW20: =$DT$3/(1+$CI$5)^CJ20 -> 22.999671 | DX20: =$DT$3/(1+$CI$6)^CJ20 -> 19.768299 | DY20: =$DT$3/(1+$CI$7)^CJ20 -> 19.328207 | DZ20: =$DT$3/(1+$CI$8)^CJ20 -> 16.269877 | EA20: =$DT$3/(1+$CI$9)^CJ20 -> 13.717851 | EB20: =$DT$3/(1+$CI$10)^CJ20 -> 12.35081 | EC20: =$DT$3/(1+$CI$11)^CJ20 -> 9.7986008 | ED20: =$DT$3/(1+$CI$12)^CJ20 -> 8.3006997 | EE20: =$DT$3/(1+$CI$13)^CJ20 -> 7.0424429 | EF20: =$DT$3/(1+$CI$14)^CJ20 -> 5.9838135 | EG20: =$DT$3/(1+$CI$15)^CJ20 -> 5.0917522 | EH20: =$DT$3/(1+$CI$16)^CJ20 -> 4.3389004 | EI20: =$DT$3/(1+$CI$17)^CJ20 -> 3.7025791 | EJ20: =$DT$3/(1+$CI$18)^CJ20 -> 3.1639568 | EM20: =$EL$3/(1+$CI$3)^CJ20 -> 26.086833 | EN20: =$EL$3/(1+$CI$4)^CJ20 -> 21.847563 | EO20: =$EL$3/(1+$CI$5)^CJ20 -> 18.328885 | EP20: =$EL$3/(1+$CI$6)^CJ20 -> 15.753742 | EQ20: =$EL$3/(1+$CI$7)^CJ20 -> 15.403024 | ER20: =$EL$3/(1+$CI$8)^CJ20 -> 12.965782 | ES20: =$EL$3/(1+$CI$9)^CJ20 -> 10.932023 | ET20: =$EL$3/(1+$CI$10)^CJ20 -> 9.8426011 | EU20: =$EL$3/(1+$CI$11)^CJ20 -> 7.8086956 | EV20: =$EL$3/(1+$CI$12)^CJ20 -> 6.6149891 | EW20: =$EL$3/(1+$CI$13)^CJ20 -> 5.6122597 | EX20: =$EL$3/(1+$CI$14)^CJ20 -> 4.7686174 | EY20: =$EL$3/(1+$CI$15)^CJ20 -> 4.0577164 | EZ20: =$EL$3/(1+$CI$16)^CJ20 -> 3.4577541 | FA20: =$EL$3/(1+$CI$17)^CJ20 -> 2.9506573 | FB20: =$EL$3/(1+$CI$18)^CJ20 -> 2.5214187 | FE20: =$FD$3/(1+$CI$3)^CJ20 -> 18.49267 | FF20: =$FD$3/(1+$CI$4)^CJ20 -> 15.487497 | FG20: =$FD$3/(1+$CI$5)^CJ20 -> 12.993145 | FH20: =$FD$3/(1+$CI$6)^CJ20 -> 11.167654 | FI20: =$FD$3/(1+$CI$7)^CJ20 -> 10.919034 | FJ20: =$FD$3/(1+$CI$8)^CJ20 -> 9.1913003 | FK20: =$FD$3/(1+$CI$9)^CJ20 -> 7.7495906 | FL20: =$FD$3/(1+$CI$10)^CJ20 -> 6.9773118 | FM20: =$FD$3/(1+$CI$11)^CJ20 -> 5.5354985 | FN20: =$FD$3/(1+$CI$12)^CJ20 -> 4.6892931 | FO20: =$FD$3/(1+$CI$13)^CJ20 -> 3.9784692 | FP20: =$FD$3/(1+$CI$14)^CJ20 -> 3.3804204 | FQ20: =$FD$3/(1+$CI$15)^CJ20 -> 2.8764705 | FR20: =$FD$3/(1+$CI$16)^CJ20 -> 2.4511639 | FS20: =$FD$3/(1+$CI$17)^CJ20 -> 2.0916885 | FT20: =$FD$3/(1+$CI$18)^CJ20 -> 1.787406 | FW20: =$FV$3/(1+$CI$3)^CJ20 -> 0.034019938 | FX20: =$FV$3/(1+$CI$4)^CJ20 -> 0.028491489 | FY20: =$FV$3/(1+$CI$5)^CJ20 -> 0.023902768 | FZ20: =$FV$3/(1+$CI$6)^CJ20 -> 0.020544514 | GA20: =$FV$3/(1+$CI$7)^CJ20 -> 0.020087141 | GB20: =$FV$3/(1+$CI$8)^CJ20 -> 0.016908725 | GC20: =$FV$3/(1+$CI$9)^CJ20 -> 0.014256492 | GD20: =$FV$3/(1+$CI$10)^CJ20 -> 0.012835773 | GE20: =$FV$3/(1+$CI$11)^CJ20 -> 0.010183349 | GF20: =$FV$3/(1+$CI$12)^CJ20 -> 0.0086266321 | GG20: =$FV$3/(1+$CI$13)^CJ20 -> 0.007318969 | GH20: =$FV$3/(1+$CI$14)^CJ20 -> 0.0062187718 | GI20: =$FV$3/(1+$CI$15)^CJ20 -> 0.0052916831 | GJ20: =$FV$3/(1+$CI$16)^CJ20 -> 0.0045092702 | GK20: =$FV$3/(1+$CI$17)^CJ20 -> 0.0038479632 | GL20: =$FV$3/(1+$CI$18)^CJ20 -> 0.0032881916
A21: Microsoft | B21: 43281 | C21: 31.317 | D21: 785.62587 | E21: 114.509 | F21: 2498.9 | G21: 16.571 | H21: =(D21/AI21) -> 47.409684 | I21: =(D21/G21) -> 47.409684 | J21: -12.52 | K21: -5.5 | L21: 20.467 | M21: -2.4 | N21: =(C21+L21+J21+K21+M21) -> 31.364 | P21: 7967000000 | Q21: =(P21-P20)/P20*100 -> -0.8833043 | S21: 102.69 | T21: =(S21*P21) -> 818131230000 | U21: =(D21-D20)/D20*100 -> 41.794536 | V21: 82.718 | W21: =(V21-V20)/V20*100 -> -5.6925585 | X21: 38.982 | Y21: =(X21-X20)/X20*100 -> -8.2409434 | AA21: 0.1 | AB21: 82.718 | AC21: 87.711 | AD21: =(G20/AA21) -> 212.04 | AE21: =(D21-AC21-AD21) -> 485.87487 | AF21: =((((D21-AD21)/(G21)*AA21)-1)/(1+(D21-AD21)/(G21))) -> 0.069113127 | AG21: =(1+AF21)/(1+AA21) -> 0.97192102 | AI21: 16.571 | AJ21: 16.571 | AL21: 16.571 | AM21: =D21/AL21 -> 47.409684 | AN21: 16.571 | AO21: =D21/AN21 -> 47.409684 | AQ21: =$D$28/AL21 -> 167.21677 | AS21: =$D$28/AN21 -> 167.21677 | AV21: =(D21/AB21) -> 9.497641 | AW21: =(D21/E21) -> 6.860822 | AX21: 43.736 | AY21: =(AB21-AX21) -> 38.982 | AZ21: =(D21/AY21) -> 20.153555 | BB21: 33.764 | BC21: 25.174 | BD21: =(BB21/D21)*100 -> 4.29772 | BE21: =(BC21/D21)*100 -> 3.2043242 | BG21: 102.69 | BH21: 7967000000 | BI21: =(BG21*BH21) -> 818131230000 | BJ21: 82.718 | BK21: =AY21 -> 38.982 | BL21: 169.662 | BM21: 58.488 | BN21: 117.642 | BO21: =(BL21-BM21-BN21) -> -6.468 | BP21: 133.768 | BQ21: =(BP21-BM21-BN21) -> -42.362 | BS21: =D21 -> 785.62587 | BT21: =E21 -> 114.509 | BU21: =N21 -> 31.364 | BV21: =G21 -> 16.571 | BW21: =((BS21/BS16)^(1/5)-1)*100 -> 20.604889 | BX21: =((BT21/BT16)^(1/5)-1)*100 -> 7.8253796 | BY21: =((BU21/BU16)^(1/5)-1)*100 -> 6.2147786 | BZ21: =((BV21/BV16)^(1/5)-1)*100 -> -5.3920151 | CE21: 43281 | CF21: 785.62587 | CG21: 31.364 | CH21: =(CG21/CF21) -> 0.039922311 | CJ21: 19 | CK21: =$CG$27/(1+$CI$3)^CJ21 -> 4.0882074 | CL21: =$CG$27/(1+$CI$4)^CJ21 -> 3.3902815 | CM21: =$CG$27/(1+$CI$5)^CJ21 -> 2.8166427 | CN21: =$CG$27/(1+$CI$6)^CJ21 -> 2.4006372 | CO21: =$CG$27/(1+$CI$7)^CJ21 -> 2.3442589 | CP21: =$CG$27/(1+$CI$8)^CJ21 -> 1.95453 | CQ21: =$CG$27/(1+$CI$9)^CJ21 -> 1.6324038 | CR21: =$CG$27/(1+$CI$10)^CJ21 -> 1.4611814 | CS21: =$CG$27/(1+$CI$11)^CJ21 -> 1.1444259 | CT21: =$CG$27/(1+$CI$12)^CJ21 -> 0.96058448 | CU21: =$CG$27/(1+$CI$13)^CJ21 -> 0.80756597 | CV21: =$CG$27/(1+$CI$14)^CJ21 -> 0.67998985 | CW21: =$CG$27/(1+$CI$15)^CJ21 -> 0.57345137 | CX21: =$CG$27/(1+$CI$16)^CJ21 -> 0.48433806 | CY21: =$CG$27/(1+$CI$17)^CJ21 -> 0.40968197 | CZ21: =$CG$27/(1+$CI$18)^CJ21 -> 0.34704042 | DC21: =$DB$3/(1+$CI$3)^CJ21 -> 29.206803 | DD21: =$DB$3/(1+$CI$4)^CJ21 -> 24.220709 | DE21: =$DB$3/(1+$CI$5)^CJ21 -> 20.122542 | DF21: =$DB$3/(1+$CI$6)^CJ21 -> 17.150533 | DG21: =$DB$3/(1+$CI$7)^CJ21 -> 16.747758 | DH21: =$DB$3/(1+$CI$8)^CJ21 -> 13.963473 | DI21: =$DB$3/(1+$CI$9)^CJ21 -> 11.662152 | DJ21: =$DB$3/(1+$CI$10)^CJ21 -> 10.438912 | DK21: =$DB$3/(1+$CI$11)^CJ21 -> 8.1759602 | DL21: =$DB$3/(1+$CI$12)^CJ21 -> 6.862568 | DM21: =$DB$3/(1+$CI$13)^CJ21 -> 5.7693795 | DN21: =$DB$3/(1+$CI$14)^CJ21 -> 4.8579554 | DO21: =$DB$3/(1+$CI$15)^CJ21 -> 4.0968276 | DP21: =$DB$3/(1+$CI$16)^CJ21 -> 3.460188 | DQ21: =$DB$3/(1+$CI$17)^CJ21 -> 2.926833 | DR21: =$DB$3/(1+$CI$18)^CJ21 -> 2.4793118 | DU21: =$DT$3/(1+$CI$3)^CJ21 -> 32.410487 | DV21: =$DT$3/(1+$CI$4)^CJ21 -> 26.877471 | DW21: =$DT$3/(1+$CI$5)^CJ21 -> 22.329777 | DX21: =$DT$3/(1+$CI$6)^CJ21 -> 19.031769 | DY21: =$DT$3/(1+$CI$7)^CJ21 -> 18.584814 | DZ21: =$DT$3/(1+$CI$8)^CJ21 -> 15.495121 | EA21: =$DT$3/(1+$CI$9)^CJ21 -> 12.941369 | EB21: =$DT$3/(1+$CI$10)^CJ21 -> 11.583953 | EC21: =$DT$3/(1+$CI$11)^CJ21 -> 9.0727786 | ED21: =$DT$3/(1+$CI$12)^CJ21 -> 7.6153208 | EE21: =$DT$3/(1+$CI$13)^CJ21 -> 6.4022208 | EF21: =$DT$3/(1+$CI$14)^CJ21 -> 5.3908229 | EG21: =$DT$3/(1+$CI$15)^CJ21 -> 4.5462073 | EH21: =$DT$3/(1+$CI$16)^CJ21 -> 3.8397349 | EI21: =$DT$3/(1+$CI$17)^CJ21 -> 3.2478764 | EJ21: =$DT$3/(1+$CI$18)^CJ21 -> 2.7512667 | EM21: =$EL$3/(1+$CI$3)^CJ21 -> 25.828548 | EN21: =$EL$3/(1+$CI$4)^CJ21 -> 21.419179 | EO21: =$EL$3/(1+$CI$5)^CJ21 -> 17.795034 | EP21: =$EL$3/(1+$CI$6)^CJ21 -> 15.166787 | EQ21: =$EL$3/(1+$CI$7)^CJ21 -> 14.8106 | ER21: =$EL$3/(1+$CI$8)^CJ21 -> 12.348364 | ES21: =$EL$3/(1+$CI$9)^CJ21 -> 10.313229 | ET21: =$EL$3/(1+$CI$10)^CJ21 -> 9.2314773 | EU21: =$EL$3/(1+$CI$11)^CJ21 -> 7.2302737 | EV21: =$EL$3/(1+$CI$12)^CJ21 -> 6.0687973 | EW21: =$EL$3/(1+$CI$13)^CJ21 -> 5.1020543 | EX21: =$EL$3/(1+$CI$14)^CJ21 -> 4.2960517 | EY21: =$EL$3/(1+$CI$15)^CJ21 -> 3.622961 | EZ21: =$EL$3/(1+$CI$16)^CJ21 -> 3.0599594 | FA21: =$EL$3/(1+$CI$17)^CJ21 -> 2.5882959 | FB21: =$EL$3/(1+$CI$18)^CJ21 -> 2.192538 | FE21: =$FD$3/(1+$CI$3)^CJ21 -> 18.309574 | FF21: =$FD$3/(1+$CI$4)^CJ21 -> 15.183821 | FG21: =$FD$3/(1+$CI$5)^CJ21 -> 12.614704 | FH21: =$FD$3/(1+$CI$6)^CJ21 -> 10.751569 | FI21: =$FD$3/(1+$CI$7)^CJ21 -> 10.499071 | FJ21: =$FD$3/(1+$CI$8)^CJ21 -> 8.7536193 | FK21: =$FD$3/(1+$CI$9)^CJ21 -> 7.3109346 | FL21: =$FD$3/(1+$CI$10)^CJ21 -> 6.5440928 | FM21: =$FD$3/(1+$CI$11)^CJ21 -> 5.1254616 | FN21: =$FD$3/(1+$CI$12)^CJ21 -> 4.3021037 | FO21: =$FD$3/(1+$CI$13)^CJ21 -> 3.6167902 | FP21: =$FD$3/(1+$CI$14)^CJ21 -> 3.0454238 | FQ21: =$FD$3/(1+$CI$15)^CJ21 -> 2.5682773 | FR21: =$FD$3/(1+$CI$16)^CJ21 -> 2.1691716 | FS21: =$FD$3/(1+$CI$17)^CJ21 -> 1.8348145 | FT21: =$FD$3/(1+$CI$18)^CJ21 -> 1.5542661 | FW21: =$FV$3/(1+$CI$3)^CJ21 -> 0.033683106 | FX21: =$FV$3/(1+$CI$4)^CJ21 -> 0.027932832 | FY21: =$FV$3/(1+$CI$5)^CJ21 -> 0.023206571 | FZ21: =$FV$3/(1+$CI$6)^CJ21 -> 0.019779064 | GA21: =$FV$3/(1+$CI$7)^CJ21 -> 0.019314559 | GB21: =$FV$3/(1+$CI$8)^CJ21 -> 0.016103547 | GC21: =$FV$3/(1+$CI$9)^CJ21 -> 0.01344952 | GD21: =$FV$3/(1+$CI$10)^CJ21 -> 0.012038804 | GE21: =$FV$3/(1+$CI$11)^CJ21 -> 0.0094290271 | GF21: =$FV$3/(1+$CI$12)^CJ21 -> 0.0079143414 | GG21: =$FV$3/(1+$CI$13)^CJ21 -> 0.0066536082 | GH21: =$FV$3/(1+$CI$14)^CJ21 -> 0.0056024971 | GI21: =$FV$3/(1+$CI$15)^CJ21 -> 0.0047247171 | GJ21: =$FV$3/(1+$CI$16)^CJ21 -> 0.0039905046 | GK21: =$FV$3/(1+$CI$17)^CJ21 -> 0.0033754064 | GL21: =$FV$3/(1+$CI$18)^CJ21 -> 0.002859297
A22: Microsoft | B22: 43646 | C22: 59.119 | D22: 1057.6142 | E22: 129.255 | F22: 3230.78 | G22: 39.237 | H22: =(D22/AI22) -> 26.954512 | I22: =(D22/G22) -> 26.954512 | J22: -16.313 | K22: -8.4 | L22: 3.866 | M22: -2.4 | N22: =(C22+L22+J22+K22+M22) -> 35.872 | P22: 7895000000 | Q22: =(P22-P21)/P21*100 -> -0.90372788 | S22: 133.96 | T22: =(S22*P22) -> 1.0576142e+12 | U22: =(D22-D21)/D21*100 -> 34.620592 | V22: 102.33 | W22: =(V22-V21)/V21*100 -> 23.709471 | X22: 52.554 | Y22: =(X22-X21)/X21*100 -> 34.816069 | AA22: 0.1 | AB22: 102.33 | AC22: 82.718 | AD22: =(G21/AA22) -> 165.71 | AE22: =(D22-AC22-AD22) -> 809.1862 | AF22: =((((D22-AD22)/(G22)*AA22)-1)/(1+(D22-AD22)/(G22))) -> 0.053647524 | AG22: =(1+AF22)/(1+AA22) -> 0.95786139 | AI22: 39.237 | AJ22: 39.237 | AL22: 39.237 | AM22: =D22/AL22 -> 26.954512 | AN22: 39.237 | AO22: =D22/AN22 -> 26.954512 | AQ22: =$D$28/AL22 -> 70.620821 | AS22: =$D$28/AN22 -> 70.620821 | AV22: =(D22/AB22) -> 10.335329 | AW22: =(D22/E22) -> 8.1823852 | AX22: 49.776 | AY22: =(AB22-AX22) -> 52.554 | AZ22: =(D22/AY22) -> 20.124333 | BB22: 38.272 | BC22: 22.486 | BD22: =(BB22/D22)*100 -> 3.6187109 | BE22: =(BC22/D22)*100 -> 2.1261061 | BG22: 133.96 | BH22: 7895000000 | BI22: =(BG22*BH22) -> 1.0576142e+12 | BJ22: 102.33 | BK22: =AY22 -> 52.554 | BL22: 175.552 | BM22: 69.42 | BN22: 114.806 | BO22: =(BL22-BM22-BN22) -> -8.674 | BP22: 133.819 | BQ22: =(BP22-BM22-BN22) -> -50.407 | BS22: =D22 -> 1057.6142 | BT22: =E22 -> 129.255 | BU22: =N22 -> 35.872 | BV22: =G22 -> 39.237 | BW22: =((BS22/BS17)^(1/5)-1)*100 -> 23.363416 | BX22: =((BT22/BT17)^(1/5)-1)*100 -> 8.117699 | BY22: =((BU22/BU17)^(1/5)-1)*100 -> 11.218491 | BZ22: =((BV22/BV17)^(1/5)-1)*100 -> 12.192274 | CE22: 43646 | CF22: 1057.6142 | CG22: 35.872 | CH22: =(CG22/CF22) -> 0.03391785 | CJ22: 20 | CK22: =$CG$27/(1+$CI$3)^CJ22 -> 4.0477301 | CL22: =$CG$27/(1+$CI$4)^CJ22 -> 3.3238054 | CM22: =$CG$27/(1+$CI$5)^CJ22 -> 2.7346045 | CN22: =$CG$27/(1+$CI$6)^CJ22 -> 2.311194 | CO22: =$CG$27/(1+$CI$7)^CJ22 -> 2.2540951 | CP22: =$CG$27/(1+$CI$8)^CJ22 -> 1.8614572 | CQ22: =$CG$27/(1+$CI$9)^CJ22 -> 1.5400035 | CR22: =$CG$27/(1+$CI$10)^CJ22 -> 1.3704572 | CS22: =$CG$27/(1+$CI$11)^CJ22 -> 1.0596536 | CT22: =$CG$27/(1+$CI$12)^CJ22 -> 0.88127016 | CU22: =$CG$27/(1+$CI$13)^CJ22 -> 0.73415088 | CV22: =$CG$27/(1+$CI$14)^CJ22 -> 0.61260347 | CW22: =$CG$27/(1+$CI$15)^CJ22 -> 0.51201015 | CX22: =$CG$27/(1+$CI$16)^CJ22 -> 0.42861775 | CY22: =$CG$27/(1+$CI$17)^CJ22 -> 0.35937015 | CZ22: =$CG$27/(1+$CI$18)^CJ22 -> 0.30177428 | DC22: =$DB$3/(1+$CI$3)^CJ22 -> 28.917627 | DD22: =$DB$3/(1+$CI$4)^CJ22 -> 23.745793 | DE22: =$DB$3/(1+$CI$5)^CJ22 -> 19.536449 | DF22: =$DB$3/(1+$CI$6)^CJ22 -> 16.511537 | DG22: =$DB$3/(1+$CI$7)^CJ22 -> 16.103613 | DH22: =$DB$3/(1+$CI$8)^CJ22 -> 13.298545 | DI22: =$DB$3/(1+$CI$9)^CJ22 -> 11.00203 | DJ22: =$DB$3/(1+$CI$10)^CJ22 -> 9.7907635 | DK22: =$DB$3/(1+$CI$11)^CJ22 -> 7.5703335 | DL22: =$DB$3/(1+$CI$12)^CJ22 -> 6.2959339 | DM22: =$DB$3/(1+$CI$13)^CJ22 -> 5.2448904 | DN22: =$DB$3/(1+$CI$14)^CJ22 -> 4.3765364 | DO22: =$DB$3/(1+$CI$15)^CJ22 -> 3.6578818 | DP22: =$DB$3/(1+$CI$16)^CJ22 -> 3.0621133 | DQ22: =$DB$3/(1+$CI$17)^CJ22 -> 2.5673974 | DR22: =$DB$3/(1+$CI$18)^CJ22 -> 2.1559233 | DU22: =$DT$3/(1+$CI$3)^CJ22 -> 32.089592 | DV22: =$DT$3/(1+$CI$4)^CJ22 -> 26.350462 | DW22: =$DT$3/(1+$CI$5)^CJ22 -> 21.679396 | DX22: =$DT$3/(1+$CI$6)^CJ22 -> 18.322682 | DY22: =$DT$3/(1+$CI$7)^CJ22 -> 17.870013 | DZ22: =$DT$3/(1+$CI$8)^CJ22 -> 14.757258 | EA22: =$DT$3/(1+$CI$9)^CJ22 -> 12.208839 | EB22: =$DT$3/(1+$CI$10)^CJ22 -> 10.864709 | EC22: =$DT$3/(1+$CI$11)^CJ22 -> 8.4007209 | ED22: =$DT$3/(1+$CI$12)^CJ22 -> 6.9865329 | EE22: =$DT$3/(1+$CI$13)^CJ22 -> 5.8202007 | EF22: =$DT$3/(1+$CI$14)^CJ22 -> 4.8565972 | EG22: =$DT$3/(1+$CI$15)^CJ22 -> 4.0591137 | EH22: =$DT$3/(1+$CI$16)^CJ22 -> 3.3979955 | EI22: =$DT$3/(1+$CI$17)^CJ22 -> 2.8490144 | EJ22: =$DT$3/(1+$CI$18)^CJ22 -> 2.3924059 | EM22: =$EL$3/(1+$CI$3)^CJ22 -> 25.57282 | EN22: =$EL$3/(1+$CI$4)^CJ22 -> 20.999196 | EO22: =$EL$3/(1+$CI$5)^CJ22 -> 17.276732 | EP22: =$EL$3/(1+$CI$6)^CJ22 -> 14.601701 | EQ22: =$EL$3/(1+$CI$7)^CJ22 -> 14.240961 | ER22: =$EL$3/(1+$CI$8)^CJ22 -> 11.760346 | ES22: =$EL$3/(1+$CI$9)^CJ22 -> 9.7294612 | ET22: =$EL$3/(1+$CI$10)^CJ22 -> 8.658298 | EU22: =$EL$3/(1+$CI$11)^CJ22 -> 6.6946979 | EV22: =$EL$3/(1+$CI$12)^CJ22 -> 5.567704 | EW22: =$EL$3/(1+$CI$13)^CJ22 -> 4.6382312 | EX22: =$EL$3/(1+$CI$14)^CJ22 -> 3.8703168 | EY22: =$EL$3/(1+$CI$15)^CJ22 -> 3.2347866 | EZ22: =$EL$3/(1+$CI$16)^CJ22 -> 2.7079287 | FA22: =$EL$3/(1+$CI$17)^CJ22 -> 2.270435 | FB22: =$EL$3/(1+$CI$18)^CJ22 -> 1.9065548 | FE22: =$FD$3/(1+$CI$3)^CJ22 -> 18.128291 | FF22: =$FD$3/(1+$CI$4)^CJ22 -> 14.886099 | FG22: =$FD$3/(1+$CI$5)^CJ22 -> 12.247286 | FH22: =$FD$3/(1+$CI$6)^CJ22 -> 10.350986 | FI22: =$FD$3/(1+$CI$7)^CJ22 -> 10.095261 | FJ22: =$FD$3/(1+$CI$8)^CJ22 -> 8.3367803 | FK22: =$FD$3/(1+$CI$9)^CJ22 -> 6.8971081 | FL22: =$FD$3/(1+$CI$10)^CJ22 -> 6.1377723 | FM22: =$FD$3/(1+$CI$11)^CJ22 -> 4.7457978 | FN22: =$FD$3/(1+$CI$12)^CJ22 -> 3.9468841 | FO22: =$FD$3/(1+$CI$13)^CJ22 -> 3.2879911 | FP22: =$FD$3/(1+$CI$14)^CJ22 -> 2.7436251 | FQ22: =$FD$3/(1+$CI$15)^CJ22 -> 2.2931047 | FR22: =$FD$3/(1+$CI$16)^CJ22 -> 1.9196209 | FS22: =$FD$3/(1+$CI$17)^CJ22 -> 1.6094864 | FT22: =$FD$3/(1+$CI$18)^CJ22 -> 1.3515357 | FW22: =$FV$3/(1+$CI$3)^CJ22 -> 0.03334961 | FX22: =$FV$3/(1+$CI$4)^CJ22 -> 0.02738513 | FY22: =$FV$3/(1+$CI$5)^CJ22 -> 0.022530651 | FZ22: =$FV$3/(1+$CI$6)^CJ22 -> 0.019042134 | GA22: =$FV$3/(1+$CI$7)^CJ22 -> 0.018571691 | GB22: =$FV$3/(1+$CI$8)^CJ22 -> 0.015336712 | GC22: =$FV$3/(1+$CI$9)^CJ22 -> 0.012688227 | GD22: =$FV$3/(1+$CI$10)^CJ22 -> 0.011291319 | GE22: =$FV$3/(1+$CI$11)^CJ22 -> 0.0087305807 | GF22: =$FV$3/(1+$CI$12)^CJ22 -> 0.0072608636 | GG22: =$FV$3/(1+$CI$13)^CJ22 -> 0.0060487347 | GH22: =$FV$3/(1+$CI$14)^CJ22 -> 0.0050472947 | GI22: =$FV$3/(1+$CI$15)^CJ22 -> 0.0042184974 | GJ22: =$FV$3/(1+$CI$16)^CJ22 -> 0.00353142 | GK22: =$FV$3/(1+$CI$17)^CJ22 -> 0.0029608828 | GL22: =$FV$3/(1+$CI$18)^CJ22 -> 0.0024863452
A23: Microsoft | B23: 44012 | C23: 77.058 | D23: 1585.9534 | E23: 145.683 | F23: 3727.04 | G23: 44.281 | H23: =(D23/AI23) -> 35.815664 | I23: =(D23/G23) -> 35.815664 | J23: -17.962 | K23: -12.5 | L23: -1.483 | M23: -2.4 | N23: =(C23+L23+J23+K23+M23) -> 42.713 | P23: 7793000000 | Q23: =(P23-P22)/P22*100 -> -1.2919569 | S23: 198.44 | T23: =(S23*P23) -> 1546442920000 | U23: =(D23-D22)/D22*100 -> 49.955762 | V23: 118.304 | W23: =(V23-V22)/V22*100 -> 15.61028 | X23: 67.915 | Y23: =(X23-X22)/X22*100 -> 29.228984 | AA23: 0.1 | AB23: 118.304 | AC23: 102.33 | AD23: =(G22/AA23) -> 392.37 | AE23: =(D23-AC23-AD23) -> 1091.2534 | AF23: =((((D23-AD23)/(G23)*AA23)-1)/(1+(D23-AD23)/(G23))) -> 0.060650699 | AG23: =(1+AF23)/(1+AA23) -> 0.96422791 | AI23: 44.281 | AJ23: 44.281 | AL23: 44.281 | AM23: =D23/AL23 -> 35.815664 | AN23: 44.281 | AO23: =D23/AN23 -> 35.815664 | AQ23: =$D$28/AL23 -> 62.576481 | AR23: =AVERAGE(AQ23:AQ27) -> 43.125754 | AS23: =$D$28/AN23 -> 62.576481 | AT23: =AVERAGE(AS23:AS27) -> 43.125754 | AV23: =(D23/AB23) -> 13.405746 | AW23: =(D23/E23) -> 10.886331 | AX23: 50.389 | AY23: =(AB23-AX23) -> 67.915 | AZ23: =(D23/AY23) -> 23.352035 | BB23: 45.113 | BC23: 33.114 | BD23: =(BB23/D23)*100 -> 2.844535 | BE23: =(BC23/D23)*100 -> 2.0879554 | BG23: 198.44 | BH23: 7793000000 | BI23: =(BG23*BH23) -> 1546442920000 | BJ23: 118.304 | BK23: =AY23 -> 67.915 | BL23: 181.915 | BM23: 72.31 | BN23: 110.697 | BO23: =(BL23-BM23-BN23) -> -1.092 | BP23: 136.527 | BQ23: =(BP23-BM23-BN23) -> -46.48 | BS23: =D23 -> 1585.9534 | BT23: =E23 -> 145.683 | BU23: =N23 -> 42.713 | BV23: =G23 -> 44.281 | CE23: 44012 | CF23: 1585.9534 | CG23: 42.713 | CH23: =(CG23/CF23) -> 0.026932064 | CJ23: 21 | CK23: =$CG$27/(1+$CI$3)^CJ23 -> 4.0076536 | CL23: =$CG$27/(1+$CI$4)^CJ23 -> 3.2586328 | CM23: =$CG$27/(1+$CI$5)^CJ23 -> 2.6549559 | CN23: =$CG$27/(1+$CI$6)^CJ23 -> 2.2250832 | CO23: =$CG$27/(1+$CI$7)^CJ23 -> 2.1673992 | CP23: =$CG$27/(1+$CI$8)^CJ23 -> 1.7728163 | CQ23: =$CG$27/(1+$CI$9)^CJ23 -> 1.4528335 | CR23: =$CG$27/(1+$CI$10)^CJ23 -> 1.2853659 | CS23: =$CG$27/(1+$CI$11)^CJ23 -> 0.98116074 | CT23: =$CG$27/(1+$CI$12)^CJ23 -> 0.80850474 | CU23: =$CG$27/(1+$CI$13)^CJ23 -> 0.66740989 | CV23: =$CG$27/(1+$CI$14)^CJ23 -> 0.55189502 | CW23: =$CG$27/(1+$CI$15)^CJ23 -> 0.45715192 | CX23: =$CG$27/(1+$CI$16)^CJ23 -> 0.37930775 | CY23: =$CG$27/(1+$CI$17)^CJ23 -> 0.31523697 | CZ23: =$CG$27/(1+$CI$18)^CJ23 -> 0.26241242 | DC23: =$DB$3/(1+$CI$3)^CJ23 -> 28.631314 | DD23: =$DB$3/(1+$CI$4)^CJ23 -> 23.28019 | DE23: =$DB$3/(1+$CI$5)^CJ23 -> 18.967426 | DF23: =$DB$3/(1+$CI$6)^CJ23 -> 15.896348 | DG23: =$DB$3/(1+$CI$7)^CJ23 -> 15.484244 | DH23: =$DB$3/(1+$CI$8)^CJ23 -> 12.665281 | DI23: =$DB$3/(1+$CI$9)^CJ23 -> 10.379273 | DJ23: =$DB$3/(1+$CI$10)^CJ23 -> 9.1828582 | DK23: =$DB$3/(1+$CI$11)^CJ23 -> 7.0095681 | DL23: =$DB$3/(1+$CI$12)^CJ23 -> 5.7760862 | DM23: =$DB$3/(1+$CI$13)^CJ23 -> 4.7680822 | DN23: =$DB$3/(1+$CI$14)^CJ23 -> 3.9428256 | DO23: =$DB$3/(1+$CI$15)^CJ23 -> 3.2659659 | DP23: =$DB$3/(1+$CI$16)^CJ23 -> 2.7098348 | DQ23: =$DB$3/(1+$CI$17)^CJ23 -> 2.252103 | DR23: =$DB$3/(1+$CI$18)^CJ23 -> 1.8747159 | DU23: =$DT$3/(1+$CI$3)^CJ23 -> 31.771873 | DV23: =$DT$3/(1+$CI$4)^CJ23 -> 25.833786 | DW23: =$DT$3/(1+$CI$5)^CJ23 -> 21.047957 | DX23: =$DT$3/(1+$CI$6)^CJ23 -> 17.640013 | DY23: =$DT$3/(1+$CI$7)^CJ23 -> 17.182705 | DZ23: =$DT$3/(1+$CI$8)^CJ23 -> 14.054532 | EA23: =$DT$3/(1+$CI$9)^CJ23 -> 11.517772 | EB23: =$DT$3/(1+$CI$10)^CJ23 -> 10.190123 | EC23: =$DT$3/(1+$CI$11)^CJ23 -> 7.7784453 | ED23: =$DT$3/(1+$CI$12)^CJ23 -> 6.4096632 | EE23: =$DT$3/(1+$CI$13)^CJ23 -> 5.2910916 | EF23: =$DT$3/(1+$CI$14)^CJ23 -> 4.3753128 | EG23: =$DT$3/(1+$CI$15)^CJ23 -> 3.6242086 | EH23: =$DT$3/(1+$CI$16)^CJ23 -> 3.0070756 | EI23: =$DT$3/(1+$CI$17)^CJ23 -> 2.4991354 | EJ23: =$DT$3/(1+$CI$18)^CJ23 -> 2.0803529 | EM23: =$EL$3/(1+$CI$3)^CJ23 -> 25.319624 | EN23: =$EL$3/(1+$CI$4)^CJ23 -> 20.587447 | EO23: =$EL$3/(1+$CI$5)^CJ23 -> 16.773526 | EP23: =$EL$3/(1+$CI$6)^CJ23 -> 14.05767 | EQ23: =$EL$3/(1+$CI$7)^CJ23 -> 13.693232 | ER23: =$EL$3/(1+$CI$8)^CJ23 -> 11.20033 | ES23: =$EL$3/(1+$CI$9)^CJ23 -> 9.1787369 | ET23: =$EL$3/(1+$CI$10)^CJ23 -> 8.1207072 | EU23: =$EL$3/(1+$CI$11)^CJ23 -> 6.1987944 | EV23: =$EL$3/(1+$CI$12)^CJ23 -> 5.1079853 | EW23: =$EL$3/(1+$CI$13)^CJ23 -> 4.2165738 | EX23: =$EL$3/(1+$CI$14)^CJ23 -> 3.4867719 | EY23: =$EL$3/(1+$CI$15)^CJ23 -> 2.8882024 | EZ23: =$EL$3/(1+$CI$16)^CJ23 -> 2.3963971 | FA23: =$EL$3/(1+$CI$17)^CJ23 -> 1.9916096 | FB23: =$EL$3/(1+$CI$18)^CJ23 -> 1.6578737 | FE23: =$FD$3/(1+$CI$3)^CJ23 -> 17.948803 | FF23: =$FD$3/(1+$CI$4)^CJ23 -> 14.594215 | FG23: =$FD$3/(1+$CI$5)^CJ23 -> 11.890568 | FH23: =$FD$3/(1+$CI$6)^CJ23 -> 9.9653274 | FI23: =$FD$3/(1+$CI$7)^CJ23 -> 9.7069817 | FJ23: =$FD$3/(1+$CI$8)^CJ23 -> 7.9397907 | FK23: =$FD$3/(1+$CI$9)^CJ23 -> 6.5067057 | FL23: =$FD$3/(1+$CI$10)^CJ23 -> 5.7566801 | FM23: =$FD$3/(1+$CI$11)^CJ23 -> 4.3942572 | FN23: =$FD$3/(1+$CI$12)^CJ23 -> 3.6209946 | FO23: =$FD$3/(1+$CI$13)^CJ23 -> 2.9890828 | FP23: =$FD$3/(1+$CI$14)^CJ23 -> 2.4717343 | FQ23: =$FD$3/(1+$CI$15)^CJ23 -> 2.0474149 | FR23: =$FD$3/(1+$CI$16)^CJ23 -> 1.6987795 | FS23: =$FD$3/(1+$CI$17)^CJ23 -> 1.4118302 | FT23: =$FD$3/(1+$CI$18)^CJ23 -> 1.1752485 | FW23: =$FV$3/(1+$CI$3)^CJ23 -> 0.033019416 | FX23: =$FV$3/(1+$CI$4)^CJ23 -> 0.026848167 | FY23: =$FV$3/(1+$CI$5)^CJ23 -> 0.021874419 | FZ23: =$FV$3/(1+$CI$6)^CJ23 -> 0.01833266 | GA23: =$FV$3/(1+$CI$7)^CJ23 -> 0.017857395 | GB23: =$FV$3/(1+$CI$8)^CJ23 -> 0.014606392 | GC23: =$FV$3/(1+$CI$9)^CJ23 -> 0.011970025 | GD23: =$FV$3/(1+$CI$10)^CJ23 -> 0.010590245 | GE23: =$FV$3/(1+$CI$11)^CJ23 -> 0.008083871 | GF23: =$FV$3/(1+$CI$12)^CJ23 -> 0.0066613428 | GG23: =$FV$3/(1+$CI$13)^CJ23 -> 0.0054988497 | GH23: =$FV$3/(1+$CI$14)^CJ23 -> 0.0045471124 | GI23: =$FV$3/(1+$CI$15)^CJ23 -> 0.0037665155 | GJ23: =$FV$3/(1+$CI$16)^CJ23 -> 0.0031251504 | GK23: =$FV$3/(1+$CI$17)^CJ23 -> 0.0025972656 | GL23: =$FV$3/(1+$CI$18)^CJ23 -> 0.0021620393
A24: Microsoft | B24: 44377 | C24: 93.076 | D24: 2087.8263 | E24: 171.62 | F24: 4766.18 | G24: 61.271 | H24: =(D24/AI24) -> 34.075277 | I24: =(D24/G24) -> 34.075277 | J24: -29.531 | K24: -13.4 | L24: -0.936 | M24: -2 | N24: =(C24+L24+J24+K24+M24) -> 47.209 | P24: 7510000000 | Q24: =(P24-P23)/P23*100 -> -3.6314641 | S24: 310.2 | T24: =(S24*P24) -> 2329602000000 | U24: =(D24-D23)/D23*100 -> 31.644868 | V24: 141.988 | W24: =(V24-V23)/V23*100 -> 20.01961 | X24: 84.477 | Y24: =(X24-X23)/X23*100 -> 24.386365 | AA24: 0.1 | AB24: 141.988 | AC24: 118.304 | AD24: =(G23/AA24) -> 442.81 | AE24: =(D24-AC24-AD24) -> 1526.7123 | AF24: =((((D24-AD24)/(G24)*AA24)-1)/(1+(D24-AD24)/(G24))) -> 0.060500146 | AG24: =(1+AF24)/(1+AA24) -> 0.96409104 | AI24: 61.271 | AJ24: 61.271 | AL24: 61.271 | AM24: =D24/AL24 -> 34.075277 | AN24: 61.271 | AO24: =D24/AN24 -> 34.075277 | AQ24: =$D$28/AL24 -> 45.224481 | AS24: =$D$28/AN24 -> 45.224481 | AV24: =(D24/AB24) -> 14.704245 | AW24: =(D24/E24) -> 12.165402 | AX24: 57.511 | AY24: =(AB24-AX24) -> 84.477 | AZ24: =(D24/AY24) -> 24.714731 | BB24: 49.209 | BC24: 32.613 | BD24: =(BB24/D24)*100 -> 2.3569489 | BE24: =(BC24/D24)*100 -> 1.5620552 | BG24: 310.2 | BH24: 7510000000 | BI24: =(BG24*BH24) -> 2329602000000 | BJ24: 141.988 | BK24: =AY24 -> 84.477 | BL24: 184.406 | BM24: 88.657 | BN24: 103.134 | BO24: =(BL24-BM24-BN24) -> -7.385 | BP24: 130.334 | BQ24: =(BP24-BM24-BN24) -> -61.457 | BS24: =D24 -> 2087.8263 | BT24: =E24 -> 171.62 | BU24: =N24 -> 47.209 | BV24: =G24 -> 61.271 | CE24: 44377 | CF24: 2087.8263 | CG24: 47.209 | CH24: =(CG24/CF24) -> 0.022611555 | CJ24: 22 | CK24: =$CG$27/(1+$CI$3)^CJ24 -> 3.9679739 | CL24: =$CG$27/(1+$CI$4)^CJ24 -> 3.194738 | CM24: =$CG$27/(1+$CI$5)^CJ24 -> 2.5776271 | CN24: =$CG$27/(1+$CI$6)^CJ24 -> 2.1421808 | CO24: =$CG$27/(1+$CI$7)^CJ24 -> 2.0840377 | CP24: =$CG$27/(1+$CI$8)^CJ24 -> 1.6883965 | CQ24: =$CG$27/(1+$CI$9)^CJ24 -> 1.3705977 | CR24: =$CG$27/(1+$CI$10)^CJ24 -> 1.205558 | CS24: =$CG$27/(1+$CI$11)^CJ24 -> 0.90848216 | CT24: =$CG$27/(1+$CI$12)^CJ24 -> 0.74174747 | CU24: =$CG$27/(1+$CI$13)^CJ24 -> 0.60673626 | CV24: =$CG$27/(1+$CI$14)^CJ24 -> 0.49720272 | CW24: =$CG$27/(1+$CI$15)^CJ24 -> 0.40817136 | CX24: =$CG$27/(1+$CI$16)^CJ24 -> 0.33567057 | CY24: =$CG$27/(1+$CI$17)^CJ24 -> 0.27652366 | CZ24: =$CG$27/(1+$CI$18)^CJ24 -> 0.22818471 | DC24: =$DB$3/(1+$CI$3)^CJ24 -> 28.347835 | DD24: =$DB$3/(1+$CI$4)^CJ24 -> 22.823715 | DE24: =$DB$3/(1+$CI$5)^CJ24 -> 18.414977 | DF24: =$DB$3/(1+$CI$6)^CJ24 -> 15.30408 | DG24: =$DB$3/(1+$CI$7)^CJ24 -> 14.888696 | DH24: =$DB$3/(1+$CI$8)^CJ24 -> 12.062173 | DI24: =$DB$3/(1+$CI$9)^CJ24 -> 9.7917673 | DJ24: =$DB$3/(1+$CI$10)^CJ24 -> 8.6126977 | DK24: =$DB$3/(1+$CI$11)^CJ24 -> 6.4903408 | DL24: =$DB$3/(1+$CI$12)^CJ24 -> 5.2991616 | DM24: =$DB$3/(1+$CI$13)^CJ24 -> 4.3346202 | DN24: =$DB$3/(1+$CI$14)^CJ24 -> 3.5520951 | DO24: =$DB$3/(1+$CI$15)^CJ24 -> 2.916041 | DP24: =$DB$3/(1+$CI$16)^CJ24 -> 2.3980839 | DQ24: =$DB$3/(1+$CI$17)^CJ24 -> 1.9755289 | DR24: =$DB$3/(1+$CI$18)^CJ24 -> 1.6301878 | DU24: =$DT$3/(1+$CI$3)^CJ24 -> 31.4573 | DV24: =$DT$3/(1+$CI$4)^CJ24 -> 25.327241 | DW24: =$DT$3/(1+$CI$5)^CJ24 -> 20.43491 | DX24: =$DT$3/(1+$CI$6)^CJ24 -> 16.982779 | DY24: =$DT$3/(1+$CI$7)^CJ24 -> 16.521832 | DZ24: =$DT$3/(1+$CI$8)^CJ24 -> 13.385268 | EA24: =$DT$3/(1+$CI$9)^CJ24 -> 10.865823 | EB24: =$DT$3/(1+$CI$10)^CJ24 -> 9.5574216 | EC24: =$DT$3/(1+$CI$11)^CJ24 -> 7.2022641 | ED24: =$DT$3/(1+$CI$12)^CJ24 -> 5.8804249 | EE24: =$DT$3/(1+$CI$13)^CJ24 -> 4.8100832 | EF24: =$DT$3/(1+$CI$14)^CJ24 -> 3.9417233 | EG24: =$DT$3/(1+$CI$15)^CJ24 -> 3.2359006 | EH24: =$DT$3/(1+$CI$16)^CJ24 -> 2.6611289 | EI24: =$DT$3/(1+$CI$17)^CJ24 -> 2.192224 | EJ24: =$DT$3/(1+$CI$18)^CJ24 -> 1.8090025 | EM24: =$EL$3/(1+$CI$3)^CJ24 -> 25.068934 | EN24: =$EL$3/(1+$CI$4)^CJ24 -> 20.183771 | EO24: =$EL$3/(1+$CI$5)^CJ24 -> 16.284977 | EP24: =$EL$3/(1+$CI$6)^CJ24 -> 13.533907 | EQ24: =$EL$3/(1+$CI$7)^CJ24 -> 13.166569 | ER24: =$EL$3/(1+$CI$8)^CJ24 -> 10.666981 | ES24: =$EL$3/(1+$CI$9)^CJ24 -> 8.6591858 | ET24: =$EL$3/(1+$CI$10)^CJ24 -> 7.6164952 | EU24: =$EL$3/(1+$CI$11)^CJ24 -> 5.7396244 | EV24: =$EL$3/(1+$CI$12)^CJ24 -> 4.686225 | EW24: =$EL$3/(1+$CI$13)^CJ24 -> 3.8332489 | EX24: =$EL$3/(1+$CI$14)^CJ24 -> 3.141236 | EY24: =$EL$3/(1+$CI$15)^CJ24 -> 2.5787521 | EZ24: =$EL$3/(1+$CI$16)^CJ24 -> 2.1207054 | FA24: =$EL$3/(1+$CI$17)^CJ24 -> 1.747026 | FB24: =$EL$3/(1+$CI$18)^CJ24 -> 1.4416293 | FE24: =$FD$3/(1+$CI$3)^CJ24 -> 17.771092 | FF24: =$FD$3/(1+$CI$4)^CJ24 -> 14.308054 | FG24: =$FD$3/(1+$CI$5)^CJ24 -> 11.544241 | FH24: =$FD$3/(1+$CI$6)^CJ24 -> 9.5940382 | FI24: =$FD$3/(1+$CI$7)^CJ24 -> 9.3336363 | FJ24: =$FD$3/(1+$CI$8)^CJ24 -> 7.5617055 | FK24: =$FD$3/(1+$CI$9)^CJ24 -> 6.1384016 | FL24: =$FD$3/(1+$CI$10)^CJ24 -> 5.3992498 | FM24: =$FD$3/(1+$CI$11)^CJ24 -> 4.0687567 | FN24: =$FD$3/(1+$CI$12)^CJ24 -> 3.3220134 | FO24: =$FD$3/(1+$CI$13)^CJ24 -> 2.717348 | FP24: =$FD$3/(1+$CI$14)^CJ24 -> 2.2267876 | FQ24: =$FD$3/(1+$CI$15)^CJ24 -> 1.828049 | FR24: =$FD$3/(1+$CI$16)^CJ24 -> 1.5033447 | FS24: =$FD$3/(1+$CI$17)^CJ24 -> 1.2384475 | FT24: =$FD$3/(1+$CI$18)^CJ24 -> 1.0219552 | FW24: =$FV$3/(1+$CI$3)^CJ24 -> 0.032692491 | FX24: =$FV$3/(1+$CI$4)^CJ24 -> 0.026321732 | FY24: =$FV$3/(1+$CI$5)^CJ24 -> 0.0212373 | FZ24: =$FV$3/(1+$CI$6)^CJ24 -> 0.017649619 | GA24: =$FV$3/(1+$CI$7)^CJ24 -> 0.017170572 | GB24: =$FV$3/(1+$CI$8)^CJ24 -> 0.01391085 | GC24: =$FV$3/(1+$CI$9)^CJ24 -> 0.011292477 | GD24: =$FV$3/(1+$CI$10)^CJ24 -> 0.0099327 | GE24: =$FV$3/(1+$CI$11)^CJ24 -> 0.0074850657 | GF24: =$FV$3/(1+$CI$12)^CJ24 -> 0.0061113237 | GG24: =$FV$3/(1+$CI$13)^CJ24 -> 0.0049989543 | GH24: =$FV$3/(1+$CI$14)^CJ24 -> 0.0040964976 | GI24: =$FV$3/(1+$CI$15)^CJ24 -> 0.0033629603 | GJ24: =$FV$3/(1+$CI$16)^CJ24 -> 0.0027656198 | GK24: =$FV$3/(1+$CI$17)^CJ24 -> 0.0022783031 | GL24: =$FV$3/(1+$CI$18)^CJ24 -> 0.0018800342
A25: Microsoft | B25: 44742 | C25: 98.14 | D25: 1916.9791 | E25: 198.603 | F25: 3839.5 | G25: 72.738 | H25: =(D25/AI25) -> 26.354576 | I25: =(D25/G25) -> 26.354576 | J25: -45.924 | K25: -16 | L25: 8.795 | M25: -1.9 | N25: =(C25+L25+J25+K25+M25) -> 43.111 | P25: 7464000000 | Q25: =(P25-P24)/P24*100 -> -0.61251664 | S25: 279.83 | T25: =(S25*P25) -> 2088651120000 | U25: =(D25-D24)/D24*100 -> -8.1830169 | V25: 166.542 | W25: =(V25-V24)/V24*100 -> 17.293011 | X25: 87.72 | Y25: =(X25-X24)/X24*100 -> 3.8389147 | AA25: 0.1 | AB25: 166.542 | AC25: 141.988 | AD25: =(G24/AA25) -> 612.71 | AE25: =(D25-AC25-AD25) -> 1162.2811 | AF25: =((((D25-AD25)/(G25)*AA25)-1)/(1+(D25-AD25)/(G25))) -> 0.041894418 | AG25: =(1+AF25)/(1+AA25) -> 0.94717674 | AI25: 72.738 | AJ25: 72.738 | AL25: 72.738 | AM25: =D25/AL25 -> 26.354576 | AN25: 72.738 | AO25: =D25/AN25 -> 26.354576 | AQ25: =$D$28/AL25 -> 38.094932 | AR25: =AVERAGE(AQ25:AQ27) -> 35.942603 | AS25: =$D$28/AN25 -> 38.094932 | AT25: =AVERAGE(AS25:AS27) -> 35.942603 | AV25: =(D25/AB25) -> 11.510485 | AW25: =(D25/E25) -> 9.652317 | AX25: 78.822 | AY25: =(AB25-AX25) -> 87.72 | AZ25: =(D25/AY25) -> 21.853387 | BB25: 45.011 | BC25: 40.448 | BD25: =(BB25/D25)*100 -> 2.3480172 | BE25: =(BC25/D25)*100 -> 2.1099865 | BG25: 279.83 | BH25: 7464000000 | BI25: =(BG25*BH25) -> 2088651120000 | BJ25: 166.542 | BK25: =AY25 -> 87.72 | BL25: 169.684 | BM25: 95.082 | BN25: 103.216 | BO25: =(BL25-BM25-BN25) -> -28.614 | BP25: 104.757 | BQ25: =(BP25-BM25-BN25) -> -93.541 | BS25: =D25 -> 1916.9791 | BT25: =E25 -> 198.603 | BU25: =N25 -> 43.111 | BV25: =G25 -> 72.738 | CE25: 44742 | CF25: 1916.9791 | CG25: 43.111 | CH25: =(CG25/CF25) -> 0.02248903 | CJ25: 23 | CK25: =$CG$27/(1+$CI$3)^CJ25 -> 3.928687 | CL25: =$CG$27/(1+$CI$4)^CJ25 -> 3.1320961 | CM25: =$CG$27/(1+$CI$5)^CJ25 -> 2.5025505 | CN25: =$CG$27/(1+$CI$6)^CJ25 -> 2.0623672 | CO25: =$CG$27/(1+$CI$7)^CJ25 -> 2.0038824 | CP25: =$CG$27/(1+$CI$8)^CJ25 -> 1.6079967 | CQ25: =$CG$27/(1+$CI$9)^CJ25 -> 1.2930167 | CR25: =$CG$27/(1+$CI$10)^CJ25 -> 1.1307053 | CS25: =$CG$27/(1+$CI$11)^CJ25 -> 0.84118719 | CT25: =$CG$27/(1+$CI$12)^CJ25 -> 0.68050226 | CU25: =$CG$27/(1+$CI$13)^CJ25 -> 0.55157842 | CV25: =$CG$27/(1+$CI$14)^CJ25 -> 0.44793038 | CW25: =$CG$27/(1+$CI$15)^CJ25 -> 0.36443871 | CX25: =$CG$27/(1+$CI$16)^CJ25 -> 0.2970536 | CY25: =$CG$27/(1+$CI$17)^CJ25 -> 0.24256461 | CZ25: =$CG$27/(1+$CI$18)^CJ25 -> 0.19842149 | DC25: =$DB$3/(1+$CI$3)^CJ25 -> 28.067164 | DD25: =$DB$3/(1+$CI$4)^CJ25 -> 22.376192 | DE25: =$DB$3/(1+$CI$5)^CJ25 -> 17.878618 | DF25: =$DB$3/(1+$CI$6)^CJ25 -> 14.733879 | DG25: =$DB$3/(1+$CI$7)^CJ25 -> 14.316054 | DH25: =$DB$3/(1+$CI$8)^CJ25 -> 11.487784 | DI25: =$DB$3/(1+$CI$9)^CJ25 -> 9.2375164 | DJ25: =$DB$3/(1+$CI$10)^CJ25 -> 8.0779381 | DK25: =$DB$3/(1+$CI$11)^CJ25 -> 6.0095748 | DL25: =$DB$3/(1+$CI$12)^CJ25 -> 4.8616162 | DM25: =$DB$3/(1+$CI$13)^CJ25 -> 3.9405638 | DN25: =$DB$3/(1+$CI$14)^CJ25 -> 3.2000857 | DO25: =$DB$3/(1+$CI$15)^CJ25 -> 2.603608 | DP25: =$DB$3/(1+$CI$16)^CJ25 -> 2.1221981 | DQ25: =$DB$3/(1+$CI$17)^CJ25 -> 1.7329201 | DR25: =$DB$3/(1+$CI$18)^CJ25 -> 1.4175546 | DU25: =$DT$3/(1+$CI$3)^CJ25 -> 31.145841 | DV25: =$DT$3/(1+$CI$4)^CJ25 -> 24.830629 | DW25: =$DT$3/(1+$CI$5)^CJ25 -> 19.839718 | DX25: =$DT$3/(1+$CI$6)^CJ25 -> 16.350033 | DY25: =$DT$3/(1+$CI$7)^CJ25 -> 15.886377 | DZ25: =$DT$3/(1+$CI$8)^CJ25 -> 12.747875 | EA25: =$DT$3/(1+$CI$9)^CJ25 -> 10.250776 | EB25: =$DT$3/(1+$CI$10)^CJ25 -> 8.9640045 | EC25: =$DT$3/(1+$CI$11)^CJ25 -> 6.6687631 | ED25: =$DT$3/(1+$CI$12)^CJ25 -> 5.3948853 | EE25: =$DT$3/(1+$CI$13)^CJ25 -> 4.3728029 | EF25: =$DT$3/(1+$CI$14)^CJ25 -> 3.551102 | EG25: =$DT$3/(1+$CI$15)^CJ25 -> 2.8891969 | EH25: =$DT$3/(1+$CI$16)^CJ25 -> 2.3549813 | EI25: =$DT$3/(1+$CI$17)^CJ25 -> 1.9230035 | EJ25: =$DT$3/(1+$CI$18)^CJ25 -> 1.5730457 | EM25: =$EL$3/(1+$CI$3)^CJ25 -> 24.820727 | EN25: =$EL$3/(1+$CI$4)^CJ25 -> 19.788011 | EO25: =$EL$3/(1+$CI$5)^CJ25 -> 15.810657 | EP25: =$EL$3/(1+$CI$6)^CJ25 -> 13.029659 | EQ25: =$EL$3/(1+$CI$7)^CJ25 -> 12.660163 | ER25: =$EL$3/(1+$CI$8)^CJ25 -> 10.159029 | ES25: =$EL$3/(1+$CI$9)^CJ25 -> 8.1690432 | ET25: =$EL$3/(1+$CI$10)^CJ25 -> 7.1435896 | EU25: =$EL$3/(1+$CI$11)^CJ25 -> 5.314467 | EV25: =$EL$3/(1+$CI$12)^CJ25 -> 4.299289 | EW25: =$EL$3/(1+$CI$13)^CJ25 -> 3.4847717 | EX25: =$EL$3/(1+$CI$14)^CJ25 -> 2.8299423 | EY25: =$EL$3/(1+$CI$15)^CJ25 -> 2.3024572 | EZ25: =$EL$3/(1+$CI$16)^CJ25 -> 1.8767304 | FA25: =$EL$3/(1+$CI$17)^CJ25 -> 1.5324789 | FB25: =$EL$3/(1+$CI$18)^CJ25 -> 1.2535907 | FE25: =$FD$3/(1+$CI$3)^CJ25 -> 17.595141 | FF25: =$FD$3/(1+$CI$4)^CJ25 -> 14.027504 | FG25: =$FD$3/(1+$CI$5)^CJ25 -> 11.208001 | FH25: =$FD$3/(1+$CI$6)^CJ25 -> 9.2365824 | FI25: =$FD$3/(1+$CI$7)^CJ25 -> 8.9746503 | FJ25: =$FD$3/(1+$CI$8)^CJ25 -> 7.2016243 | FK25: =$FD$3/(1+$CI$9)^CJ25 -> 5.7909449 | FL25: =$FD$3/(1+$CI$10)^CJ25 -> 5.0640121 | FM25: =$FD$3/(1+$CI$11)^CJ25 -> 3.7673673 | FN25: =$FD$3/(1+$CI$12)^CJ25 -> 3.0477187 | FO25: =$FD$3/(1+$CI$13)^CJ25 -> 2.4703164 | FP25: =$FD$3/(1+$CI$14)^CJ25 -> 2.006115 | FQ25: =$FD$3/(1+$CI$15)^CJ25 -> 1.6321866 | FR25: =$FD$3/(1+$CI$16)^CJ25 -> 1.3303936 | FS25: =$FD$3/(1+$CI$17)^CJ25 -> 1.0863575 | FT25: =$FD$3/(1+$CI$18)^CJ25 -> 0.88865668 | FW25: =$FV$3/(1+$CI$3)^CJ25 -> 0.032368803 | FX25: =$FV$3/(1+$CI$4)^CJ25 -> 0.025805619 | FY25: =$FV$3/(1+$CI$5)^CJ25 -> 0.020618738 | FZ25: =$FV$3/(1+$CI$6)^CJ25 -> 0.016992028 | GA25: =$FV$3/(1+$CI$7)^CJ25 -> 0.016510166 | GB25: =$FV$3/(1+$CI$8)^CJ25 -> 0.013248428 | GC25: =$FV$3/(1+$CI$9)^CJ25 -> 0.01065328 | GD25: =$FV$3/(1+$CI$10)^CJ25 -> 0.009315982 | GE25: =$FV$3/(1+$CI$11)^CJ25 -> 0.0069306164 | GF25: =$FV$3/(1+$CI$12)^CJ25 -> 0.005606719 | GG25: =$FV$3/(1+$CI$13)^CJ25 -> 0.0045445039 | GH25: =$FV$3/(1+$CI$14)^CJ25 -> 0.0036905384 | GI25: =$FV$3/(1+$CI$15)^CJ25 -> 0.0030026431 | GJ25: =$FV$3/(1+$CI$16)^CJ25 -> 0.0024474512 | GK25: =$FV$3/(1+$CI$17)^CJ25 -> 0.0019985115 | GL25: =$FV$3/(1+$CI$18)^CJ25 -> 0.0016348124
A26: Microsoft | B26: 45107 | C26: 106.772 | D26: 2530.8933 | E26: 212.703 | F26: 4769.83 | G26: 72.361 | H26: =(D26/AI26) -> 34.97593 | I26: =(D26/G26) -> 34.97593 | J26: -29.777 | K26: -23.1 | L26: 5.61 | M26: -1.7 | N26: =(C26+L26+J26+K26+M26) -> 57.805 | P26: 7431000000 | Q26: =(P26-P25)/P25*100 -> -0.44212219 | S26: 367.94 | T26: =(S26*P26) -> 2734162140000 | U26: =(D26-D25)/D25*100 -> 32.025083 | V26: 206.223 | W26: =(V26-V25)/V25*100 -> 23.826422 | X26: 128.971 | Y26: =(X26-X25)/X25*100 -> 47.025764 | AA26: 0.1 | AB26: 206.223 | AC26: 166.542 | AD26: =(G25/AA26) -> 727.38 | AE26: =(D26-AC26-AD26) -> 1636.9713 | AF26: =((((D26-AD26)/(G26)*AA26)-1)/(1+(D26-AD26)/(G26))) -> 0.057567999 | AG26: =(1+AF26)/(1+AA26) -> 0.96142545 | AI26: 72.361 | AJ26: 72.361 | AL26: 72.361 | AM26: =D26/AL26 -> 34.97593 | AN26: 72.361 | AO26: =D26/AN26 -> 34.97593 | AQ26: =$D$28/AL26 -> 38.293406 | AS26: =$D$28/AN26 -> 38.293406 | AV26: =(D26/AB26) -> 12.272604 | AW26: =(D26/E26) -> 11.898719 | AX26: 77.252 | AY26: =(AB26-AX26) -> 128.971 | AZ26: =(D26/AY26) -> 19.623739 | BB26: 59.505 | BC26: 44.908 | BD26: =(BB26/D26)*100 -> 2.3511462 | BE26: =(BC26/D26)*100 -> 1.7743933 | BG26: 367.94 | BH26: 7432000000 | BI26: =(BG26*BH26) -> 2734530080000 | BJ26: 206.223 | BK26: =AY26 -> 128.971 | BL26: 184.257 | BM26: 104.149 | BN26: 101.604 | BO26: =(BL26-BM26-BN26) -> -21.496 | BP26: 111.262 | BQ26: =(BP26-BM26-BN26) -> -94.491 | BS26: =D26 -> 2530.8933 | BT26: =E26 -> 212.703 | BU26: =N26 -> 57.805 | BV26: =G26 -> 72.361 | CE26: 45107 | CF26: 2530.8933 | CG26: 57.805 | CH26: =(CG26/CF26) -> 0.022839762 | CJ26: 24 | CK26: =$CG$27/(1+$CI$3)^CJ26 -> 3.8897891 | CL26: =$CG$27/(1+$CI$4)^CJ26 -> 3.0706824 | CM26: =$CG$27/(1+$CI$5)^CJ26 -> 2.4296607 | CN26: =$CG$27/(1+$CI$6)^CJ26 -> 1.9855273 | CO26: =$CG$27/(1+$CI$7)^CJ26 -> 1.92681 | CP26: =$CG$27/(1+$CI$8)^CJ26 -> 1.5314254 | CQ26: =$CG$27/(1+$CI$9)^CJ26 -> 1.2198271 | CR26: =$CG$27/(1+$CI$10)^CJ26 -> 1.0605002 | CS26: =$CG$27/(1+$CI$11)^CJ26 -> 0.77887703 | CT26: =$CG$27/(1+$CI$12)^CJ26 -> 0.624314 | CU26: =$CG$27/(1+$CI$13)^CJ26 -> 0.50143493 | CV26: =$CG$27/(1+$CI$14)^CJ26 -> 0.40354088 | CW26: =$CG$27/(1+$CI$15)^CJ26 -> 0.32539171 | CX26: =$CG$27/(1+$CI$16)^CJ26 -> 0.2628793 | CY26: =$CG$27/(1+$CI$17)^CJ26 -> 0.21277598 | CZ26: =$CG$27/(1+$CI$18)^CJ26 -> 0.17254042 | DC26: =$DB$3/(1+$CI$3)^CJ26 -> 27.789271 | DD26: =$DB$3/(1+$CI$4)^CJ26 -> 21.937443 | DE26: =$DB$3/(1+$CI$5)^CJ26 -> 17.357882 | DF26: =$DB$3/(1+$CI$6)^CJ26 -> 14.184922 | DG26: =$DB$3/(1+$CI$7)^CJ26 -> 13.765436 | DH26: =$DB$3/(1+$CI$8)^CJ26 -> 10.940746 | DI26: =$DB$3/(1+$CI$9)^CJ26 -> 8.7146381 | DJ26: =$DB$3/(1+$CI$10)^CJ26 -> 7.5763817 | DK26: =$DB$3/(1+$CI$11)^CJ26 -> 5.5644211 | DL26: =$DB$3/(1+$CI$12)^CJ26 -> 4.4601983 | DM26: =$DB$3/(1+$CI$13)^CJ26 -> 3.5823307 | DN26: =$DB$3/(1+$CI$14)^CJ26 -> 2.8829601 | DO26: =$DB$3/(1+$CI$15)^CJ26 -> 2.32465 | DP26: =$DB$3/(1+$CI$16)^CJ26 -> 1.8780514 | DQ26: =$DB$3/(1+$CI$17)^CJ26 -> 1.5201054 | DR26: =$DB$3/(1+$CI$18)^CJ26 -> 1.2326562 | DU26: =$DT$3/(1+$CI$3)^CJ26 -> 30.837467 | DV26: =$DT$3/(1+$CI$4)^CJ26 -> 24.343754 | DW26: =$DT$3/(1+$CI$5)^CJ26 -> 19.261862 | DX26: =$DT$3/(1+$CI$6)^CJ26 -> 15.740862 | DY26: =$DT$3/(1+$CI$7)^CJ26 -> 15.275362 | DZ26: =$DT$3/(1+$CI$8)^CJ26 -> 12.140833 | EA26: =$DT$3/(1+$CI$9)^CJ26 -> 9.6705439 | EB26: =$DT$3/(1+$CI$10)^CJ26 -> 8.4074325 | EC26: =$DT$3/(1+$CI$11)^CJ26 -> 6.1747806 | ED26: =$DT$3/(1+$CI$12)^CJ26 -> 4.949436 | EE26: =$DT$3/(1+$CI$13)^CJ26 -> 3.9752754 | EF26: =$DT$3/(1+$CI$14)^CJ26 -> 3.199191 | EG26: =$DT$3/(1+$CI$15)^CJ26 -> 2.5796401 | EH26: =$DT$3/(1+$CI$16)^CJ26 -> 2.0840543 | EI26: =$DT$3/(1+$CI$17)^CJ26 -> 1.6868452 | EJ26: =$DT$3/(1+$CI$18)^CJ26 -> 1.3678658 | EM26: =$EL$3/(1+$CI$3)^CJ26 -> 24.574977 | EN26: =$EL$3/(1+$CI$4)^CJ26 -> 19.400011 | EO26: =$EL$3/(1+$CI$5)^CJ26 -> 15.350153 | EP26: =$EL$3/(1+$CI$6)^CJ26 -> 12.544199 | EQ26: =$EL$3/(1+$CI$7)^CJ26 -> 12.173233 | ER26: =$EL$3/(1+$CI$8)^CJ26 -> 9.6752661 | ES26: =$EL$3/(1+$CI$9)^CJ26 -> 7.7066445 | ET26: =$EL$3/(1+$CI$10)^CJ26 -> 6.7000465 | EU26: =$EL$3/(1+$CI$11)^CJ26 -> 4.9208028 | EV26: =$EL$3/(1+$CI$12)^CJ26 -> 3.9443018 | EW26: =$EL$3/(1+$CI$13)^CJ26 -> 3.1679743 | EX26: =$EL$3/(1+$CI$14)^CJ26 -> 2.5494976 | EY26: =$EL$3/(1+$CI$15)^CJ26 -> 2.0557654 | EZ26: =$EL$3/(1+$CI$16)^CJ26 -> 1.6608234 | FA26: =$EL$3/(1+$CI$17)^CJ26 -> 1.3442798 | FB26: =$EL$3/(1+$CI$18)^CJ26 -> 1.0900789 | FE26: =$FD$3/(1+$CI$3)^CJ26 -> 17.420931 | FF26: =$FD$3/(1+$CI$4)^CJ26 -> 13.752454 | FG26: =$FD$3/(1+$CI$5)^CJ26 -> 10.881555 | FH26: =$FD$3/(1+$CI$6)^CJ26 -> 8.8924448 | FI26: =$FD$3/(1+$CI$7)^CJ26 -> 8.6294714 | FJ26: =$FD$3/(1+$CI$8)^CJ26 -> 6.8586898 | FK26: =$FD$3/(1+$CI$9)^CJ26 -> 5.4631556 | FL26: =$FD$3/(1+$CI$10)^CJ26 -> 4.7495893 | FM26: =$FD$3/(1+$CI$11)^CJ26 -> 3.488303 | FN26: =$FD$3/(1+$CI$12)^CJ26 -> 2.7960722 | FO26: =$FD$3/(1+$CI$13)^CJ26 -> 2.2457422 | FP26: =$FD$3/(1+$CI$14)^CJ26 -> 1.8073108 | FQ26: =$FD$3/(1+$CI$15)^CJ26 -> 1.4573095 | FR26: =$FD$3/(1+$CI$16)^CJ26 -> 1.1773394 | FS26: =$FD$3/(1+$CI$17)^CJ26 -> 0.95294515 | FT26: =$FD$3/(1+$CI$18)^CJ26 -> 0.77274494 | FW26: =$FV$3/(1+$CI$3)^CJ26 -> 0.03204832 | FX26: =$FV$3/(1+$CI$4)^CJ26 -> 0.025299627 | FY26: =$FV$3/(1+$CI$5)^CJ26 -> 0.020018192 | FZ26: =$FV$3/(1+$CI$6)^CJ26 -> 0.016358937 | GA26: =$FV$3/(1+$CI$7)^CJ26 -> 0.015875159 | GB26: =$FV$3/(1+$CI$8)^CJ26 -> 0.012617551 | GC26: =$FV$3/(1+$CI$9)^CJ26 -> 0.010050264 | GD26: =$FV$3/(1+$CI$10)^CJ26 -> 0.0087375558 | GE26: =$FV$3/(1+$CI$11)^CJ26 -> 0.0064172374 | GF26: =$FV$3/(1+$CI$12)^CJ26 -> 0.0051437789 | GG26: =$FV$3/(1+$CI$13)^CJ26 -> 0.0041313672 | GH26: =$FV$3/(1+$CI$14)^CJ26 -> 0.0033248094 | GI26: =$FV$3/(1+$CI$15)^CJ26 -> 0.0026809314 | GJ26: =$FV$3/(1+$CI$16)^CJ26 -> 0.002165886 | GK26: =$FV$3/(1+$CI$17)^CJ26 -> 0.0017530803 | GL26: =$FV$3/(1+$CI$18)^CJ26 -> 0.001421576
A27: Microsoft | B27: 45473 | C27: 123.97 | D27: 3322.6263 | E27: 245.122 | F27: 5881.63 | G27: 88.136 | H27: =(D27/AI27) -> 37.698855 | I27: =(D27/G27) -> 37.698855 | J27: -113.609 | K27: -23.4 | L27: 19.678 | M27: -1.7 | N27: =(C27+L27+J27+K27+M27) -> 4.939 | P27: 7432305794 | Q27: =(P27-P26)/P26*100 -> 0.017572251 | S27: 424.83 | T27: =(S27*P27) -> 3.1574665e+12 | U27: =(D27-D26)/D26*100 -> 31.28275 | V27: 268.477 | W27: =(V27-V26)/V26*100 -> 30.187709 | X27: 121.66 | Y27: =(X27-X26)/X26*100 -> -5.6687162 | AA27: 0.1 | AB27: 268.477 | AC27: 206.223 | AD27: =(G26/AA27) -> 723.61 | AE27: =(D27-AC27-AD27) -> 2392.7933 | AF27: =((((D27-AD27)/(G27)*AA27)-1)/(1+(D27-AD27)/(G27))) -> 0.063921062 | AG27: =(1+AF27)/(1+AA27) -> 0.96720097 | AI27: 88.136 | AJ27: 88.136 | AL27: 88.136 | AM27: =D27/AL27 -> 37.698855 | AN27: 88.136 | AO27: =D27/AN27 -> 37.698855 | AQ27: =$D$28/AL27 -> 31.43947 | AR27: =AQ27 -> 31.43947 | AS27: =$D$28/AN27 -> 31.43947 | AT27: =AS27 -> 31.43947 | AV27: =(D27/AB27) -> 12.375832 | AW27: =(D27/E27) -> 13.55499 | AX27: 146.817 | AY27: =(AB27-AX27) -> 121.66 | AZ27: =(D27/AY27) -> 27.310754 | BB27: 6.639 | BC27: -0.403 | BD27: =(BB27/D27)*100 -> 0.19981182 | BE27: =(BC27/D27)*100 -> -0.01212896 | BG27: 424.83 | BH27: 7432305794 | BI27: =(BG27*BH27) -> 3.1574665e+12 | BJ27: 268.477 | BK27: =AY27 -> 121.66 | BL27: 159.734 | BM27: 125.286 | BN27: 118.4 | BO27: =(BL27-BM27-BN27) -> -83.952 | BP27: 75.543 | BQ27: =(BP27-BM27-BN27) -> -168.143 | BS27: =D27 -> 3322.6263 | BT27: =E27 -> 245.122 | BU27: =N27 -> 4.939 | BV27: =G27 -> 88.136 | BW27: =((BS27/BS22)^(1/5)-1)*100 -> 25.727664 | BX27: =((BT27/BT22)^(1/5)-1)*100 -> 13.654592 | BY27: =((BU27/BU22)^(1/5)-1)*100 -> -32.73693 | BZ27: =((BV27/BV22)^(1/5)-1)*100 -> 17.568644 | CA27: =((BS27/BS17)^(1/10)-1)*100 -> 24.53993 | CB27: =((BT27/BT17)^(1/10)-1)*100 -> 10.851581 | CC27: =((BU27/BU17)^(1/10)-1)*100 -> -13.50782 | CD27: =((BV27/BV17)^(1/10)-1)*100 -> 14.849003 | CE27: 45473 | CF27: 3322.6263 | CG27: 4.939 | CH27: =(CG27/CF27) -> 0.0014864747 | CJ27: 25 | CK27: =$CG$27/(1+$CI$3)^CJ27 -> 3.8512763 | CL27: =$CG$27/(1+$CI$4)^CJ27 -> 3.010473 | CM27: =$CG$27/(1+$CI$5)^CJ27 -> 2.3588939 | CN27: =$CG$27/(1+$CI$6)^CJ27 -> 1.9115503 | CO27: =$CG$27/(1+$CI$7)^CJ27 -> 1.8527019 | CP27: =$CG$27/(1+$CI$8)^CJ27 -> 1.4585004 | CQ27: =$CG$27/(1+$CI$9)^CJ27 -> 1.1507802 | CR27: =$CG$27/(1+$CI$10)^CJ27 -> 0.99465409 | CS27: =$CG$27/(1+$CI$11)^CJ27 -> 0.72118243 | CT27: =$CG$27/(1+$CI$12)^CJ27 -> 0.57276514 | CU27: =$CG$27/(1+$CI$13)^CJ27 -> 0.45584993 | CV27: =$CG$27/(1+$CI$14)^CJ27 -> 0.36355034 | CW27: =$CG$27/(1+$CI$15)^CJ27 -> 0.29052831 | CX27: =$CG$27/(1+$CI$16)^CJ27 -> 0.23263654 | CY27: =$CG$27/(1+$CI$17)^CJ27 -> 0.18664559 | CZ27: =$CG$27/(1+$CI$18)^CJ27 -> 0.15003515 | DC27: =$DB$3/(1+$CI$3)^CJ27 -> 27.51413 | DD27: =$DB$3/(1+$CI$4)^CJ27 -> 21.507297 | DE27: =$DB$3/(1+$CI$5)^CJ27 -> 16.852313 | DF27: =$DB$3/(1+$CI$6)^CJ27 -> 13.656419 | DG27: =$DB$3/(1+$CI$7)^CJ27 -> 13.235996 | DH27: =$DB$3/(1+$CI$8)^CJ27 -> 10.419758 | DI27: =$DB$3/(1+$CI$9)^CJ27 -> 8.2213567 | DJ27: =$DB$3/(1+$CI$10)^CJ27 -> 7.1059667 | DK27: =$DB$3/(1+$CI$11)^CJ27 -> 5.1522418 | DL27: =$DB$3/(1+$CI$12)^CJ27 -> 4.0919251 | DM27: =$DB$3/(1+$CI$13)^CJ27 -> 3.2566643 | DN27: =$DB$3/(1+$CI$14)^CJ27 -> 2.5972613 | DO27: =$DB$3/(1+$CI$15)^CJ27 -> 2.0755804 | DP27: =$DB$3/(1+$CI$16)^CJ27 -> 1.6619924 | DQ27: =$DB$3/(1+$CI$17)^CJ27 -> 1.3334258 | DR27: =$DB$3/(1+$CI$18)^CJ27 -> 1.0718749 | DU27: =$DT$3/(1+$CI$3)^CJ27 -> 30.532145 | DV27: =$DT$3/(1+$CI$4)^CJ27 -> 23.866425 | DW27: =$DT$3/(1+$CI$5)^CJ27 -> 18.700837 | DX27: =$DT$3/(1+$CI$6)^CJ27 -> 15.154387 | DY27: =$DT$3/(1+$CI$7)^CJ27 -> 14.687848 | DZ27: =$DT$3/(1+$CI$8)^CJ27 -> 11.562698 | EA27: =$DT$3/(1+$CI$9)^CJ27 -> 9.1231546 | EB27: =$DT$3/(1+$CI$10)^CJ27 -> 7.8854178 | EC27: =$DT$3/(1+$CI$11)^CJ27 -> 5.7173895 | ED27: =$DT$3/(1+$CI$12)^CJ27 -> 4.540767 | EE27: =$DT$3/(1+$CI$13)^CJ27 -> 3.6138867 | EF27: =$DT$3/(1+$CI$14)^CJ27 -> 2.8821541 | EG27: =$DT$3/(1+$CI$15)^CJ27 -> 2.3032501 | EH27: =$DT$3/(1+$CI$16)^CJ27 -> 1.8442958 | EI27: =$DT$3/(1+$CI$17)^CJ27 -> 1.4796888 | EJ27: =$DT$3/(1+$CI$18)^CJ27 -> 1.1894485 | EM27: =$EL$3/(1+$CI$3)^CJ27 -> 24.331661 | EN27: =$EL$3/(1+$CI$4)^CJ27 -> 19.019618 | EO27: =$EL$3/(1+$CI$5)^CJ27 -> 14.903061 | EP27: =$EL$3/(1+$CI$6)^CJ27 -> 12.076826 | EQ27: =$EL$3/(1+$CI$7)^CJ27 -> 11.705032 | ER27: =$EL$3/(1+$CI$8)^CJ27 -> 9.2145391 | ES27: =$EL$3/(1+$CI$9)^CJ27 -> 7.2704194 | ET27: =$EL$3/(1+$CI$10)^CJ27 -> 6.2840429 | EU27: =$EL$3/(1+$CI$11)^CJ27 -> 4.5562989 | EV27: =$EL$3/(1+$CI$12)^CJ27 -> 3.6186256 | EW27: =$EL$3/(1+$CI$13)^CJ27 -> 2.8799766 | EX27: =$EL$3/(1+$CI$14)^CJ27 -> 2.2968447 | EY27: =$EL$3/(1+$CI$15)^CJ27 -> 1.8355048 | EZ27: =$EL$3/(1+$CI$16)^CJ27 -> 1.4697552 | FA27: =$EL$3/(1+$CI$17)^CJ27 -> 1.1791928 | FB27: =$EL$3/(1+$CI$18)^CJ27 -> 0.94789468 | FE27: =$FD$3/(1+$CI$3)^CJ27 -> 17.248447 | FF27: =$FD$3/(1+$CI$4)^CJ27 -> 13.482798 | FG27: =$FD$3/(1+$CI$5)^CJ27 -> 10.564616 | FH27: =$FD$3/(1+$CI$6)^CJ27 -> 8.5611291 | FI27: =$FD$3/(1+$CI$7)^CJ27 -> 8.2975687 | FJ27: =$FD$3/(1+$CI$8)^CJ27 -> 6.5320855 | FK27: =$FD$3/(1+$CI$9)^CJ27 -> 5.1539204 | FL27: =$FD$3/(1+$CI$10)^CJ27 -> 4.4546889 | FM27: =$FD$3/(1+$CI$11)^CJ27 -> 3.2299102 | FN27: =$FD$3/(1+$CI$12)^CJ27 -> 2.5652039 | FO27: =$FD$3/(1+$CI$13)^CJ27 -> 2.0415838 | FP27: =$FD$3/(1+$CI$14)^CJ27 -> 1.6282079 | FQ27: =$FD$3/(1+$CI$15)^CJ27 -> 1.3011692 | FR27: =$FD$3/(1+$CI$16)^CJ27 -> 1.0418933 | FS27: =$FD$3/(1+$CI$17)^CJ27 -> 0.8359168 | FT27: =$FD$3/(1+$CI$18)^CJ27 -> 0.67195212 | FW27: =$FV$3/(1+$CI$3)^CJ27 -> 0.03173101 | FX27: =$FV$3/(1+$CI$4)^CJ27 -> 0.024803556 | FY27: =$FV$3/(1+$CI$5)^CJ27 -> 0.019435138 | FZ27: =$FV$3/(1+$CI$6)^CJ27 -> 0.015749434 | GA27: =$FV$3/(1+$CI$7)^CJ27 -> 0.015264576 | GB27: =$FV$3/(1+$CI$8)^CJ27 -> 0.012016715 | GC27: =$FV$3/(1+$CI$9)^CJ27 -> 0.0094813812 | GD27: =$FV$3/(1+$CI$10)^CJ27 -> 0.0081950439 | GE27: =$FV$3/(1+$CI$11)^CJ27 -> 0.0059418865 | GF27: =$FV$3/(1+$CI$12)^CJ27 -> 0.0047190632 | GG27: =$FV$3/(1+$CI$13)^CJ27 -> 0.0037557884 | GH27: =$FV$3/(1+$CI$14)^CJ27 -> 0.0029953237 | GI27: =$FV$3/(1+$CI$15)^CJ27 -> 0.0023936887 | GJ27: =$FV$3/(1+$CI$16)^CJ27 -> 0.0019167133 | GK27: =$FV$3/(1+$CI$17)^CJ27 -> 0.0015377897 | GL27: =$FV$3/(1+$CI$18)^CJ27 -> 0.001236153
A28: Microsoft | B28: 45747 | C28: 171.812 | D28: 2770.9492 | E28: 70.066 | F28: 42215.8 | G28: 101.832 | H28: =(D28/AI28) -> 107.30132 | I28: =(D28/G28) -> 27.210986 | J28: -51.707 | K28: 0 | L28: 10.015 | M28: 0 | N28: =(C28+L28+J28+K28+M28) -> 130.12 | U28: =(D28-D27)/D27*100 -> -16.603647 | V28: 321.891 | W28: =(V28-V27)/V27*100 -> 19.895187 | X28: 178.594 | Y28: =(X28-X27)/X27*100 -> 46.797633 | AA28: 0.1 | AB28: 321.891 | AC28: 268.477 | AD28: =(G27/AA28) -> 881.36 | AE28: =(D28-AC28-AD28) -> 1621.1122 | AF28: =((((D28-AD28)/(G28)*AA28)-1)/(1+(D28-AD28)/(G28))) -> 0.043751125 | AG28: =(1+AF28)/(1+AA28) -> 0.94886466 | AI28: 25.824 | AJ28: 25.824 | AL28: 25.824 | AM28: =D28/AL28 -> 107.30132 | AN28: 25.824 | AO28: =D28/AN28 -> 107.30132 | AQ28: =$D$28/AL28 -> 107.30132 | AS28: =$D$28/AN28 -> 107.30132 | AV28: =(D28/AB28) -> 8.6083462 | AW28: =(D28/E28) -> 39.5477 | AX28: 143.297 | AY28: =(AB28-AX28) -> 178.594 | AZ28: =(D28/AY28) -> 15.515354 | BB28: 41.808 | BC28: 33.455 | BD28: =(BB28/D28)*100 -> 1.5087971 | BE28: =(BC28/D28)*100 -> 1.207348 | BJ28: 321.891 | BK28: =AY28 -> 178.594 | BL28: 156.644 | BM28: 114.206 | BN28: 126.527 | BO28: =(BL28-BM28-BN28) -> -84.089 | BP28: 79.618 | BQ28: =(BP28-BM28-BN28) -> -161.115 | BS28: =D28 -> 2770.9492 | BT28: =E28 -> 70.066 | BU28: =N28 -> 130.12 | BV28: =G28 -> 101.832 | BW28: =((BS28/BS23)^(1/5)-1)*100 -> 11.806647 | BX28: =((BT28/BT23)^(1/5)-1)*100 -> -13.618709 | BY28: =((BU28/BU23)^(1/5)-1)*100 -> 24.955908 | BZ28: =((BV28/BV23)^(1/5)-1)*100 -> 18.122701 | CD28: =((BV28/BV18)^(1/10)-1)*100 -> 23.645231 | CE28: 45747 | CF28: 2770.9492 | CG28: 41.808 | CH28: =(CG28/CF28) -> 0.015087971 | CJ28: 26 | CK28: =$CG$27/(1+$CI$3)^CJ28 -> 3.8131449 | CL28: =$CG$27/(1+$CI$4)^CJ28 -> 2.9514441 | CM28: =$CG$27/(1+$CI$5)^CJ28 -> 2.2901883 | CN28: =$CG$27/(1+$CI$6)^CJ28 -> 1.8403296 | CO28: =$CG$27/(1+$CI$7)^CJ28 -> 1.7814441 | CP28: =$CG$27/(1+$CI$8)^CJ28 -> 1.389048 | CQ28: =$CG$27/(1+$CI$9)^CJ28 -> 1.0856417 | CR28: =$CG$27/(1+$CI$10)^CJ28 -> 0.93289635 | CS28: =$CG$27/(1+$CI$11)^CJ28 -> 0.66776151 | CT28: =$CG$27/(1+$CI$12)^CJ28 -> 0.52547261 | CU28: =$CG$27/(1+$CI$13)^CJ28 -> 0.41440903 | CV28: =$CG$27/(1+$CI$14)^CJ28 -> 0.32752283 | CW28: =$CG$27/(1+$CI$15)^CJ28 -> 0.25940028 | CX28: =$CG$27/(1+$CI$16)^CJ28 -> 0.20587305 | CY28: =$CG$27/(1+$CI$17)^CJ28 -> 0.16372421 | CZ28: =$CG$27/(1+$CI$18)^CJ28 -> 0.13046535 | DC28: =$DB$3/(1+$CI$3)^CJ28 -> 27.241712 | DD28: =$DB$3/(1+$CI$4)^CJ28 -> 21.085585 | DE28: =$DB$3/(1+$CI$5)^CJ28 -> 16.361468 | DF28: =$DB$3/(1+$CI$6)^CJ28 -> 13.147607 | DG28: =$DB$3/(1+$CI$7)^CJ28 -> 12.72692 | DH28: =$DB$3/(1+$CI$8)^CJ28 -> 9.9235793 | DI28: =$DB$3/(1+$CI$9)^CJ28 -> 7.7559969 | DJ28: =$DB$3/(1+$CI$10)^CJ28 -> 6.6647596 | DK28: =$DB$3/(1+$CI$11)^CJ28 -> 4.7705942 | DL28: =$DB$3/(1+$CI$12)^CJ28 -> 3.7540597 | DM28: =$DB$3/(1+$CI$13)^CJ28 -> 2.9606039 | DN28: =$DB$3/(1+$CI$14)^CJ28 -> 2.3398751 | DO28: =$DB$3/(1+$CI$15)^CJ28 -> 1.8531968 | DP28: =$DB$3/(1+$CI$16)^CJ28 -> 1.4707897 | DQ28: =$DB$3/(1+$CI$17)^CJ28 -> 1.1696717 | DR28: =$DB$3/(1+$CI$18)^CJ28 -> 0.93206516 | DU28: =$DT$3/(1+$CI$3)^CJ28 -> 30.229847 | DV28: =$DT$3/(1+$CI$4)^CJ28 -> 23.398456 | DW28: =$DT$3/(1+$CI$5)^CJ28 -> 18.156153 | DX28: =$DT$3/(1+$CI$6)^CJ28 -> 14.589763 | DY28: =$DT$3/(1+$CI$7)^CJ28 -> 14.122931 | DZ28: =$DT$3/(1+$CI$8)^CJ28 -> 11.012093 | EA28: =$DT$3/(1+$CI$9)^CJ28 -> 8.6067496 | EB28: =$DT$3/(1+$CI$10)^CJ28 -> 7.3958149 | EC28: =$DT$3/(1+$CI$11)^CJ28 -> 5.2938791 | ED28: =$DT$3/(1+$CI$12)^CJ28 -> 4.1658413 | EE28: =$DT$3/(1+$CI$13)^CJ28 -> 3.2853516 | EF28: =$DT$3/(1+$CI$14)^CJ28 -> 2.5965352 | EG28: =$DT$3/(1+$CI$15)^CJ28 -> 2.0564733 | EH28: =$DT$3/(1+$CI$16)^CJ28 -> 1.6321202 | EI28: =$DT$3/(1+$CI$17)^CJ28 -> 1.2979726 | EJ28: =$DT$3/(1+$CI$18)^CJ28 -> 1.0343031 | EM28: =$EL$3/(1+$CI$3)^CJ28 -> 24.090753 | EN28: =$EL$3/(1+$CI$4)^CJ28 -> 18.646685 | EO28: =$EL$3/(1+$CI$5)^CJ28 -> 14.468991 | EP28: =$EL$3/(1+$CI$6)^CJ28 -> 11.626866 | EQ28: =$EL$3/(1+$CI$7)^CJ28 -> 11.254839 | ER28: =$EL$3/(1+$CI$8)^CJ28 -> 8.7757515 | ES28: =$EL$3/(1+$CI$9)^CJ28 -> 6.8588862 | ET28: =$EL$3/(1+$CI$10)^CJ28 -> 5.8938688 | EU28: =$EL$3/(1+$CI$11)^CJ28 -> 4.2187953 | EV28: =$EL$3/(1+$CI$12)^CJ28 -> 3.31984 | EW28: =$EL$3/(1+$CI$13)^CJ28 -> 2.6181606 | EX28: =$EL$3/(1+$CI$14)^CJ28 -> 2.0692294 | EY28: =$EL$3/(1+$CI$15)^CJ28 -> 1.6388436 | EZ28: =$EL$3/(1+$CI$16)^CJ28 -> 1.3006683 | FA28: =$EL$3/(1+$CI$17)^CJ28 -> 1.0343796 | FB28: =$EL$3/(1+$CI$18)^CJ28 -> 0.82425624 | FE28: =$FD$3/(1+$CI$3)^CJ28 -> 17.07767 | FF28: =$FD$3/(1+$CI$4)^CJ28 -> 13.21843 | FG28: =$FD$3/(1+$CI$5)^CJ28 -> 10.256909 | FH28: =$FD$3/(1+$CI$6)^CJ28 -> 8.2421576 | FI28: =$FD$3/(1+$CI$7)^CJ28 -> 7.9784314 | FJ28: =$FD$3/(1+$CI$8)^CJ28 -> 6.2210338 | FK28: =$FD$3/(1+$CI$9)^CJ28 -> 4.862189 | FL28: =$FD$3/(1+$CI$10)^CJ28 -> 4.1780988 | FM28: =$FD$3/(1+$CI$11)^CJ28 -> 2.9906576 | FN28: =$FD$3/(1+$CI$12)^CJ28 -> 2.3533981 | FO28: =$FD$3/(1+$CI$13)^CJ28 -> 1.8559853 | FP28: =$FD$3/(1+$CI$14)^CJ28 -> 1.466854 | FQ28: =$FD$3/(1+$CI$15)^CJ28 -> 1.1617582 | FR28: =$FD$3/(1+$CI$16)^CJ28 -> 0.92202948 | FS28: =$FD$3/(1+$CI$17)^CJ28 -> 0.73326035 | FT28: =$FD$3/(1+$CI$18)^CJ28 -> 0.58430619 | FW28: =$FV$3/(1+$CI$3)^CJ28 -> 0.031416842 | FX28: =$FV$3/(1+$CI$4)^CJ28 -> 0.024317212 | FY28: =$FV$3/(1+$CI$5)^CJ28 -> 0.018869066 | FZ28: =$FV$3/(1+$CI$6)^CJ28 -> 0.01516264 | GA28: =$FV$3/(1+$CI$7)^CJ28 -> 0.014677477 | GB28: =$FV$3/(1+$CI$8)^CJ28 -> 0.011444491 | GC28: =$FV$3/(1+$CI$9)^CJ28 -> 0.0089446992 | GD28: =$FV$3/(1+$CI$10)^CJ28 -> 0.0076862164 | GE28: =$FV$3/(1+$CI$11)^CJ28 -> 0.0055017468 | GF28: =$FV$3/(1+$CI$12)^CJ28 -> 0.0043294158 | GG28: =$FV$3/(1+$CI$13)^CJ28 -> 0.003414353 | GH28: =$FV$3/(1+$CI$14)^CJ28 -> 0.0026984899 | GI28: =$FV$3/(1+$CI$15)^CJ28 -> 0.0021372221 | GJ28: =$FV$3/(1+$CI$16)^CJ28 -> 0.0016962064 | GK28: =$FV$3/(1+$CI$17)^CJ28 -> 0.0013489384 | GL28: =$FV$3/(1+$CI$18)^CJ28 -> 0.0010749157
B29: CAGR % | AA29: 0.1 | AC29: 321.891 | AD29: =(G28/AA29) -> 1018.32 | AE29: =(D29-AC29-AD29) -> -1340.211 | AF29: =((((D29-AD29)/(G29)*AA29)-1)/(1+(D29-AD29)/(G29))) -> #DIV/0! | AG29: =(1+AF29)/(1+AA29) -> #DIV/0! | CJ29: 27 | CK29: =$CG$27/(1+$CI$3)^CJ29 -> 3.775391 | CL29: =$CG$27/(1+$CI$4)^CJ29 -> 2.8935726 | CM29: =$CG$27/(1+$CI$5)^CJ29 -> 2.2234837 | CN29: =$CG$27/(1+$CI$6)^CJ29 -> 1.7717624 | CO29: =$CG$27/(1+$CI$7)^CJ29 -> 1.712927 | CP29: =$CG$27/(1+$CI$8)^CJ29 -> 1.3229028 | CQ29: =$CG$27/(1+$CI$9)^CJ29 -> 1.0241903 | CR29: =$CG$27/(1+$CI$10)^CJ29 -> 0.87497313 | CS29: =$CG$27/(1+$CI$11)^CJ29 -> 0.6182977 | CT29: =$CG$27/(1+$CI$12)^CJ29 -> 0.48208496 | CU29: =$CG$27/(1+$CI$13)^CJ29 -> 0.37673548 | CV29: =$CG$27/(1+$CI$14)^CJ29 -> 0.29506561 | CW29: =$CG$27/(1+$CI$15)^CJ29 -> 0.23160739 | CX29: =$CG$27/(1+$CI$16)^CJ29 -> 0.18218854 | CY29: =$CG$27/(1+$CI$17)^CJ29 -> 0.14361772 | CZ29: =$CG$27/(1+$CI$18)^CJ29 -> 0.11344813 | DC29: =$DB$3/(1+$CI$3)^CJ29 -> 26.971992 | DD29: =$DB$3/(1+$CI$4)^CJ29 -> 20.672142 | DE29: =$DB$3/(1+$CI$5)^CJ29 -> 15.884921 | DF29: =$DB$3/(1+$CI$6)^CJ29 -> 12.657752 | DG29: =$DB$3/(1+$CI$7)^CJ29 -> 12.237423 | DH29: =$DB$3/(1+$CI$8)^CJ29 -> 9.4510279 | DI29: =$DB$3/(1+$CI$9)^CJ29 -> 7.3169782 | DJ29: =$DB$3/(1+$CI$10)^CJ29 -> 6.2509469 | DK29: =$DB$3/(1+$CI$11)^CJ29 -> 4.4172169 | DL29: =$DB$3/(1+$CI$12)^CJ29 -> 3.4440915 | DM29: =$DB$3/(1+$CI$13)^CJ29 -> 2.6914581 | DN29: =$DB$3/(1+$CI$14)^CJ29 -> 2.1079956 | DO29: =$DB$3/(1+$CI$15)^CJ29 -> 1.65464 | DP29: =$DB$3/(1+$CI$16)^CJ29 -> 1.3015838 | DQ29: =$DB$3/(1+$CI$17)^CJ29 -> 1.0260278 | DR29: =$DB$3/(1+$CI$18)^CJ29 -> 0.81049144 | DU29: =$DT$3/(1+$CI$3)^CJ29 -> 29.930541 | DV29: =$DT$3/(1+$CI$4)^CJ29 -> 22.939663 | DW29: =$DT$3/(1+$CI$5)^CJ29 -> 17.627333 | DX29: =$DT$3/(1+$CI$6)^CJ29 -> 14.046176 | DY29: =$DT$3/(1+$CI$7)^CJ29 -> 13.579742 | DZ29: =$DT$3/(1+$CI$8)^CJ29 -> 10.487708 | EA29: =$DT$3/(1+$CI$9)^CJ29 -> 8.1195751 | EB29: =$DT$3/(1+$CI$10)^CJ29 -> 6.9366112 | EC29: =$DT$3/(1+$CI$11)^CJ29 -> 4.9017399 | ED29: =$DT$3/(1+$CI$12)^CJ29 -> 3.8218727 | EE29: =$DT$3/(1+$CI$13)^CJ29 -> 2.9866832 | EF29: =$DT$3/(1+$CI$14)^CJ29 -> 2.3392209 | EG29: =$DT$3/(1+$CI$15)^CJ29 -> 1.8361369 | EH29: =$DT$3/(1+$CI$16)^CJ29 -> 1.4443541 | EI29: =$DT$3/(1+$CI$17)^CJ29 -> 1.1385725 | EJ29: =$DT$3/(1+$CI$18)^CJ29 -> 0.89939398 | EM29: =$EL$3/(1+$CI$3)^CJ29 -> 23.852231 | EN29: =$EL$3/(1+$CI$4)^CJ29 -> 18.281063 | EO29: =$EL$3/(1+$CI$5)^CJ29 -> 14.047564 | EP29: =$EL$3/(1+$CI$6)^CJ29 -> 11.193671 | EQ29: =$EL$3/(1+$CI$7)^CJ29 -> 10.82196 | ER29: =$EL$3/(1+$CI$8)^CJ29 -> 8.3578586 | ES29: =$EL$3/(1+$CI$9)^CJ29 -> 6.4706474 | ET29: =$EL$3/(1+$CI$10)^CJ29 -> 5.5279204 | EU29: =$EL$3/(1+$CI$11)^CJ29 -> 3.9062919 | EV29: =$EL$3/(1+$CI$12)^CJ29 -> 3.0457247 | EW29: =$EL$3/(1+$CI$13)^CJ29 -> 2.380146 | EX29: =$EL$3/(1+$CI$14)^CJ29 -> 1.8641707 | EY29: =$EL$3/(1+$CI$15)^CJ29 -> 1.4632532 | EZ29: =$EL$3/(1+$CI$16)^CJ29 -> 1.1510339 | FA29: =$EL$3/(1+$CI$17)^CJ29 -> 0.90735055 | FB29: =$EL$3/(1+$CI$18)^CJ29 -> 0.71674456 | FE29: =$FD$3/(1+$CI$3)^CJ29 -> 16.908584 | FF29: =$FD$3/(1+$CI$4)^CJ29 -> 12.959245 | FG29: =$FD$3/(1+$CI$5)^CJ29 -> 9.9581639 | FH29: =$FD$3/(1+$CI$6)^CJ29 -> 7.9350704 | FI29: =$FD$3/(1+$CI$7)^CJ29 -> 7.6715687 | FJ29: =$FD$3/(1+$CI$8)^CJ29 -> 5.9247941 | FK29: =$FD$3/(1+$CI$9)^CJ29 -> 4.5869708 | FL29: =$FD$3/(1+$CI$10)^CJ29 -> 3.918682 | FM29: =$FD$3/(1+$CI$11)^CJ29 -> 2.7691274 | FN29: =$FD$3/(1+$CI$12)^CJ29 -> 2.1590808 | FO29: =$FD$3/(1+$CI$13)^CJ29 -> 1.6872593 | FP29: =$FD$3/(1+$CI$14)^CJ29 -> 1.3214901 | FQ29: =$FD$3/(1+$CI$15)^CJ29 -> 1.0372841 | FR29: =$FD$3/(1+$CI$16)^CJ29 -> 0.81595529 | FS29: =$FD$3/(1+$CI$17)^CJ29 -> 0.64321083 | FT29: =$FD$3/(1+$CI$18)^CJ29 -> 0.50809234 | FW29: =$FV$3/(1+$CI$3)^CJ29 -> 0.031105784 | FX29: =$FV$3/(1+$CI$4)^CJ29 -> 0.023840404 | FY29: =$FV$3/(1+$CI$5)^CJ29 -> 0.018319481 | FZ29: =$FV$3/(1+$CI$6)^CJ29 -> 0.014597708 | GA29: =$FV$3/(1+$CI$7)^CJ29 -> 0.014112959 | GB29: =$FV$3/(1+$CI$8)^CJ29 -> 0.010899515 | GC29: =$FV$3/(1+$CI$9)^CJ29 -> 0.0084383955 | GD29: =$FV$3/(1+$CI$10)^CJ29 -> 0.0072089818 | GE29: =$FV$3/(1+$CI$11)^CJ29 -> 0.00509421 | GF29: =$FV$3/(1+$CI$12)^CJ29 -> 0.0039719411 | GG29: =$FV$3/(1+$CI$13)^CJ29 -> 0.0031039573 | GH29: =$FV$3/(1+$CI$14)^CJ29 -> 0.0024310719 | GI29: =$FV$3/(1+$CI$15)^CJ29 -> 0.001908234 | GJ29: =$FV$3/(1+$CI$16)^CJ29 -> 0.0015010677 | GK29: =$FV$3/(1+$CI$17)^CJ29 -> 0.0011832793 | GL29: =$FV$3/(1+$CI$18)^CJ29 -> 0.00093470927
